Workbook

Sheet 云盘-原始
A1: 工号-新 | B1: 部门 | C1: 中心 | D1: 岗位 | E1: 姓名 | F1: 考核目标 | G1: 实际完成 | H1: 完成率 | I1: 权重 | J1: 目标得分 | K1: 总完成率 | L1: 总得分 | M1: 总奖金 | N1: 绩效基数 | O1: 奖金系数 | P1: 车补天数 | Q1: 车补 | R1: 备注 | S1: 排名 | T1: 排名系数 | U1: 奖金池总额 | V1: 奖金池绩效 | W1: 绩效奖金
A2: FD-071139 | B2: 线下渠道部 | D2: 督导 | E2: 王冬梅 | F2: 活动POS目标 500000 | G2: 1037582.8 | H2: 2.0751656 | I2: 0.35 | K2: 1.7077429 | L2: 1.5 | M2: 4050 | N2: 3000 | O2: 1.35 | P2: 24 | Q2: 384
B3: 线下渠道部 | D3: 督导 | F3: 个人pos目标 38000 | G3: 60521.51 | H3: 1.5926713 | I3: 0.35 | L3: 1.5
B4: 线下渠道部 | D4: 督导 | F4: 总部演讲考核 1 | G4: 1 | H4: 1 | I4: 0.1 | L4: 1
B5: 线下渠道部 | D5: 督导 | F5: 线下培训考核 5 | G5: 8.1 | H5: 1.62 | I5: 0.2 | L5: 1.5
A6: FD-074553 | B6: 线下渠道部 | D6: 督导 | E6: 王娜 | F6: 活动POS目标 500000 | G6: 851012 | H6: 1.702024 | I6: 0.35 | K6: 1.5428642 | L6: 1.5 | M6: 3000 | N6: 3000 | O6: 1 | P6: 27 | Q6: 432
B7: 线下渠道部 | D7: 督导 | F7: 个人pos目标 38000 | G7: 57234.06 | H7: 1.5061595 | I7: 0.35 | L7: 1.5
B8: 线下渠道部 | D8: 督导 | F8: 总部演讲考核 1 | G8: 1.5 | H8: 1.5 | I8: 0.1 | L8: 1.5
B9: 线下渠道部 | D9: 督导 | F9: 线下培训考核 5 | G9: 6.75 | H9: 1.35 | I9: 0.2 | L9: 1.2
A10: FD-078246 | B10: 线下渠道部 | D10: 督导 | E10: 张婷 | F10: 活动POS目标 500000 | G10: 760591.4 | H10: 1.5211828 | I10: 0.35 | K10: 1.4778811 | L10: 1.5 | M10: 3000 | N10: 3000 | O10: 1 | P10: 27 | Q10: 432
B11: 线下渠道部 | D11: 督导 | F11: 个人pos目标 38000 | G11: 60742.14 | H11: 1.5984774 | I11: 0.35 | L11: 1.5
B12: 线下渠道部 | D12: 督导 | F12: 总部演讲考核 1 | G12: 0.8 | H12: 0.8 | I12: 0.1 | L12: 0.8
B13: 线下渠道部 | D13: 督导 | F13: 线下培训考核 5 | G13: 7.65 | H13: 1.53 | I13: 0.2 | L13: 1.5
A14: 外包督导 | B14: 线下渠道部 | D14: 督导 | E14: 时美娟 | F14: 活动POS目标 500000 | G14: 853560.43 | H14: 1.7071209 | I14: 0.35 | K14: 1.5809081 | L14: 1.5 | M14: 2400 | N14: 3000 | O14: 0.8
B15: 线下渠道部 | D15: 督导 | F15: 个人pos目标 38000 | G15: 64428 | H15: 1.6954737 | I15: 0.35 | L15: 1.5
B16: 线下渠道部 | D16: 督导 | F16: 总部演讲考核 1 | G16: 1.2 | H16: 1.2 | I16: 0.1 | L16: 1.2
B17: 线下渠道部 | D17: 督导 | F17: 线下培训考核 5 | G17: 6.75 | H17: 1.35 | I17: 0.2 | L17: 1.2
A18: FD-077555 | B18: 线下渠道部 | D18: 督导 | E18: 王琳 | F18: 活动POS目标 500000 | G18: 844581.7 | H18: 1.6891634 | I18: 0.35 | K18: 1.5296934 | L18: 1.5 | M18: 4050 | N18: 3000 | O18: 1.35 | P18: 29 | Q18: 464
B19: 线下渠道部 | D19: 督导 | F19: 个人pos目标 38000 | G19: 58029.93 | H19: 1.5271034 | I19: 0.35 | L19: 1.5
B20: 线下渠道部 | D20: 督导 | F20: 总部演讲考核 1 | G20: 1 | H20: 1 | I20: 0.1 | L20: 1
B21: 线下渠道部 | D21: 督导 | F21: 线下培训考核 5 | G21: 7.6 | H21: 1.52 | I21: 0.2 | L21: 1.5
A22: 外包督导 | B22: 线下渠道部 | D22: 督导 | E22: 刘茜 | F22: 活动POS目标 500000 | G22: 833877.42 | H22: 1.6677548 | I22: 0.35 | K22: 1.4989692 | L22: 1.5 | M22: 1500 | N22: 3000 | O22: 0.5
B23: 线下渠道部 | D23: 督导 | F23: 个人pos目标 38000 | G23: 61587.69 | H23: 1.6207287 | I23: 0.35 | L23: 1.5
B24: 线下渠道部 | D24: 督导 | F24: 总部演讲考核 1 | G24: 0.5 | H24: 0.5 | I24: 0.1 | L24: 0.5
B25: 线下渠道部 | D25: 督导 | F25: 线下培训考核 5 | G25: 7.45 | H25: 1.49 | I25: 0.2 | L25: 1.2
A26: FD-078109 | B26: 线下渠道部 | E26: 许元元 | Q26: 460
A27: FD-070643 | B27: 线下渠道部 | E27: 罗静文 | Q27: 500
A28: FD-078387 | B28: 线下渠道部 | E28: 李宏庆 | Q28: 420
A29: FD-076847 | B29: 线下渠道部 | E29: 蒋冰清 | Q29: 300
A30: FD-078748 | B30: 线下渠道部 | E30: 杨敏 | Q30: 500
A31: FD-070181 | B31: 线下渠道部 | E31: 梁倩雯 | Q31: 360
A32: FD-079435 | B32: 线下渠道部 | E32: 热夏提·古尔班江 | Q32: 460
A33: FD-070780 | B33: 线下渠道部 | E33: 黄策 | Q33: 380
A34: FD-074038 | B34: 线下渠道部 | E34: 黄慧琳 | Q34: 440
A35: FD-072418 | B35: 线下渠道部 | E35: 马诗瑾 | Q35: 340
A36: FD-076987 | B36: 线下渠道部 | E36: 孙海诺 | Q36: 340
A37: FD-075526 | B37: 线下渠道部 | E37: 夏星泽 | Q37: 576
... A39: FD-075978 | B39: 线下渠道部 | E39: 赵海宝 | Q39: 200
A40: FD-070915 | B40: 线下渠道部 | E40: 吴雪玲 | M40: 1800 | N40: 4000 | O40: 0.3 | R40: 当月绩效3600，5月6月绩效调整额-1800，计算后为1800
B41: 产品供应部 | D41: 主管 | E41: 李炜瑶 | F41: 货品降本基本必达目标 | G41: 7月目标69.7万 实际达成148万 | H41: 1 | I41: 0.5 | J41: 0.5 | K41: 1.2 | L41: 1.2 | M41: 5400 | N41: 5000 | S41: 1 | T41: 1 | U41: 1000 | V41: 400 | W41: 5400
B42: 产品供应部 | F42: 货品成本挑战目标 | G42: 7月目标13万 实际达成78 | H42: 1.5 | I42: 0.4 | J42: 0.6
B43: 产品供应部 | F43: 关键降本项目完成率指标 | H43: 1 | I43: 0.1 | J43: 0.1
B44: 产品供应部 | D44: 主管 | E44: 杨尚儒 | F44: 负评指标： WIS隐形水润面膜4.0：7.30前完成功效外检报告 赫系柔感洗发水2.0：7.31出货 KONO 控油奢护洗发水配方升级：7.20金标新设计打样完成 赫系赋活发膜3.0：7.30出货 | G44: 隐形水润4.0:7.22已完成外检功效报告 赫系柔感洗发水：7.25已出货 KONO控油奢护洗发水配方升级：由于设计确版逾期，7.27下推打样，预计8.10打样完成。 赫系赋活发膜3.0：7.20已出货。 | H44: 0.75 | I44: 0.1 | J44: 0.075 | K44: 1.013 | L44: 1.01 | M44: 5000 | N44: 5000 | S44: 6 | T44: 6 | U44: 1000 | W44: 5000
B45: 产品供应部 | F45: 成本控制指标:打样费<3.9万元 | G45: 实际打样费31570元，完成率1.19 | H45: 1.19 | I45: 0.2 | J45: 0.238
B46: 产品供应部 | F46: WIS好评卡：预计7.3出货 赫系头皮紧致焕活精华液：预计7.5出货 KONO旅行套（香氛沐浴露版）预计7.20出货 KONO卡厘控油蓬松洗发水（仲夏之柚香氛限定）50g、8g规格：预计7.20出货 KONO 卡厘控油蓬松洗发水2.0：预计7.30出货 赫系赋活发膜3.0，预计7.30出货 赫系柔感洗发水2.0，预计7.31出 | G46: WIS好评卡：预计7.3到仓，7.3已到仓 赫系头皮紧致焕活精华液：预计7.5出货，提前至7.3到仓 KONO旅行套（香氛沐浴露版）预计7.20出货，7.20已出货 KONO卡厘控油蓬松洗发水（仲夏之柚香氛限定）50g、8g规格：预计7.20出货，提前至7.15出货。 KONO 卡厘控油蓬松洗发水2.0：预计7.30出货，已提前至7.20出货 赫系赋活发膜3.0，预计7.30出货，预计提前至7.20出货，7.20已出货 赫系柔感洗发水2.0，预计7.31出货，预计提前至7.25出货。 | H46: 1 | I46: 0.7 | J46: 0.7
B47: 产品供应部 | E47: 陈林文 | F47: 计划准确率：83% | G47: 0.8355 | H47: 1 | I47: 0.2 | J47: 0.2 | K47: 1.0206 | L47: 1.02 | M47: 5100 | N47: 5000 | S47: 5 | T47: 5 | U47: 1000 | V47: 100 | W47: 5100
B48: 产品供应部 | F48: 总库存目标3840.9万 | G48: 3745万 | H48: 1 | I48: 0.2 | J48: 0.2
B49: 产品供应部 | F49: 生产订单履约目标95% | G49: 0.9722 | H49: 1 | I49: 0.2 | J49: 0.2
B50: 产品供应部 | F50: 物料报废控制在5万元内 | G50: 0 | H50: 1.5 | I50: 0.2 | J50: 0.3
B51: 产品供应部 | F51: 生产损耗控制在10万元内 | G51: 7.39万元（已确定） | H51: 1.35 | I51: 0.2 | J51: 0.271
B52: 产品供应部 | F52: 成品缺货项 | G52: 缺货扣分0.15 | J52: -0.15
B53: 产品供应部 | E53: 朱丹萍 | F53: 降本项目目标达成率（目标37.7万） | G53: 98.68万（已确定） | H53: 1.4 | I53: 0.5 | J53: 0.7 | K53: 1.2 | L53: 1.2 | M53: 5400 | N53: 5000 | S53: 1 | T53: 1 | U53: 1000 | V53: 400 | W53: 5400
B54: 产品供应部 | F54: 协助其他中心公司各个部门的需求按时完成率90% | G54: 实际按时完成率为95.83% | H54: 1 | I54: 0.4 | J54: 0.4
B55: 产品供应部 | F55: 市场行情监控 | G55: 平均分4.56 | H55: 1 | I55: 0.1 | J55: 0.1
B56: 产品供应部 | E56: 郑烁纯 | F56: 供应商梯队优质率99% | G56: 7月份100% | H56: 1 | I56: 0.25 | J56: 0.25 | K56: 1.05 | L56: 1.05 | M56: 2100 | N56: 2000 | S56: 4 | T56: 4 | U56: 1000 | V56: 100 | W56: 2100
B57: 产品供应部 | F57: 质量赔付月均≤3w | G57: 1177.92元 | H57: 1 | I57: 0.15 | J57: 0.15
B58: 产品供应部 | F58: 产品合格率98% | G58: 0.9983 | H58: 1 | I58: 0.3 | J58: 0.3
B59: 产品供应部 | F59: 质量报废≤3w | G59: 0 | H59: 1 | I59: 0.1 | J59: 0.1
B60: 产品供应部 | F60: 质量报废=0 | G60: 0 | H60: 1.5 | I60: 0.1 | J60: 0.15
B61: 产品供应部 | F61: 产品供应部合规达成率 | G61: 本月完成Q3内审及整改 | H61: 1 | I61: 0.1 | J61: 0.1
B62: 产品供应部 | E62: 吴永星 | F62: 物流降本挑战目标达成率指标 | G62: 目标：105.7万 结果：172.8万 | H62: 1.5 | I62: 0.4 | J62: 0.6 | K62: 1.187 | L62: 1.19 | M62: 5200 | N62: 5000 | S62: 2 | T62: 2 | U62: 1000 | V62: 200 | W62: 5200
B63: 产品供应部 | F63: 物流降本基础目标 | G63: 目标：82.2万 结果：172.8万 | H63: 1 | I63: 0.4 | J63: 0.4
B64: 产品供应部 | F64: 物流履约 | G64: 抖店不达标1，天猫不达标2，其余20达标 | H64: 0.87 | I64: 0.1 | J64: 0.09
B65: 产品供应部 | F65: 关键工作指标 | G65: 库准99.97%，资产负债表正常；无压单 | H65: 1 | I65: 0.1 | J65: 0.1
B66: 产品供应部 | E66: 黄晓莲 | F66: 抖音体验分：可麦/IRY目标80分，其他品牌90分 | G66: 目标90分 实际92分 | H66: 1 | I66: 0.55 | J66: 0.55 | K66: 1.099 | L66: 1.1 | M66: 2200 | N66: 2000 | S66: 3 | T66: 3 | U66: 1000 | V66: 200 | W66: 2200
B67: 产品供应部 | F67: 天猫、快手、视频号服务分目标4.7分 | G67: 体验分目标4.7分 | H67: 1 | I67: 0.15 | J67: 0.15
B68: 产品供应部 | F68: 2026年1月份36人，目标节省人力6人，减至30人 | G68: 目标6 人 实际8人 | H68: 1.33 | I68: 0.3 | J68: 0.4
B69: 产品供应部 | E69: 谢昊 | F69: 降本指标：6.3万，实际达成：7.87w元，实际达成率125% | G69: 78781（已确定） | H69: 1.25 | I69: 0.4 | J69: 0.5 | K69: 1.1 | L69: 1.1 | M69: 5200 | N69: 5000 | S69: 3 | T69: 3 | U69: 1000 | V69: 200 | W69: 5200
B70: 产品供应部 | F70: 安全生产 | G70: 0生产事故 | H70: 1 | I70: 0.1 | J70: 0.1
B71: 产品供应部 | F71: 库存准确率：差异件数<3500件 | G71: 3309件 | H71: 1 | I71: 0.15 | J71: 0.15
B72: 产品供应部 | F72: 发货指标：2C错漏发 | G72: 2C错漏发率99.999%（截至 7月31，C端共计1467934单，错漏发12单） | H72: 1 | I72: 0.1 | J72: 0.1
B73: 产品供应部 | F73: 发货指标：压单情况 | G73: 无压单 | H73: 1 | I73: 0.15 | J73: 0.15
B74: 产品供应部 | F74: 发货指标：2B履约率100% | G74: 履约率100% | H74: 1 | I74: 0.1 | J74: 0.1
B75: 产品供应部 | E75: 王誉炫 | F75: 包材订单履约率97% | G75: 0.987 | H75: 1 | I75: 0.35 | J75: 0.35 | K75: 0.8 | L75: 0.8 | M75: 4000 | N75: 4000 | S75: 7 | T75: 7 | U75: 1000 | W75: 4000
B76: 产品供应部 | F76: 原料订单履约率99% | G76: 0.994 | H76: 1 | I76: 0.35 | J76: 0.35
B77: 产品供应部 | F77: 物料报废金额5万 | G77: 99960 | H77: 0 | I77: 0.2 | J77: 0
B78: 产品供应部 | F78: 关键任务完成率 | G78: 1.积压包材消耗 2.积压原料消耗 | H78: 1 | I78: 0.1 | J78: 0.1
B79: 产品供应部 | E79: 陈远连 | F79: 降本目标20.9万 | G79: 23.6万 | H79: 1.13 | I79: 0.45 | J79: 0.50813397 | K79: 1.0581 | L79: 1.06 | M79: 2570.61 | N79: 0.51412298 | S79: 1 | T79: 1 | U79: 5000 | W79: 2570.61
B80: 产品供应部 | F80: 订单履约率目标95% | G80: 0.9716 | H80: 1 | I80: 0.25 | J80: 0.25
B81: 产品供应部 | F81: 生产损耗目标7.83万 | G81: 6.14万 | H81: 1 | I81: 0.2 | J81: 0.2
B82: 产品供应部 | F82: 工厂安全事故目标0起 | G82: 0起 | H82: 1 | I82: 0.05 | J82: 0.05
B83: 产品供应部 | F83: 工厂重大质量事故目标0起 | G83: 0起 | H83: 1 | I83: 0.05 | J83: 0.05
B84: 产品供应部 | E84: 杨雄贤 | F84: 质量合格率 | G84: 1 | H84: 1 | I84: 0.45 | J84: 0.45 | K84: 1 | L84: 1 | M84: 2429.39 | N84: 0.48587702 | S84: 2 | T84: 2 | U84: 5000
B85: 产品供应部 | F85: 库存准确率99.97% | G85: 1 | H85: 1 | I85: 0.35 | J85: 0.35
B86: 产品供应部 | F86: 工厂安全事故 | G86: 0起 | H86: 1 | I86: 0.1 | J86: 0.1
B87: 产品供应部 | F87: 工厂重大质量事故 | G87: 0起 | H87: 1 | I87: 0.1 | J87: 0.1

Sheet 云盘-原始（副本）
A1: 工号-新 | B1: 部门 | C1: 中心 | D1: 岗位 | E1: 姓名 | F1: 考核目标 | G1: 实际完成 | H1: 完成率 | I1: 权重 | J1: 目标得分 | K1: 总完成率 | L1: 总得分 | M1: 总奖金 | N1: 绩效基数 | O1: 奖金系数 | P1: 车补天数 | Q1: 车补 | R1: 备注 | S1: 排名 | T1: 排名系数 | U1: 奖金池总额 | V1: 奖金池绩效 | W1: 绩效奖金
A2: FD-071139 | B2: 线下渠道部 | D2: 督导 | E2: 王冬梅 | F2: 活动POS目标 500000 | G2: 1037582.8 | H2: 2.0751656 | I2: 0.35 | K2: 1.7077429 | L2: 1.5 | M2: 4050 | N2: 3000 | O2: 1.35 | P2: 24 | Q2: 384
B3: 线下渠道部 | D3: 督导 | F3: 个人pos目标 38000 | G3: 60521.51 | H3: 1.5926713 | I3: 0.35 | L3: 1.5
A4: FD-074553 | B4: 线下渠道部 | D4: 督导 | E4: 王娜 | F4: 活动POS目标 500000 | G4: 851012 | H4: 1.702024 | I4: 0.35 | K4: 1.5428642 | L4: 1.5 | M4: 3000 | N4: 3000 | O4: 1 | P4: 27 | Q4: 432
A5: FD-078246 | B5: 线下渠道部 | D5: 督导 | E5: 张婷 | F5: 活动POS目标 500000 | G5: 760591.4 | H5: 1.5211828 | I5: 0.35 | K5: 1.4778811 | L5: 1.5 | M5: 3000 | N5: 3000 | O5: 1 | P5: 27 | Q5: 432
A6: 外包督导 | B6: 线下渠道部 | D6: 督导 | E6: 时美娟 | F6: 活动POS目标 500000 | G6: 853560.43 | H6: 1.7071209 | I6: 0.35 | K6: 1.5809081 | L6: 1.5 | M6: 2400 | N6: 3000 | O6: 0.8
A7: FD-077555 | B7: 线下渠道部 | D7: 督导 | E7: 王琳 | F7: 活动POS目标 500000 | G7: 844581.7 | H7: 1.6891634 | I7: 0.35 | K7: 1.5296934 | L7: 1.5 | M7: 4050 | N7: 3000 | O7: 1.35 | P7: 29 | Q7: 464
A8: 外包督导 | B8: 线下渠道部 | D8: 督导 | E8: 刘茜 | F8: 活动POS目标 500000 | G8: 833877.42 | H8: 1.6677548 | I8: 0.35 | K8: 1.4989692 | L8: 1.5 | M8: 1500 | N8: 3000 | O8: 0.5
A9: FD-078109 | B9: 线下渠道部 | E9: 许元元 | Q9: 460
A10: FD-070643 | B10: 线下渠道部 | E10: 罗静文 | Q10: 500
A11: FD-078387 | B11: 线下渠道部 | E11: 李宏庆 | Q11: 420
A12: FD-076847 | B12: 线下渠道部 | E12: 蒋冰清 | Q12: 300
A13: FD-078748 | B13: 线下渠道部 | E13: 杨敏 | Q13: 500
A14: FD-070181 | B14: 线下渠道部 | E14: 梁倩雯 | Q14: 360
A15: FD-079435 | B15: 线下渠道部 | E15: 热夏提·古尔班江 | Q15: 460
A16: FD-070780 | B16: 线下渠道部 | E16: 黄策 | Q16: 380
A17: FD-074038 | B17: 线下渠道部 | E17: 黄慧琳 | Q17: 440
A18: FD-072418 | B18: 线下渠道部 | E18: 马诗瑾 | Q18: 340
A19: FD-076987 | B19: 线下渠道部 | E19: 孙海诺 | Q19: 340
A20: FD-075526 | B20: 线下渠道部 | E20: 夏星泽 | Q20: 576
... A22: FD-075978 | B22: 线下渠道部 | E22: 赵海宝 | Q22: 200
A23: FD-070915 | B23: 线下渠道部 | E23: 吴雪玲 | M23: 1800 | N23: 4000 | O23: 0.3 | R23: 当月绩效3600，5月6月绩效调整额-1800，计算后为1800
B24: 产品供应部 | D24: 主管 | E24: 李炜瑶 | F24: 货品降本基本必达目标 | G24: 7月目标69.7万 实际达成148万 | H24: 1 | I24: 0.5 | J24: 0.5 | K24: 1.2 | L24: 1.2 | M24: 5400 | N24: 5000 | S24: 1 | T24: 1 | U24: 1000 | V24: 400 | W24: 5400
B25: 产品供应部 | F25: 货品成本挑战目标 | G25: 7月目标13万 实际达成78 | H25: 1.5 | I25: 0.4 | J25: 0.6
B26: 产品供应部 | D26: 主管 | E26: 杨尚儒 | F26: 负评指标： WIS隐形水润面膜4.0：7.30前完成功效外检报告 赫系柔感洗发水2.0：7.31出货 KONO 控油奢护洗发水配方升级：7.20金标新设计打样完成 赫系赋活发膜3.0：7.30出货 | G26: 隐形水润4.0:7.22已完成外检功效报告 赫系柔感洗发水：7.25已出货 KONO控油奢护洗发水配方升级：由于设计确版逾期，7.27下推打样，预计8.10打样完成。 赫系赋活发膜3.0：7.20已出货。 | H26: 0.75 | I26: 0.1 | J26: 0.075 | K26: 1.013 | L26: 1.01 | M26: 5000 | N26: 5000 | S26: 6 | T26: 6 | U26: 1000 | W26: 5000
B27: 产品供应部 | E27: 陈林文 | F27: 计划准确率：83% | G27: 0.8355 | H27: 1 | I27: 0.2 | J27: 0.2 | K27: 1.0206 | L27: 1.02 | M27: 5100 | N27: 5000 | S27: 5 | T27: 5 | U27: 1000 | V27: 100 | W27: 5100
B28: 产品供应部 | E28: 朱丹萍 | F28: 降本项目目标达成率（目标37.7万） | G28: 98.68万（已确定） | H28: 1.4 | I28: 0.5 | J28: 0.7 | K28: 1.2 | L28: 1.2 | M28: 5400 | N28: 5000 | S28: 1 | T28: 1 | U28: 1000 | V28: 400 | W28: 5400
B29: 产品供应部 | E29: 郑烁纯 | F29: 供应商梯队优质率99% | G29: 7月份100% | H29: 1 | I29: 0.25 | J29: 0.25 | K29: 1.05 | L29: 1.05 | M29: 2100 | N29: 2000 | S29: 4 | T29: 4 | U29: 1000 | V29: 100 | W29: 2100
B30: 产品供应部 | E30: 吴永星 | F30: 物流降本挑战目标达成率指标 | G30: 目标：105.7万 结果：172.8万 | H30: 1.5 | I30: 0.4 | J30: 0.6 | K30: 1.187 | L30: 1.19 | M30: 5200 | N30: 5000 | S30: 2 | T30: 2 | U30: 1000 | V30: 200 | W30: 5200
B31: 产品供应部 | E31: 黄晓莲 | F31: 抖音体验分：可麦/IRY目标80分，其他品牌90分 | G31: 目标90分 实际92分 | H31: 1 | I31: 0.55 | J31: 0.55 | K31: 1.099 | L31: 1.1 | M31: 2200 | N31: 2000 | S31: 3 | T31: 3 | U31: 1000 | V31: 200 | W31: 2200
B32: 产品供应部 | E32: 谢昊 | F32: 降本指标：6.3万，实际达成：7.87w元，实际达成率125% | G32: 78781（已确定） | H32: 1.25 | I32: 0.4 | J32: 0.5 | K32: 1.1 | L32: 1.1 | M32: 5200 | N32: 5000 | S32: 3 | T32: 3 | U32: 1000 | V32: 200 | W32: 5200
B33: 产品供应部 | E33: 王誉炫 | F33: 包材订单履约率97% | G33: 0.987 | H33: 1 | I33: 0.35 | J33: 0.35 | K33: 0.8 | L33: 0.8 | M33: 4000 | N33: 4000 | S33: 7 | T33: 7 | U33: 1000 | W33: 4000
B34: 产品供应部 | E34: 陈远连 | F34: 降本目标20.9万 | G34: 23.6万 | H34: 1.13 | I34: 0.45 | J34: 0.50813397 | K34: 1.0581 | L34: 1.06 | M34: 2570.61 | N34: 0.51412298 | S34: 1 | T34: 1 | U34: 5000 | W34: 2570.61
B35: 产品供应部 | E35: 杨雄贤 | F35: 质量合格率 | G35: 1 | H35: 1 | I35: 0.45 | J35: 0.45 | K35: 1 | L35: 1 | M35: 2429.39 | N35: 0.48587702 | S35: 2 | T35: 2 | U35: 5000

Sheet 系统-原始
A1: 工号 | B1: 部门 | C1: 中心 | D1: 岗位 | E1: 姓名 | F1: 所属周期 | G1: 绩效方案名称 | H1: 任务名称 | I1: 任务内容 | J1: 目标 | K1: 实际完成数值 | L1: 完成情况说明 | M1: 单项完成率 | N1: 权重 | O1: 单项最终得分 | P1: 总完成率 | Q1: 总得分 | R1: 绩效奖金 | S1: 总奖金 | T1: 绩效基数 | U1: 子指标名称 | V1: 子指标说明 | W1: 子指标目标 | X1: 子指标完成量 | Y1: 子指标完成情况说明 | Z1: 子指标完成率 | AA1: 子指标权重 | AB1: 子指标得分
A2: FD-096937 | B2: 产品供应部-计划中心 | C2: 产品供应部-计划中心 | D2: 计划经理 | E2: 郭翠 | F2: 2026年07月 | G2: 产品供应部计划经理绩效考核方案 | H2: 生产履约目标完成率 | I2: 成品订单履约率完成95% | J2: 95 | K2: 0.971 | L2: 卓多姿35条目标，完成34条，1条未完成。34/35=97.1% | M2: 1.022 | N2: 0.5 | O2: 1 | P2: 0.911 | Q2: 0.91 | R2: 2821 | S2: 2821 | T2: 3100 | U2: 子指标名称 | V2: 子指标说明 | W2: 子指标目标 | X2: 子指标完成量 | Y2: 子指标完成情况说明 | Z2: 子指标完成率 | AA2: 子指标权重 | AB2: 子指标得分
A3: FD-096937 | B3: 产品供应部-计划中心 | C3: 产品供应部-计划中心 | D3: 计划经理 | E3: 郭翠 | F3: 2026年07月 | G3: 产品供应部计划经理绩效考核方案 | H3: 生产损耗 | I3: 损耗（按照中心降损目标比例完成） (损耗金额目标（除特殊高损耗订单外），其余订单损耗总金额≤在加工厂生产的总产值占所有加工厂生产总产值比重*15万元)） | K3: 1 | L3: 卓多姿目标损耗额39040元，卓多姿实际损耗额5617.1元 | M3: 1 | N3: 0.3 | O3: 1 | P3: 0.911 | Q3: 0.91 | R3: 2821 | S3: 2821 | T3: 3100 | U3: 子指标名称 | V3: 子指标说明 | W3: 子指标目标 | X3: 子指标完成量 | Y3: 子指标完成情况说明 | Z3: 子指标完成率 | AA3: 子指标权重 | AB3: 子指标得分
A4: FD-096937 | B4: 产品供应部-计划中心 | C4: 产品供应部-计划中心 | D4: 计划经理 | E4: 郭翠 | F4: 2026年07月 | G4: 产品供应部计划经理绩效考核方案 | H4: 部门关键项目完成率 | I4: 1、中心Skill项目推进 2、AI与计划中心文档 3、新品开发流程梳理，多维表格 | J4: 100 | K4: 0.5 | L4: 1、完成中心Skill项目推进（交流会、日常问题处理、Skill考核体系文档等）。2、完成AI与计划中心文档。3、完成新品开发流程多维表格。 | M4: 0.5 | N4: 0.2 | O4: 0.5 | P4: 0.911 | Q4: 0.91 | R4: 2821 | S4: 2821 | T4: 3100 | U4: 子指标名称 | V4: 子指标说明 | W4: 子指标目标 | X4: 子指标完成量 | Y4: 子指标完成情况说明 | Z4: 子指标完成率 | AA4: 子指标权重 | AB4: 子指标得分
A5: FD-098593 | B5: 产品供应部-计划中心 | C5: 产品供应部-计划中心 | D5: 计划经理 | E5: 王妙芳 | F5: 2026年07月 | G5: 产品供应部计划经理绩效考核方案 | H5: 计划准确率完成率 | I5: 准确率目标88% | J5: 0.88 | K5: 100%%%%% | L5: 准确率完成情况是88.91% | M5: 1 | N5: 0.3 | O5: 1 | P5: 0.95 | Q5: 0.95 | R5: 2968.9 | S5: 2968.9 | T5: 3000 | U5: 子指标名称 | V5: 子指标说明 | W5: 子指标目标 | X5: 子指标完成量 | Y5: 子指标完成情况说明 | Z5: 子指标完成率 | AA5: 子指标权重 | AB5: 子指标得分
A6: FD-098593 | B6: 产品供应部-计划中心 | C6: 产品供应部-计划中心 | D6: 计划经理 | E6: 王妙芳 | F6: 2026年07月 | G6: 产品供应部计划经理绩效考核方案 | H6: 总库存货值目标完成率 | I6: 总库存控制在179.5万内 | J6: 179.5万元 | K6: 167万元万元 | L6: 总库存控制在179.5万内 | M6: 1 | N6: 0.15 | O6: 1 | P6: 0.95 | Q6: 0.95 | R6: 2968.9 | S6: 2968.9 | T6: 3000 | U6: 子指标名称 | V6: 子指标说明 | W6: 子指标目标 | X6: 子指标完成量 | Y6: 子指标完成情况说明 | Z6: 子指标完成率 | AA6: 子指标权重 | AB6: 子指标得分
A7: FD-098593 | B7: 产品供应部-计划中心 | C7: 产品供应部-计划中心 | D7: 计划经理 | E7: 王妙芳 | F7: 2026年07月 | G7: 产品供应部计划经理绩效考核方案 | H7: 生产损耗 | I7: 按时准确提交 | K7: 100 | L7: 按时按量完成 | M7: 1 | N7: 0.05 | O7: 1 | P7: 0.95 | Q7: 0.95 | R7: 2968.9 | S7: 2968.9 | T7: 3000 | U7: 子指标名称 | V7: 子指标说明 | W7: 子指标目标 | X7: 子指标完成量 | Y7: 子指标完成情况说明 | Z7: 子指标完成率 | AA7: 子指标权重 | AB7: 子指标得分
A8: FD-098593 | B8: 产品供应部-计划中心 | C8: 产品供应部-计划中心 | D8: 计划经理 | E8: 王妙芳 | F8: 2026年07月 | G8: 产品供应部计划经理绩效考核方案 | H8: 部门关键项目完成率 | I8: 1、月度报废 2、IRY下单量协商 3、库存管理范围与方法课件输出 4、IRY赠品降本方案输出与沟通 | J8: 1 | K8: 88%% | L8: 1、月度报废--已完成，已输出报废文件 2、IRY下单量协商--已完成，已确认好下单需求数量 3、库存管理范围与方法课件输出--输出后驳回，重新补充内容 4、IRY赠品降本方案输出与沟通--已完成输出，品牌需求变更 | M8: 0.9 | N8: 0.5 | O8: 0.9 | P8: 0.95 | Q8: 0.95 | R8: 2968.9 | S8: 2968.9 | T8: 3000 | U8: 子指标名称 | V8: 子指标说明 | W8: 子指标目标 | X8: 子指标完成量 | Y8: 子指标完成情况说明 | Z8: 子指标完成率 | AA8: 子指标权重 | AB8: 子指标得分
A9: FD-091691 | B9: 产品供应部-计划中心 | C9: 产品供应部-计划中心 | D9: 计划经理 | E9: 吴开智 | F9: 2026年07月 | G9: 产品供应部计划经理绩效考核方案 | H9: 总库存货值目标完成率 | I9: 1750 | J9: 1750万 | K9: 1548万万万 | M9: 1.13 | N9: 0.3 | O9: 1.13 | P9: 1.0025 | Q9: 0.85 | R9: 2550 | S9: 2550 | T9: 3000 | U9: 子指标名称 | V9: 子指标说明 | W9: 子指标目标 | X9: 子指标完成量 | Y9: 子指标完成情况说明 | Z9: 子指标完成率 | AA9: 子指标权重 | AB9: 子指标得分
A10: FD-091691 | B10: 产品供应部-计划中心 | C10: 产品供应部-计划中心 | D10: 计划经理 | E10: 吴开智 | F10: 2026年07月 | G10: 产品供应部计划经理绩效考核方案 | H10: 部门关键项目完成率 | I10: 眼膜测试 | J10: 100 | K10: 0.95 | M10: 0.95 | N10: 0.4 | O10: 0.95 | P10: 1.0025 | Q10: 0.85 | R10: 2550 | S10: 2550 | T10: 3000 | U10: 子指标名称 | V10: 子指标说明 | W10: 子指标目标 | X10: 子指标完成量 | Y10: 子指标完成情况说明 | Z10: 子指标完成率 | AA10: 子指标权重 | AB10: 子指标得分
A11: FD-091691 | B11: 产品供应部-计划中心 | C11: 产品供应部-计划中心 | D11: 计划经理 | E11: 吴开智 | F11: 2026年07月 | G11: 产品供应部计划经理绩效考核方案 | H11: 计划准确率完成率 | I11: 计划准确率81% | J11: 81 | K11: 76.53 | M11: 0.945 | N11: 0.3 | O11: 0.95 | P11: 1.0025 | Q11: 0.85 | R11: 2550 | S11: 2550 | T11: 3000 | U11: 子指标名称 | V11: 子指标说明 | W11: 子指标目标 | X11: 子指标完成量 | Y11: 子指标完成情况说明 | Z11: 子指标完成率 | AA11: 子指标权重 | AB11: 子指标得分
A12: FD-085087 | B12: 产品供应部-计划中心 | C12: 产品供应部-计划中心 | D12: 计划经理 | E12: 张璐萍 | F12: 2026年07月 | G12: 产品供应部计划经理绩效考核方案 | H12: 部门关键项目完成率 | I12: 1、损耗率降低至1.5%以下-损耗分析输出。寻找降损点 2、KONO经典系列限定款去膜 -说服品牌方去膜 3、凡岛工厂与总部流程优化与执行-1. 第二模块的详细流程 4、加工厂基础跟产流程各类定义、解释和对应端口梳理（跟产名词、细节宝典）-完善第二板块，写第三板块 5、8g袋包降损-1. 推进袋包机购置方案 6、料体高损耗降损-1. 软管打样上级，测试损耗率 7、凡岛临期原料管理-1. 与工厂了解临期原料管理流程 2. 与供应端梳理新流程情况 3. 结合新流程重新共识 | J12: 1 | K12: 92%%% | L12: 1、损耗率降低至1.5%以下-损耗分析输出。寻找降损点（已完成） 2、KONO经典系列限定款去膜 -说服品牌方去膜 （已完成，项目暂停）3、凡岛工厂与总部流程优化与执行-1. 第二模块的详细流程 （已完成）4、加工厂基础跟产流程各类定义、解释和对应端口梳理（跟产名词、细节宝典）-完善第二板块，写第三板块 （已完成）5、8g袋包降损-1. 推进袋包机购置方案 （不推进购置，确认其他方案90%））6、料体高损耗降损-1. 软管打样上级，测试损耗率 （待测试结果，完成95%）7、凡岛临期原料管理-1. 与工厂了解临期原料管理流程 2. 与供应端梳理新流程情况 3. 结合新流程重新共识（待试运行，完成90%） | M12: 0.92 | N12: 0.2 | O12: 0.92 | P12: 0.9396 | Q12: 0.99 | R12: 3475.6 | S12: 3475.6 | T12: 3000 | U12: 子指标名称 | V12: 子指标说明 | W12: 子指标目标 | X12: 子指标完成量 | Y12: 子指标完成情况说明 | Z12: 子指标完成率 | AA12: 子指标权重 | AB12: 子指标得分
A13: FD-085087 | B13: 产品供应部-计划中心 | C13: 产品供应部-计划中心 | D13: 计划经理 | E13: 张璐萍 | F13: 2026年07月 | G13: 产品供应部计划经理绩效考核方案 | H13: 生产履约目标完成率 | I13: 凡岛工厂履约95% | J13: 0.95 | K13: 0.962 | L13: 7月目标共106条，，履约102条，未履约4条 工厂原因：均为乳化锅损坏导致乳化延后 【WIS乳糖酸多效面膜2.0_25g×10片】 【赫系轻盈洗发水3.0 450g】 【赫系水光护发素新配方450ml（短泵头）】 其中洗发水和护发素虽然减少计划因此生产数量达标，但是因设备问题较为严重，最后一条目标我没有算履约，由此提高对设备维护的重视 非工厂原因： 【WIS焕颜透嫩紧致淡纹精华液30ml】 原料逾期 | M13: 1 | N13: 0.5 | O13: 1 | P13: 0.9396 | Q13: 0.99 | R13: 3475.6 | S13: 3475.6 | T13: 3000 | U13: 子指标名称 | V13: 子指标说明 | W13: 子指标目标 | X13: 子指标完成量 | Y13: 子指标完成情况说明 | Z13: 子指标完成率 | AA13: 子指标权重 | AB13: 子指标得分
A14: FD-085087 | B14: 产品供应部-计划中心 | C14: 产品供应部-计划中心 | D14: 计划经理 | E14: 张璐萍 | F14: 2026年07月 | G14: 产品供应部计划经理绩效考核方案 | H14: 生产损耗 | I14: 负责加工厂损耗总金额/负责加工厂产值占本月排产生产的比重≤10万元 | K14: 6.14万元 | L14: 7月目标共106条，，履约102条，未履约4条 工厂原因：均为乳化锅损坏导致乳化延后 【WIS乳糖酸多效面膜2.0_25g×10片】 【赫系轻盈洗发水3.0 450g】 【赫系水光护发素新配方450ml（短泵头）】 其中洗发水和护发素虽然减少计划因此生产数量达标，但是因设备问题较为严重，最后一条目标我没有算履约，由此提高对设备维护的重视 非工厂原因： 【WIS焕颜透嫩紧致淡纹精华液30ml】 原料逾期 | M14: 0.852 | N14: 0.3 | O14: 0.852 | P14: 0.9396 | Q14: 0.99 | R14: 3475.6 | S14: 3475.6 | T14: 3000 | U14: 子指标名称 | V14: 子指标说明 | W14: 子指标目标 | X14: 子指标完成量 | Y14: 子指标完成情况说明 | Z14: 子指标完成率 | AA14: 子指标权重 | AB14: 子指标得分
A15: FD-094730 | B15: 产品供应部-计划中心 | C15: 产品供应部-计划中心 | D15: 计划经理 | E15: 魏振涛 | F15: 2026年07月 | G15: 产品供应部计划经理绩效考核方案 | H15: 部门关键项目完成率 | I15: 1、TCO落地计算 2、找到1-1.5、1.5-2以及物料稳定出库方案 | J15: 2条 | K15: 95%条 | L15: TCO完成，效期出库只有物料还无出库方案，新增返工费用计算完成 | M15: 0.95 | N15: 0.4 | O15: 0.95 | P15: 0.905 | Q15: 0.91 | R15: 2730 | S15: 2730 | T15: 3000 | U15: 子指标名称 | V15: 子指标说明 | W15: 子指标目标 | X15: 子指标完成量 | Y15: 子指标完成情况说明 | Z15: 子指标完成率 | AA15: 子指标权重 | AB15: 子指标得分
A16: FD-094730 | B16: 产品供应部-计划中心 | C16: 产品供应部-计划中心 | D16: 计划经理 | E16: 魏振涛 | F16: 2026年07月 | G16: 产品供应部计划经理绩效考核方案 | H16: 总库存货值目标完成率 | I16: 库存水位 | J16: 851万 | K16: 960万 | L16: 30号当天库存960万，完成率89% | M16: 0.89 | N16: 0.3 | O16: 0.89 | P16: 0.905 | Q16: 0.91 | R16: 2730 | S16: 2730 | T16: 3000 | U16: 子指标名称 | V16: 子指标说明 | W16: 子指标目标 | X16: 子指标完成量 | Y16: 子指标完成情况说明 | Z16: 子指标完成率 | AA16: 子指标权重 | AB16: 子指标得分
A17: FD-094730 | B17: 产品供应部-计划中心 | C17: 产品供应部-计划中心 | D17: 计划经理 | E17: 魏振涛 | F17: 2026年07月 | G17: 产品供应部计划经理绩效考核方案 | H17: 计划准确率完成率 | I17: 预测准确率82% | J17: 0.82 | K17: 0.705 | L17: 准确率70.5，换算完成率85% | M17: 0.86 | N17: 0.3 | O17: 0.86 | P17: 0.905 | Q17: 0.91 | R17: 2730 | S17: 2730 | T17: 3000 | U17: 子指标名称 | V17: 子指标说明 | W17: 子指标目标 | X17: 子指标完成量 | Y17: 子指标完成情况说明 | Z17: 子指标完成率 | AA17: 子指标权重 | AB17: 子指标得分
A18: FD-177153 | B18: 产品供应部-计划中心 | C18: 产品供应部-计划中心 | D18: 计划经理 | E18: 马猷安 | F18: 2026年07月 | G18: 产品供应部计划经理绩效考核方案 | H18: 部门关键项目完成率 | I18: 1. 数据上金蝶 2. 加工厂库位管理 3. 生产端包材优化 4. 杜明、郭翠带教 | J18: 1 | K18: 85%% | L18: 包材成本优化板块 没有深入学习和拓展 | M18: 0.85 | N18: 0.6 | O18: 0.85 | P18: 0.972 | Q18: 0.98 | R18: 3058.9 | S18: 3058.9 | T18: 3000 | U18: 子指标名称 | V18: 子指标说明 | W18: 子指标目标 | X18: 子指标完成量 | Y18: 子指标完成情况说明 | Z18: 子指标完成率 | AA18: 子指标权重 | AB18: 子指标得分
A19: FD-177153 | B19: 产品供应部-计划中心 | C19: 产品供应部-计划中心 | D19: 计划经理 | E19: 马猷安 | F19: 2026年07月 | G19: 产品供应部计划经理绩效考核方案 | H19: 生产损耗 | I19: 梦莎、美汇做货 | K19: 2119 | L19: 总目标金额5720， 实际损耗金额2119 | M19: 1.62 | N19: 0.1 | O19: 1.5 | P19: 0.972 | Q19: 0.98 | R19: 3058.9 | S19: 3058.9 | T19: 3000 | U19: 子指标名称 | V19: 子指标说明 | W19: 子指标目标 | X19: 子指标完成量 | Y19: 子指标完成情况说明 | Z19: 子指标完成率 | AA19: 子指标权重 | AB19: 子指标得分
A20: FD-177153 | B20: 产品供应部-计划中心 | C20: 产品供应部-计划中心 | D20: 计划经理 | E20: 马猷安 | F20: 2026年07月 | G20: 产品供应部计划经理绩效考核方案 | H20: 生产履约目标完成率 | I20: 梦莎、美汇做货 | J20: 1 | K20: 1 | L20: 总目标金额5720， 实际损耗金额2119 | M20: 1 | N20: 0.3 | O20: 1 | P20: 0.972 | Q20: 0.98 | R20: 3058.9 | S20: 3058.9 | T20: 3000 | U20: 子指标名称 | V20: 子指标说明 | W20: 子指标目标 | X20: 子指标完成量 | Y20: 子指标完成情况说明 | Z20: 子指标完成率 | AA20: 子指标权重 | AB20: 子指标得分
A21: FD-097678 | B21: 产品供应部-计划中心 | C21: 产品供应部-计划中心 | D21: 管培生 | E21: 钟恩宝 | F21: 2026年07月 | G21: 产品供应部计划经理绩效考核方案 | H21: 部门关键项目完成率 | I21: 关键项目 | J21: 1 | K21: 90%%% | L21: 总目标金额5720， 实际损耗金额2119 | M21: 0.9 | N21: 0.4 | O21: 0.9 | P21: 1.00971 | Q21: 1.01 | R21: 5525.6 | S21: 5525.6 | T21: 5000 | U21: 子指标名称 | V21: 子指标说明 | W21: 子指标目标 | X21: 子指标完成量 | Y21: 子指标完成情况说明 | Z21: 子指标完成率 | AA21: 子指标权重 | AB21: 子指标得分
A22: FD-097678 | B22: 产品供应部-计划中心 | C22: 产品供应部-计划中心 | D22: 管培生 | E22: 钟恩宝 | F22: 2026年07月 | G22: 产品供应部计划经理绩效考核方案 | H22: 计划准确率完成率 | I22: 预测准确率 | J22: 0.9 | K22: 90.33%% | L22: 总目标金额5720， 实际损耗金额2119 | M22: 1.0037 | N22: 0.3 | O22: 1 | P22: 1.00971 | Q22: 1.01 | R22: 5525.6 | S22: 5525.6 | T22: 5000 | U22: 子指标名称 | V22: 子指标说明 | W22: 子指标目标 | X22: 子指标完成量 | Y22: 子指标完成情况说明 | Z22: 子指标完成率 | AA22: 子指标权重 | AB22: 子指标得分
A23: FD-097678 | B23: 产品供应部-计划中心 | C23: 产品供应部-计划中心 | D23: 管培生 | E23: 钟恩宝 | F23: 2026年07月 | G23: 产品供应部计划经理绩效考核方案 | H23: 总库存货值目标完成率 | I23: 目标1150w | J23: 1150万元 | K23: 964万元万元万元 | L23: 总目标金额5720， 实际损耗金额2119 | M23: 1.162 | N23: 0.3 | O23: 1.162 | P23: 1.00971 | Q23: 1.01 | R23: 5525.6 | S23: 5525.6 | T23: 5000 | U23: 子指标名称 | V23: 子指标说明 | W23: 子指标目标 | X23: 子指标完成量 | Y23: 子指标完成情况说明 | Z23: 子指标完成率 | AA23: 子指标权重 | AB23: 子指标得分
A24: FD-092488 | B24: 产品供应部-计划中心 | C24: 产品供应部-计划中心 | D24: 管培生 | E24: 林杜明 | F24: 2026年07月 | G24: 产品供应部计划经理绩效考核方案 | H24: 生产履约目标完成率 | I24: 沪汇加工厂履约率 | J24: 1 | K24: 1 | L24: 沪汇7月份履约率100% | M24: 1 | N24: 0.3 | O24: 1 | P24: 0.89 | Q24: 0.91 | R24: 0 | S24: 0 | T24: 5000 | U24: 子指标名称 | V24: 子指标说明 | W24: 子指标目标 | X24: 子指标完成量 | Y24: 子指标完成情况说明 | Z24: 子指标完成率 | AA24: 子指标权重 | AB24: 子指标得分
A25: FD-092488 | B25: 产品供应部-计划中心 | C25: 产品供应部-计划中心 | D25: 管培生 | E25: 林杜明 | F25: 2026年07月 | G25: 产品供应部计划经理绩效考核方案 | H25: 生产损耗 | I25: 沪汇加工厂损耗率 | K25: 0.5 | L25: 沪汇7月份履约率100% | M25: 0.3 | N25: 0.1 | O25: 0.5 | P25: 0.89 | Q25: 0.91 | R25: 0 | S25: 0 | T25: 5000 | U25: 子指标名称 | V25: 子指标说明 | W25: 子指标目标 | X25: 子指标完成量 | Y25: 子指标完成情况说明 | Z25: 子指标完成率 | AA25: 子指标权重 | AB25: 子指标得分
A26: FD-092488 | B26: 产品供应部-计划中心 | C26: 产品供应部-计划中心 | D26: 管培生 | E26: 林杜明 | F26: 2026年07月 | G26: 产品供应部计划经理绩效考核方案 | H26: 部门关键项目完成率 | I26: 全链路成本计算 | J26: 1 | K26: 0.9 | L26: 沪汇7月份履约率100% | M26: 0.9 | N26: 0.2 | O26: 0.9 | P26: 0.89 | Q26: 0.91 | R26: 0 | S26: 0 | T26: 5000 | U26: 子指标名称 | V26: 子指标说明 | W26: 子指标目标 | X26: 子指标完成量 | Y26: 子指标完成情况说明 | Z26: 子指标完成率 | AA26: 子指标权重 | AB26: 子指标得分
A27: FD-092488 | B27: 产品供应部-计划中心 | C27: 产品供应部-计划中心 | D27: 管培生 | E27: 林杜明 | F27: 2026年07月 | G27: 产品供应部计划经理绩效考核方案 | H27: 部门关键项目完成率 | I27: 凡岛工厂排产优化 | J27: 1 | K27: 0.9 | L27: 沪汇7月份履约率100% | M27: 0.9 | N27: 0.2 | O27: 0.9 | P27: 0.89 | Q27: 0.91 | R27: 0 | S27: 0 | T27: 5000 | U27: 子指标名称 | V27: 子指标说明 | W27: 子指标目标 | X27: 子指标完成量 | Y27: 子指标完成情况说明 | Z27: 子指标完成率 | AA27: 子指标权重 | AB27: 子指标得分
A28: FD-092488 | B28: 产品供应部-计划中心 | C28: 产品供应部-计划中心 | D28: 管培生 | E28: 林杜明 | F28: 2026年07月 | G28: 产品供应部计划经理绩效考核方案 | H28: 部门关键项目完成率 | I28: workbuddy课程培训 | J28: 1 | K28: 1 | M28: 1 | N28: 0.2 | O28: 1 | P28: 0.89 | Q28: 0.91 | R28: 0 | S28: 0 | T28: 5000 | U28: 子指标名称 | V28: 子指标说明 | W28: 子指标目标 | X28: 子指标完成量 | Y28: 子指标完成情况说明 | Z28: 子指标完成率 | AA28: 子指标权重 | AB28: 子指标得分
A29: OD-002451 | B29: 人资行政部-组织发展中心 | C29: 人资行政部-组织发展中心 | D29: SSC助理 | E29: 陆颖 | F29: 2026年07月 | G29: 人资行政部-组织发展中心-SSC助理 | H29: 例行工作及时率 | I29: 按照对应节点完成各项工作 | J29: 1 | K29: 0 | L29: 已按照节点完成 | M29: 1 | N29: 0.5 | O29: 1 | P29: 1 | Q29: 1 | R29: 1500 | S29: 1500 | T29: 1500 | U29: 转正管理及时率 | V29: 6.30完成7、8月转正名单更新；7.10完成6月转正考勤更新；7.29完成6月转正结果更新；7.30完成8、9月转正名单更新 | X29: 子指标完成量 | Y29: 6.30更新7、8月预计转正名单，7.9更新转正考勤，7.29更新转正结果，7.30更新8、9月转正名单 | Z29: 1 | AA29: 0.2 | AB29: 1
A30: OD-002451 | B30: 人资行政部-组织发展中心 | C30: 人资行政部-组织发展中心 | D30: SSC助理 | E30: 陆颖 | F30: 2026年07月 | G30: 人资行政部-组织发展中心-SSC助理 | H30: 例行工作及时率 | I30: 按照对应节点完成各项工作 | J30: 1 | K30: 0 | L30: 已按照节点完成 | M30: 1 | N30: 0.5 | O30: 1 | P30: 1 | Q30: 1 | R30: 1500 | S30: 1500 | T30: 1500 | U30: 月度考勤报表提交及时率 | V30: 7月6号前完成6月月度考勤表（初版） | X30: 子指标完成量 | Y30: 7.6完成6月月度考勤表 | Z30: 1 | AA30: 0.4 | AB30: 1
A31: OD-002451 | B31: 人资行政部-组织发展中心 | C31: 人资行政部-组织发展中心 | D31: SSC助理 | E31: 陆颖 | F31: 2026年07月 | G31: 人资行政部-组织发展中心-SSC助理 | H31: 例行工作及时率 | I31: 按照对应节点完成各项工作 | J31: 1 | K31: 0 | L31: 已按照节点完成 | M31: 1 | N31: 0.5 | O31: 1 | P31: 1 | Q31: 1 | R31: 1500 | S31: 1500 | T31: 1500 | U31: 三方处理及时率 | V31: 1-3个工作日内，完成三方发起 | X31: 子指标完成量 | Y31: 7月处理两方/三方需求合计3人，已结束2人，流程中1人（等同学补充资料） | Z31: 1 | AA31: 0.2 | AB31: 1
A32: OD-002451 | B32: 人资行政部-组织发展中心 | C32: 人资行政部-组织发展中心 | D32: SSC助理 | E32: 陆颖 | F32: 2026年07月 | G32: 人资行政部-组织发展中心-SSC助理 | H32: 例行工作及时率 | I32: 按照对应节点完成各项工作 | J32: 1 | K32: 0 | L32: 已按照节点完成 | M32: 1 | N32: 0.5 | O32: 1 | P32: 1 | Q32: 1 | R32: 1500 | S32: 1500 | T32: 1500 | U32: 竞业处理及时率 | V32: 7.7完成7月竞业打款名单；7.25前完成7月竞业跟进总结 | X32: 子指标完成量 | Y32: 7.7确认7月竞业打款名单，7.24完成竞业跟进总结 | Z32: 1 | AA32: 0.1 | AB32: 1
A33: OD-002451 | B33: 人资行政部-组织发展中心 | C33: 人资行政部-组织发展中心 | D33: SSC助理 | E33: 陆颖 | F33: 2026年07月 | G33: 人资行政部-组织发展中心-SSC助理 | H33: 例行工作及时率 | I33: 按照对应节点完成各项工作 | J33: 1 | K33: 0 | L33: 已按照节点完成 | M33: 1 | N33: 0.5 | O33: 1 | P33: 1 | Q33: 1 | R33: 1500 | S33: 1500 | T33: 1500 | U33: 调动处理及时率 | V33: 1-2个工作日内，完成组织架构/岗位/负责人/HR经理维护更新 | X33: 子指标完成量 | Y33: 已按照节点完成 | Z33: 1 | AA33: 0.1 | AB33: 1
A34: OD-002451 | B34: 人资行政部-组织发展中心 | C34: 人资行政部-组织发展中心 | D34: SSC助理 | E34: 陆颖 | F34: 2026年07月 | G34: 人资行政部-组织发展中心-SSC助理 | H34: 例行工作准确率 | I34: 保证各项工作准确无误 | J34: 1 | K34: 0 | L34: 准确完成 | M34: 1 | N34: 0.5 | O34: 1 | P34: 1 | Q34: 1 | R34: 1500 | S34: 1500 | T34: 1500 | U34: 转正名单及结果更新准确率 | V34: 确保转正名单、考勤、结果准确 | X34: 准确完成 | Y34: 已按照节点完成 | Z34: 1 | AA34: 0.2 | AB34: 1
A35: OD-002451 | B35: 人资行政部-组织发展中心 | C35: 人资行政部-组织发展中心 | D35: SSC助理 | E35: 陆颖 | F35: 2026年07月 | G35: 人资行政部-组织发展中心-SSC助理 | H35: 例行工作准确率 | I35: 保证各项工作准确无误 | J35: 1 | K35: 0 | L35: 准确完成 | M35: 1 | N35: 0.5 | O35: 1 | P35: 1 | Q35: 1 | R35: 1500 | S35: 1500 | T35: 1500 | U35: 月度考勤报表准确率 | V35: 确保月度考勤表准确 | X35: 准确完成 | Y35: 已按照节点完成 | Z35: 1 | AA35: 0.4 | AB35: 1
A36: OD-002451 | B36: 人资行政部-组织发展中心 | C36: 人资行政部-组织发展中心 | D36: SSC助理 | E36: 陆颖 | F36: 2026年07月 | G36: 人资行政部-组织发展中心-SSC助理 | H36: 例行工作准确率 | I36: 保证各项工作准确无误 | J36: 1 | K36: 0 | L36: 准确完成 | M36: 1 | N36: 0.5 | O36: 1 | P36: 1 | Q36: 1 | R36: 1500 | S36: 1500 | T36: 1500 | U36: 三方处理准确率 | V36: 确保薪资、协议内容、时间等准确 | X36: 准确完成 | Y36: 已按照节点完成 | Z36: 1 | AA36: 0.2 | AB36: 1
A37: OD-002451 | B37: 人资行政部-组织发展中心 | C37: 人资行政部-组织发展中心 | D37: SSC助理 | E37: 陆颖 | F37: 2026年07月 | G37: 人资行政部-组织发展中心-SSC助理 | H37: 例行工作准确率 | I37: 保证各项工作准确无误 | J37: 1 | K37: 0 | L37: 准确完成 | M37: 1 | N37: 0.5 | O37: 1 | P37: 1 | Q37: 1 | R37: 1500 | S37: 1500 | T37: 1500 | U37: 竞业处理准确率 | V37: 确保竞业金额、名单、生效周期准确 | X37: 准确完成 | Y37: 已按照节点完成 | Z37: 1 | AA37: 0.1 | AB37: 1
A38: OD-002451 | B38: 人资行政部-组织发展中心 | C38: 人资行政部-组织发展中心 | D38: SSC助理 | E38: 陆颖 | F38: 2026年07月 | G38: 人资行政部-组织发展中心-SSC助理 | H38: 例行工作准确率 | I38: 保证各项工作准确无误 | J38: 1 | K38: 0 | L38: 准确完成 | M38: 1 | N38: 0.5 | O38: 1 | P38: 1 | Q38: 1 | R38: 1500 | S38: 1500 | T38: 1500 | U38: 工时更新准确率 | V38: 确认工时数据准确 | X38: 准确完成 | Y38: 已按照节点完成 | Z38: 1 | AA38: 0.1 | AB38: 1
A39: OD-000664 | B39: 人资行政部-组织发展中心 | C39: 人资行政部-组织发展中心 | D39: SSC助理 | E39: 宋月 | F39: 2026年07月 | G39: 人资行政部-组织发展中心-SSC助理 | H39: 例行工作及时率 | I39: 季度评级：跟进OA岛民上级提交 定计划文档提交率80% 7.13完成绩效数据整理 | J39: 1 | K39: 0 | L39: 季度评级：跟进OA岛民上级提交 定计划文档提交率80% 7.13完成绩效数据整理 7.10完成 | M39: 1.075 | N39: 0.5 | O39: 1.075 | P39: 1.0285 | Q39: 1.03 | R39: 2060 | S39: 2060 | T39: 2000 | U39: 绩效数据汇总分析完成率 | X39: 准确完成 | Y39: 7.10完成 | Z39: 1.2 | AA39: 0.6 | AB39: 1.2
A40: OD-000664 | B40: 人资行政部-组织发展中心 | C40: 人资行政部-组织发展中心 | D40: SSC助理 | E40: 宋月 | F40: 2026年07月 | G40: 人资行政部-组织发展中心-SSC助理 | H40: 例行工作及时率 | I40: 季度评级：跟进OA岛民上级提交 定计划文档提交率80% 7.13完成绩效数据整理 | J40: 1 | K40: 0 | L40: 季度评级：跟进OA岛民上级提交 定计划文档提交率80% 7.13完成绩效数据整理 7.10完成 | M40: 1.075 | N40: 0.5 | O40: 1.075 | P40: 1.0285 | Q40: 1.03 | R40: 2060 | S40: 2060 | T40: 2000 | U40: 定计划审批提交率80% | X40: 准确完成 | Y40: 提交73% | Z40: 0.73 | AA40: 0.1 | AB40: 0.73
A41: OD-000664 | B41: 人资行政部-组织发展中心 | C41: 人资行政部-组织发展中心 | D41: SSC助理 | E41: 宋月 | F41: 2026年07月 | G41: 人资行政部-组织发展中心-SSC助理 | H41: 例行工作及时率 | I41: 季度评级：跟进OA岛民上级提交 定计划文档提交率80% 7.13完成绩效数据整理 | J41: 1 | K41: 0 | L41: 季度评级：跟进OA岛民上级提交 定计划文档提交率80% 7.13完成绩效数据整理 7.10完成 | M41: 1.075 | N41: 0.5 | O41: 1.075 | P41: 1.0285 | Q41: 1.03 | R41: 2060 | S41: 2060 | T41: 2000 | U41: 季度评定数据更新及时率 | X41: 准确完成 | Y41: 完成94% | Z41: 0.94 | AA41: 0.3 | AB41: 0.94
A42: OD-000664 | B42: 人资行政部-组织发展中心 | C42: 人资行政部-组织发展中心 | D42: SSC助理 | E42: 宋月 | F42: 2026年07月 | G42: 人资行政部-组织发展中心-SSC助理 | H42: 例行工作准确率 | I42: 绩效数据更新汇总 背调 季度评级 | J42: 1 | K42: 0 | L42: 季度评级：跟进OA岛民上级提交 定计划文档提交率80% 7.13完成绩效数据整理 7.10完成 | M42: 0.982 | N42: 0.5 | O42: 0.982 | P42: 1.0285 | Q42: 1.03 | R42: 2060 | S42: 2060 | T42: 2000 | U42: 绩效数据更新准确率 | X42: 100 | Y42: 完成94% | Z42: 1 | AA42: 0.6 | AB42: 1
A43: OD-000664 | B43: 人资行政部-组织发展中心 | C43: 人资行政部-组织发展中心 | D43: SSC助理 | E43: 宋月 | F43: 2026年07月 | G43: 人资行政部-组织发展中心-SSC助理 | H43: 例行工作准确率 | I43: 绩效数据更新汇总 背调 季度评级 | J43: 1 | K43: 0 | L43: 季度评级：跟进OA岛民上级提交 定计划文档提交率80% 7.13完成绩效数据整理 7.10完成 | M43: 0.982 | N43: 0.5 | O43: 0.982 | P43: 1.0285 | Q43: 1.03 | R43: 2060 | S43: 2060 | T43: 2000 | U43: 背调 | X43: 100 | Y43: 完成94% | Z43: 1 | AA43: 0.1 | AB43: 1
A44: OD-000664 | B44: 人资行政部-组织发展中心 | C44: 人资行政部-组织发展中心 | D44: SSC助理 | E44: 宋月 | F44: 2026年07月 | G44: 人资行政部-组织发展中心-SSC助理 | H44: 例行工作准确率 | I44: 绩效数据更新汇总 背调 季度评级 | J44: 1 | K44: 0 | L44: 季度评级：跟进OA岛民上级提交 定计划文档提交率80% 7.13完成绩效数据整理 7.10完成 | M44: 0.982 | N44: 0.5 | O44: 0.982 | P44: 1.0285 | Q44: 1.03 | R44: 2060 | S44: 2060 | T44: 2000 | U44: 季度评级跟进 | X44: 100 | Y44: 完成94% | Z44: 0.94 | AA44: 0.3 | AB44: 0.94
A45: OD-008606 | B45: 人资行政部-组织发展中心 | C45: 人资行政部-组织发展中心 | D45: SSC助理 | E45: 吴瑶华 | F45: 2026年07月 | G45: 人资行政部-组织发展中心-SSC助理 | H45: 例行工作及时率 | I45: 1、离职流程完结率 2、三方处理及时率 3、社保公积金缴纳及时率 3、社保公积金补缴及时率 4、生育津贴处理及时率 5、工伤申报处理及时率 | J45: 1 | K45: 0 | L45: 及时完成 | M45: 1 | N45: 0.5 | O45: 1 | P45: 0.9375 | Q45: 0.94 | R45: 1410 | S45: 1410 | T45: 1500 | U45: 离职流程完结率 | V45: - 计算公式：离职流程完结及时率=离职流程完结数/当月离职总人数*100% 1. 离职流程准时完结数：账号注销日期为最后工作日结束后的三个工作日内 账号注销：需要业务部门确认工作交接、财务确认报销流程完结、行政确认固定资产交接完结、组发核对考勤完结，开具离职证明后注销 1. 当月离职总人数：含正式、试用期、实习期、兼职等所有人员，以【飞书审批-离职交接、实习结束交接申请】数据为准 | W45: 1 | X45: 100 | Y45: "6.29-6.30离职24人，7月离职145人，剔除7.30及之后25人，离职的离职完结3天内的达126/144人，占比87.5% 岛民离职进度跟进表-SSC专用 " | Z45: 0.875 | AA45: 0.3 | AB45: 1
A46: OD-008606 | B46: 人资行政部-组织发展中心 | C46: 人资行政部-组织发展中心 | D46: SSC助理 | E46: 吴瑶华 | F46: 2026年07月 | G46: 人资行政部-组织发展中心-SSC助理 | H46: 例行工作及时率 | I46: 1、离职流程完结率 2、三方处理及时率 3、社保公积金缴纳及时率 3、社保公积金补缴及时率 4、生育津贴处理及时率 5、工伤申报处理及时率 | J46: 1 | K46: 0 | L46: 及时完成 | M46: 1 | N46: 0.5 | O46: 1 | P46: 0.9375 | Q46: 0.94 | R46: 1410 | S46: 1410 | T46: 1500 | U46: 社保公积金缴纳及时率 | V46: 目标完成时间：每月25号 | W46: 1 | X46: 100 | Y46: "1.自有主体（80%）：7.24、7.27完成扣费 2.外区社保（20%）：7月账单按时打款" | Z46: 1 | AA46: 0.2 | AB46: 1
A47: OD-008606 | B47: 人资行政部-组织发展中心 | C47: 人资行政部-组织发展中心 | D47: SSC助理 | E47: 吴瑶华 | F47: 2026年07月 | G47: 人资行政部-组织发展中心-SSC助理 | H47: 例行工作及时率 | I47: 1、离职流程完结率 2、三方处理及时率 3、社保公积金缴纳及时率 3、社保公积金补缴及时率 4、生育津贴处理及时率 5、工伤申报处理及时率 | J47: 1 | K47: 0 | L47: 及时完成 | M47: 1 | N47: 0.5 | O47: 1 | P47: 0.9375 | Q47: 0.94 | R47: 1410 | S47: 1410 | T47: 1500 | U47: 社保公积金补缴及时率 | V47: 1.收到税局/公积金管理局电话或补缴函的次工作日内联系补缴人 2.收到社保补缴材料及个人费用支付转账/公积金核查通知书的的10个工作日内提交补缴材料 | W47: 1 | X47: 100 | Y47: 及时完成 | Z47: 1 | AA47: 0.1 | AB47: 1
A48: OD-008606 | B48: 人资行政部-组织发展中心 | C48: 人资行政部-组织发展中心 | D48: SSC助理 | E48: 吴瑶华 | F48: 2026年07月 | G48: 人资行政部-组织发展中心-SSC助理 | H48: 例行工作及时率 | I48: 1、离职流程完结率 2、三方处理及时率 3、社保公积金缴纳及时率 3、社保公积金补缴及时率 4、生育津贴处理及时率 5、工伤申报处理及时率 | J48: 1 | K48: 0 | L48: 及时完成 | M48: 1 | N48: 0.5 | O48: 1 | P48: 0.9375 | Q48: 0.94 | R48: 1410 | S48: 1410 | T48: 1500 | U48: 生育津贴处理及时率 | V48: 收到岛民申报要求5个工作日内完成申报材料提交v | W48: 1 | X48: 100 | Y48: 及时完成 | Z48: 1 | AA48: 0.1 | AB48: 1
A49: OD-008606 | B49: 人资行政部-组织发展中心 | C49: 人资行政部-组织发展中心 | D49: SSC助理 | E49: 吴瑶华 | F49: 2026年07月 | G49: 人资行政部-组织发展中心-SSC助理 | H49: 例行工作及时率 | I49: 1、离职流程完结率 2、三方处理及时率 3、社保公积金缴纳及时率 3、社保公积金补缴及时率 4、生育津贴处理及时率 5、工伤申报处理及时率 | J49: 1 | K49: 0 | L49: 及时完成 | M49: 1 | N49: 0.5 | O49: 1 | P49: 0.9375 | Q49: 0.94 | R49: 1410 | S49: 1410 | T49: 1500 | U49: 工伤申报处理及时率 | V49: 收到岛民工伤报备当日在社保局完成报备；收到岛民工伤报备后30个工作日内完成工伤申报材料提交 | W49: 1 | X49: 100 | Y49: 及时完成 | Z49: 1 | AA49: 0.2 | AB49: 1
A50: OD-008606 | B50: 人资行政部-组织发展中心 | C50: 人资行政部-组织发展中心 | D50: SSC助理 | E50: 吴瑶华 | F50: 2026年07月 | G50: 人资行政部-组织发展中心-SSC助理 | H50: 例行工作准确率 | I50: 1、入职薪资登记准确率 2、花名册及OA岛民档案信息准确率 3、社保公积金增减员名单准确率 4、社保公积金在册名单更新准确率 | J50: 1 | K50: 1 | L50: 及时完成 | M50: 0.875 | N50: 0.5 | O50: 0.875 | P50: 0.9375 | Q50: 0.94 | R50: 1410 | S50: 1410 | T50: 1500 | U50: 入职薪资登记准确率 | V50: 准确无误 | W50: 1 | X50: 1 | Y50: 无误 | Z50: 1 | AA50: 0.3 | AB50: 1
A51: OD-008606 | B51: 人资行政部-组织发展中心 | C51: 人资行政部-组织发展中心 | D51: SSC助理 | E51: 吴瑶华 | F51: 2026年07月 | G51: 人资行政部-组织发展中心-SSC助理 | H51: 例行工作准确率 | I51: 1、入职薪资登记准确率 2、花名册及OA岛民档案信息准确率 3、社保公积金增减员名单准确率 4、社保公积金在册名单更新准确率 | J51: 1 | K51: 1 | L51: 及时完成 | M51: 0.875 | N51: 0.5 | O51: 0.875 | P51: 0.9375 | Q51: 0.94 | R51: 1410 | S51: 1410 | T51: 1500 | U51: 花名册及OA岛民档案信息准确率 | V51: 准确无误 | W51: 1 | X51: 1 | Y51: 无误 | Z51: 1 | AA51: 0.25 | AB51: 1
A52: OD-008606 | B52: 人资行政部-组织发展中心 | C52: 人资行政部-组织发展中心 | D52: SSC助理 | E52: 吴瑶华 | F52: 2026年07月 | G52: 人资行政部-组织发展中心-SSC助理 | H52: 例行工作准确率 | I52: 1、入职薪资登记准确率 2、花名册及OA岛民档案信息准确率 3、社保公积金增减员名单准确率 4、社保公积金在册名单更新准确率 | J52: 1 | K52: 1 | L52: 及时完成 | M52: 0.875 | N52: 0.5 | O52: 0.875 | P52: 0.9375 | Q52: 0.94 | R52: 1410 | S52: 1410 | T52: 1500 | U52: 社保公积金增减员名单准确率 | V52: 准确无误 | W52: 1 | X52: 0.5 | Y52: "6人转社保，单工伤未及时减员 这6人属于6月二次增员操作的系统增员，同时6月共享盘在册转多维表格在册，导出时未正确筛选字段，导致未匹配到需要单工伤减员 解决：1.更新多维表格的同时做好excel在册，方便自己每月匹配增减员 2.当月社保在册整理完毕，再进行匹配完整的社保在册名单进行增减员单工伤" | Z52: 0.5 | AA52: 0.25 | AB52: 0.25
A53: OD-008606 | B53: 人资行政部-组织发展中心 | C53: 人资行政部-组织发展中心 | D53: SSC助理 | E53: 吴瑶华 | F53: 2026年07月 | G53: 人资行政部-组织发展中心-SSC助理 | H53: 例行工作准确率 | I53: 1、入职薪资登记准确率 2、花名册及OA岛民档案信息准确率 3、社保公积金增减员名单准确率 4、社保公积金在册名单更新准确率 | J53: 1 | K53: 1 | L53: 及时完成 | M53: 0.875 | N53: 0.5 | O53: 0.875 | P53: 0.9375 | Q53: 0.94 | R53: 1410 | S53: 1410 | T53: 1500 | U53: 社保公积金在册名单更新准确率 | V53: 准确无误 | W53: 1 | X53: 1 | Y53: 无误 | Z53: 1 | AA53: 0.2 | AB53: 1
A54: FD-155599 | B54: 人资行政部-组织发展中心 | C54: 人资行政部-组织发展中心 | D54: COE专家 | E54: 王雅丽 | F54: 2026年07月 | G54: 人资行政部-组织发展中心-COE专家、SSC专家202606 | H54: 价值创造类 | I54: 社保公积金年度调基方案 | K54: 已完成 | L54: 及时完成 | M54: 1 | N54: 0.5 | O54: 1 | P54: 1 | Q54: 1 | R54: 3386 | S54: 3386 | T54: 3000 | U54: 社保公积金年度调基方案 | X54: 已完成 | Y54: 无误 | Z54: 1 | AA54: 1 | AB54: 1
A55: FD-155599 | B55: 人资行政部-组织发展中心 | C55: 人资行政部-组织发展中心 | D55: COE专家 | E55: 王雅丽 | F55: 2026年07月 | G55: 人资行政部-组织发展中心-COE专家、SSC专家202606 | H55: 价值创造类 | I55: 2026年调薪方案 | K55: 已完成 | L55: 及时完成 | M55: 1 | N55: 0.5 | O55: 1 | P55: 1 | Q55: 1 | R55: 3386 | S55: 3386 | T55: 3000 | U55: 2026年调薪方案 | X55: 已完成 | Y55: 无误 | Z55: 1 | AA55: 1 | AB55: 1
A56: FD-156792 | B56: 人资行政部-组织发展中心 | C56: 人资行政部-组织发展中心 | D56: COE专家 | E56: 宫兆宜 | F56: 2026年07月 | G56: 人资行政部-组织发展中心-COE专家、SSC专家202606 | H56: 价值创造类 | I56: 绩效访谈的开展&分析报告的输出 | K56: 1 | L56: 完成方案的初版报告的生成（AI版本） | M56: 1 | N56: 0.7 | O56: 1 | P56: 1 | Q56: 1 | R56: 3386 | S56: 3386 | T56: 3000 | U56: 交付进度完成率 | X56: 1 | Y56: 无误 | Z56: 1 | AA56: 0.4 | AB56: 1
A57: FD-156792 | B57: 人资行政部-组织发展中心 | C57: 人资行政部-组织发展中心 | D57: COE专家 | E57: 宫兆宜 | F57: 2026年07月 | G57: 人资行政部-组织发展中心-COE专家、SSC专家202606 | H57: 价值创造类 | I57: 绩效访谈的开展&分析报告的输出 | K57: 1 | L57: 完成方案的初版报告的生成（AI版本） | M57: 1 | N57: 0.7 | O57: 1 | P57: 1 | Q57: 1 | R57: 3386 | S57: 3386 | T57: 3000 | U57: 交付质量完成率 | X57: 100 | Y57: 无误 | Z57: 1 | AA57: 0.6 | AB57: 1
A58: FD-156792 | B58: 人资行政部-组织发展中心 | C58: 人资行政部-组织发展中心 | D58: COE专家 | E58: 宫兆宜 | F58: 2026年07月 | G58: 人资行政部-组织发展中心-COE专家、SSC专家202606 | H58: 价值创造类 | I58: 完成绩效数据例行分析&绩效系统数据分析校准or识别规则输出 | K58: 1 | L58: 完成方案的初版报告的生成（AI版本） | M58: 1 | N58: 0.3 | O58: 1 | P58: 1 | Q58: 1 | R58: 3386 | S58: 3386 | T58: 3000 | U58: 交付进度完成率 | X58: 100 | Y58: 无误 | Z58: 1 | AA58: 0.4 | AB58: 1
A59: FD-156792 | B59: 人资行政部-组织发展中心 | C59: 人资行政部-组织发展中心 | D59: COE专家 | E59: 宫兆宜 | F59: 2026年07月 | G59: 人资行政部-组织发展中心-COE专家、SSC专家202606 | H59: 价值创造类 | I59: 完成绩效数据例行分析&绩效系统数据分析校准or识别规则输出 | K59: 1 | L59: 完成方案的初版报告的生成（AI版本） | M59: 1 | N59: 0.3 | O59: 1 | P59: 1 | Q59: 1 | R59: 3386 | S59: 3386 | T59: 3000 | U59: 交付质量完成率 | X59: 100 | Y59: 无误 | Z59: 1 | AA59: 0.6 | AB59: 1
A60: FD-154391 | B60: 人资行政部-组织发展中心 | C60: 人资行政部-组织发展中心 | D60: SSC专家 | E60: 胡涵冰 | F60: 2026年07月 | G60: 人资行政部-组织发展中心-COE专家、SSC专家202606 | H60: 合同签订及时率 | I60: 把控跟进合同及协议签订流程 | J60: 1 | K60: 0.7943 | L60: 实际合同签订及时率为79.43% | M60: 0.7943 | N60: 0.3 | O60: 0.6354 | P60: 0.85829 | Q60: 0.81 | R60: 2128 | S60: 2128 | T60: 2200 | U60: 交付质量完成率 | X60: 100 | Y60: 无误 | Z60: 1 | AA60: 0.6 | AB60: 1
A61: FD-154391 | B61: 人资行政部-组织发展中心 | C61: 人资行政部-组织发展中心 | D61: SSC专家 | E61: 胡涵冰 | F61: 2026年07月 | G61: 人资行政部-组织发展中心-COE专家、SSC专家202606 | H61: 员工关系审批及时率 | I61: 及时跟进员工关系处理 | J61: 1 | K61: 0.8 | L61: 实际员工关系审批及时率为80% | M61: 0.8 | N61: 0.4 | O61: 0.8 | P61: 0.85829 | Q61: 0.81 | R61: 2128 | S61: 2128 | T61: 2200 | U61: 交付质量完成率 | X61: 100 | Y61: 无误 | Z61: 1 | AA61: 0.6 | AB61: 1
A62: FD-154391 | B62: 人资行政部-组织发展中心 | C62: 人资行政部-组织发展中心 | D62: SSC专家 | E62: 胡涵冰 | F62: 2026年07月 | G62: 人资行政部-组织发展中心-COE专家、SSC专家202606 | H62: 关键工作完成率 | I62: 2026年7月已入职应届毕业生岛民转签劳动合同安排、员工关系类Skill开发 | J62: 1 | K62: 1 | L62: 已完成 | M62: 1 | N62: 0.3 | O62: 1 | P62: 0.85829 | Q62: 0.81 | R62: 2128 | S62: 2128 | T62: 2200 | U62: 交付质量完成率 | X62: 100 | Y62: 无误 | Z62: 1 | AA62: 0.6 | AB62: 1
A63: FD-155628 | B63: 人资行政部-组织发展中心 | C63: 人资行政部-组织发展中心 | D63: 管培生 | E63: 杨宁 | F63: 2026年07月 | G63: 人资行政部-组织发展中心-COE专家、SSC专家202606 | H63: 关键工作完成率 | I63: 人岗匹配Q3分析报告 + 优化方案 | J63: 100 | K63: 80 | L63: 人岗匹配优化方案3.0+人才评估体系思考2.0 | M63: 0.8 | N63: 0.6 | O63: 0.8 | P63: 0.8 | Q63: 0.8 | R63: 4300 | S63: 4300 | T63: 5000 | U63: 交付质量完成率 | X63: 100 | Y63: 无误 | Z63: 1 | AA63: 0.6 | AB63: 1
A64: FD-155628 | B64: 人资行政部-组织发展中心 | C64: 人资行政部-组织发展中心 | D64: 管培生 | E64: 杨宁 | F64: 2026年07月 | G64: 人资行政部-组织发展中心-COE专家、SSC专家202606 | H64: 关键工作完成率 | I64: 岗位文件管理机制 | J64: 100 | K64: 80 | L64: 岗位相关文件更新机制流程 | M64: 0.8 | N64: 0.1 | O64: 0.8 | P64: 0.8 | Q64: 0.8 | R64: 4300 | S64: 4300 | T64: 5000 | U64: 交付质量完成率 | X64: 100 | Y64: 无误 | Z64: 1 | AA64: 0.6 | AB64: 1
A65: FD-155628 | B65: 人资行政部-组织发展中心 | C65: 人资行政部-组织发展中心 | D65: 管培生 | E65: 杨宁 | F65: 2026年07月 | G65: 人资行政部-组织发展中心-COE专家、SSC专家202606 | H65: 关键工作完成率 | I65: 外包供应商过渡 | J65: 100 | K65: 80 | L65: 外包供应商招聘接入测试+小猎合同续签 | M65: 0.8 | N65: 0.3 | O65: 0.8 | P65: 0.8 | Q65: 0.8 | R65: 4300 | S65: 4300 | T65: 5000 | U65: 交付质量完成率 | X65: 100 | Y65: 无误 | Z65: 1 | AA65: 0.6 | AB65: 1
A66: FD-083986 | B66: 新品牌事业部-设计中心 | C66: 新品牌事业部-设计中心 | D66: 产品设计师 | E66: 罗亦晨 | F66: 2026年07月 | G66: 新品牌事业部-设计中心-产品组各岗位设计师月度绩效考核方案 | H66: 核心设计项目产出 | I66: 可麦纸箱设计升级3.0 设计定版，下推打样 | J66: 1 | K66: 80 | M66: 0.4 | N66: 0.4 | O66: 0.4 | P66: 0.67 | Q66: 1.07 | R66: 3200 | S66: 3200 | T66: 2800 | U66: 交付质量完成率 | X66: 100 | Y66: 无误 | Z66: 1 | AA66: 0.6 | AB66: 1
A67: FD-083986 | B67: 新品牌事业部-设计中心 | C67: 新品牌事业部-设计中心 | D67: 产品设计师 | E67: 罗亦晨 | F67: 2026年07月 | G67: 新品牌事业部-设计中心-产品组各岗位设计师月度绩效考核方案 | H67: 核心设计项目产出 | I67: 可麦400g设计升级3.0 设计通过总监 | J67: 1 | K67: 80 | M67: 1 | N67: 0.3 | O67: 1 | P67: 0.67 | Q67: 1.07 | R67: 3200 | S67: 3200 | T67: 2800 | U67: 交付质量完成率 | X67: 100 | Y67: 无误 | Z67: 1 | AA67: 0.6 | AB67: 1
A68: FD-083986 | B68: 新品牌事业部-设计中心 | C68: 新品牌事业部-设计中心 | D68: 产品设计师 | E68: 罗亦晨 | F68: 2026年07月 | G68: 新品牌事业部-设计中心-产品组各岗位设计师月度绩效考核方案 | H68: 核心设计项目产出 | I68: MVE气垫+彩盒设计（年轻时尚方向） 设计定版（通过总监），下推打样 | J68: 1 | K68: 80 | M68: 0.7 | N68: 0.3 | O68: 0.7 | P68: 0.67 | Q68: 1.07 | R68: 3200 | S68: 3200 | T68: 2800 | U68: 交付质量完成率 | X68: 100 | Y68: 无误 | Z68: 1 | AA68: 0.6 | AB68: 1
A69: FD-080197 | B69: 新品牌事业部-设计中心 | C69: 新品牌事业部-设计中心 | D69: 产品设计师 | E69: 邓力欣 | F69: 2026年07月 | G69: 新品牌事业部-设计中心-产品组各岗位设计师月度绩效考核方案 | H69: 核心设计项目产出 | I69: 可麦纸箱设计升级3.0 设计定版，下推打样 | J69: 100& | K69: 80 | M69: 1 | N69: 0.4 | O69: 1 | P69: 0.67 | Q69: 0.77 | R69: 2216 | S69: 2216 | T69: 2800 | U69: 交付质量完成率 | X69: 100 | Y69: 无误 | Z69: 1 | AA69: 0.6 | AB69: 1
A70: FD-080197 | B70: 新品牌事业部-设计中心 | C70: 新品牌事业部-设计中心 | D70: 产品设计师 | E70: 邓力欣 | F70: 2026年07月 | G70: 新品牌事业部-设计中心-产品组各岗位设计师月度绩效考核方案 | H70: 核心设计项目产出 | I70: 可麦400g设计升级3.0 设计通过总监 | J70: 1 | K70: 80 | M70: 0.2 | N70: 0.3 | O70: 0.2 | P70: 0.67 | Q70: 0.77 | R70: 2216 | S70: 2216 | T70: 2800 | U70: 交付质量完成率 | X70: 100 | Y70: 无误 | Z70: 1 | AA70: 0.6 | AB70: 1
A71: FD-080197 | B71: 新品牌事业部-设计中心 | C71: 新品牌事业部-设计中心 | D71: 产品设计师 | E71: 邓力欣 | F71: 2026年07月 | G71: 新品牌事业部-设计中心-产品组各岗位设计师月度绩效考核方案 | H71: 核心设计项目产出 | I71: MVE气垫+彩盒设计（年轻时尚方向） 设计定版（通过总监），下推打样 | J71: 1 | K71: 80 | M71: 0.7 | N71: 0.3 | O71: 0.7 | P71: 0.67 | Q71: 0.77 | R71: 2216 | S71: 2216 | T71: 2800 | U71: 交付质量完成率 | X71: 100 | Y71: 无误 | Z71: 1 | AA71: 0.6 | AB71: 1
A72: FD-088054 | B72: 新品牌事业部-设计中心 | C72: 新品牌事业部-设计中心 | D72: 产品设计师 | E72: 余楚薰 | F72: 2026年07月 | G72: 新品牌事业部-设计中心-产品组各岗位设计师月度绩效考核方案 | H72: 核心设计项目产出 | I72: 可麦纸箱设计升级3.0 设计定版，下推打样 | J72: 1 | K72: 80 | M72: 0.4 | N72: 0.4 | O72: 0.4 | P72: 0.58 | Q72: 0.68 | R72: 0 | S72: 0 | T72: 2800 | U72: 交付质量完成率 | X72: 100 | Y72: 无误 | Z72: 1 | AA72: 0.6 | AB72: 1
A73: FD-088054 | B73: 新品牌事业部-设计中心 | C73: 新品牌事业部-设计中心 | D73: 产品设计师 | E73: 余楚薰 | F73: 2026年07月 | G73: 新品牌事业部-设计中心-产品组各岗位设计师月度绩效考核方案 | H73: 核心设计项目产出 | I73: 可麦400g设计升级 3.0设计通过总监 | J73: 1 | K73: 80 | M73: 1 | N73: 0.3 | O73: 1 | P73: 0.58 | Q73: 0.68 | R73: 0 | S73: 0 | T73: 2800 | U73: 交付质量完成率 | X73: 100 | Y73: 无误 | Z73: 1 | AA73: 0.6 | AB73: 1
A74: FD-088054 | B74: 新品牌事业部-设计中心 | C74: 新品牌事业部-设计中心 | D74: 产品设计师 | E74: 余楚薰 | F74: 2026年07月 | G74: 新品牌事业部-设计中心-产品组各岗位设计师月度绩效考核方案 | H74: 日常产品工单完成率 | I74: MVE气垫+彩盒设计(年轻时尚方向)设计定版(通过总监)，下推打样 | J74: 1 | K74: 40%%% | M74: 0.4 | N74: 0.3 | O74: 0.4 | P74: 0.58 | Q74: 0.68 | R74: 0 | S74: 0 | T74: 2800 | U74: 交付质量完成率 | X74: 100 | Y74: 无误 | Z74: 1 | AA74: 0.6 | AB74: 1
A75: FD-085640 | B75: 新品牌事业部-设计中心 | C75: 新品牌事业部-设计中心 | D75: 首席平面设计师 | E75: 谢志达 | F75: 2026年07月 | G75: 新品牌事业部-设计中心-平面组各岗位设计师月度绩效考核方案 | H75: 核心设计项目产出 | I75: AI应用设计的项目流程优化方案-营销AI视频自动化 | J75: 1 | K75: 40%%% | L75: 1 | M75: 1 | N75: 0.3 | O75: 0.3 | P75: 0.7 | Q75: 0.75 | R75: 3810 | S75: 3810 | T75: 5000 | U75: 交付质量完成率 | X75: 100 | Y75: 无误 | Z75: 1 | AA75: 0.6 | AB75: 1
A76: FD-085640 | B76: 新品牌事业部-设计中心 | C76: 新品牌事业部-设计中心 | D76: 首席平面设计师 | E76: 谢志达 | F76: 2026年07月 | G76: 新品牌事业部-设计中心-平面组各岗位设计师月度绩效考核方案 | H76: 核心设计项目产出 | I76: 可麦400g设计升级 设计通过总监 | J76: 1 | K76: 40%%% | L76: 1 | M76: 0 | N76: 0.3 | O76: 0 | P76: 0.7 | Q76: 0.75 | R76: 3810 | S76: 3810 | T76: 5000 | U76: 交付质量完成率 | X76: 100 | Y76: 无误 | Z76: 1 | AA76: 0.6 | AB76: 1
A77: FD-085640 | B77: 新品牌事业部-设计中心 | C77: 新品牌事业部-设计中心 | D77: 首席平面设计师 | E77: 谢志达 | F77: 2026年07月 | G77: 新品牌事业部-设计中心-平面组各岗位设计师月度绩效考核方案 | H77: 日常平面工单完成率 | I77: 日常平面工单完成率 | J77: 1 | K77: 1 | L77: 1 | M77: 1 | N77: 0.4 | O77: 0.4 | P77: 0.7 | Q77: 0.75 | R77: 3810 | S77: 3810 | T77: 5000 | U77: 交付质量完成率 | X77: 100 | Y77: 无误 | Z77: 1 | AA77: 0.6 | AB77: 1
A78: FD-084584 | B78: 新品牌事业部-设计中心 | C78: 新品牌事业部-设计中心 | D78: 资深平面设计师 | E78: 张盛源 | F78: 2026年07月 | G78: 新品牌事业部-设计中心-平面组各岗位设计师月度绩效考核方案 | H78: 核心设计项目产出 | I78: 凡岛季度荣誉榜kv设计 | J78: 1 | K78: 完成荣誉榜KV*1+人物组合*3%%% | L78: 100%已完成 | M78: 1 | N78: 0.3 | O78: 1 | P78: 0.73 | Q78: 0.83 | R78: 2870 | S78: 2870 | T78: 3000 | U78: 交付质量完成率 | X78: 100 | Y78: 无误 | Z78: 1 | AA78: 0.6 | AB78: 1
A79: FD-084584 | B79: 新品牌事业部-设计中心 | C79: 新品牌事业部-设计中心 | D79: 资深平面设计师 | E79: 张盛源 | F79: 2026年07月 | G79: 新品牌事业部-设计中心-平面组各岗位设计师月度绩效考核方案 | H79: 核心设计项目产出 | I79: 可麦主品设计升级 | J79: 1 | K79: 完成荣誉榜KV*1+人物组合*3%%% | L79: 完成进度10% | M79: 0.1 | N79: 0.3 | O79: 0.1 | P79: 0.73 | Q79: 0.83 | R79: 2870 | S79: 2870 | T79: 3000 | U79: 交付质量完成率 | X79: 100 | Y79: 无误 | Z79: 1 | AA79: 0.6 | AB79: 1
A80: FD-084584 | B80: 新品牌事业部-设计中心 | C80: 新品牌事业部-设计中心 | D80: 资深平面设计师 | E80: 张盛源 | F80: 2026年07月 | G80: 新品牌事业部-设计中心-平面组各岗位设计师月度绩效考核方案 | H80: 日常平面工单完成率 | I80: 日常平面工单完成率 100%（含直播间、创意图等） | J80: 1 | K80: 1 | L80: 完成直播间、手卡、日常主图、动画等 | M80: 1 | N80: 0.4 | O80: 1 | P80: 0.73 | Q80: 0.83 | R80: 2870 | S80: 2870 | T80: 3000 | U80: 交付质量完成率 | X80: 100 | Y80: 无误 | Z80: 1 | AA80: 0.6 | AB80: 1
A81: FD-084304 | B81: 新品牌事业部-设计中心 | C81: 新品牌事业部-设计中心 | D81: 资深平面设计师 | E81: 苏秋英 | F81: 2026年07月 | G81: 新品牌事业部-设计中心-平面组各岗位设计师月度绩效考核方案 | H81: 日常平面工单完成率 | I81: IRY日常平面工单完成率 100% | J81: 1 | K81: 100%% | L81: 100 | M81: 1 | N81: 0.3 | O81: 1 | P81: 1 | Q81: 1 | R81: 3400 | S81: 3400 | T81: 3000 | U81: 交付质量完成率 | X81: 100 | Y81: 无误 | Z81: 1 | AA81: 0.6 | AB81: 1
A82: FD-084304 | B82: 新品牌事业部-设计中心 | C82: 新品牌事业部-设计中心 | D82: 资深平面设计师 | E82: 苏秋英 | F82: 2026年07月 | G82: 新品牌事业部-设计中心-平面组各岗位设计师月度绩效考核方案 | H82: 核心设计项目产出 | I82: 活动主图自动化套图-AI工作流 | J82: 1 | K82: 100%% | L82: 100 | M82: 1 | N82: 0.3 | O82: 1 | P82: 1 | Q82: 1 | R82: 3400 | S82: 3400 | T82: 3000 | U82: 交付质量完成率 | X82: 100 | Y82: 无误 | Z82: 1 | AA82: 0.6 | AB82: 1
A83: FD-084304 | B83: 新品牌事业部-设计中心 | C83: 新品牌事业部-设计中心 | D83: 资深平面设计师 | E83: 苏秋英 | F83: 2026年07月 | G83: 新品牌事业部-设计中心-平面组各岗位设计师月度绩效考核方案 | H83: 日常平面工单完成率 | I83: 7月活动+推文*4 | J83: 1 | K83: 100%% | L83: 100 | M83: 1 | N83: 0.4 | O83: 1 | P83: 1 | Q83: 1 | R83: 3400 | S83: 3400 | T83: 3000 | U83: 交付质量完成率 | X83: 100 | Y83: 无误 | Z83: 1 | AA83: 0.6 | AB83: 1
A84: FD-155034 | B84: 凡岛大学 | C84: 凡岛大学 | D84: 培训讲师 | E84: 蒋欣 | F84: 2026年07月 | G84: 凡岛大学-培训讲师绩效考核方案2606 | H84: 管理类培训-课程交付完成 | I84: 按计划完成管理课程开发100%(权重30%) | J84: 8门 | K84: 8门 | L84: 已完成8门课程的开发，并交付落地 | M84: 1 | N84: 0.3 | O84: 1 | P84: 1 | Q84: 1 | R84: 2000 | S84: 2000 | T84: 2000 | U84: 交付质量完成率 | X84: 100 | Y84: 无误 | Z84: 1 | AA84: 0.6 | AB84: 1
A85: FD-155034 | B85: 凡岛大学 | C85: 凡岛大学 | D85: 培训讲师 | E85: 蒋欣 | F85: 2026年07月 | G85: 凡岛大学-培训讲师绩效考核方案2606 | H85: 管理类培训-优质授课 | I85: 优秀授课率100%(权重70%) | J85: 8门 | K85: 8门 | L85: 课程： 高级经理课程《品牌在全渠道的管理》--辛小甜总监，4.72 《凡岛之路》--校长，4.9 《管理者的自我修炼》--陈一萌总监 5.0 《激活组织氛围》--校长 5.0 《价值判断与价值共识》--侯庆福总监，4.76 《品牌管理与产品》--廖丫，4.810 《品牌营销与传播》--唐娟总监，4.952 《渠道认知与实操》--松梅总监，5.0 | M85: 1 | N85: 0.7 | O85: 1 | P85: 1 | Q85: 1 | R85: 2000 | S85: 2000 | T85: 2000 | U85: 交付质量完成率 | X85: 100 | Y85: 无误 | Z85: 1 | AA85: 0.6 | AB85: 1
A86: FD-203809 | B86: 凡岛大学 | C86: 凡岛大学 | D86: 培训讲师 | E86: 王无双 | F86: 2026年07月 | G86: 凡岛大学-培训讲师绩效考核方案2606 | H86: 专业技能体系得分 | I86: 人资市场公关品牌管理部7月考核 | J86: 20次 | K86: 完成部门考核100%次 | L86: 课程： 高级经理课程《品牌在全渠道的管理》--辛小甜总监，4.72 《凡岛之路》--校长，4.9 《管理者的自我修炼》--陈一萌总监 5.0 《激活组织氛围》--校长 5.0 《价值判断与价值共识》--侯庆福总监，4.76 《品牌管理与产品》--廖丫，4.810 《品牌营销与传播》--唐娟总监，4.952 《渠道认知与实操》--松梅总监，5.0 | M86: 1 | N86: 0.15 | O86: 1 | P86: 0.83 | Q86: 0.83 | R86: 2490 | S86: 2490 | T86: 3000 | U86: 人资考核落地执行率 | V86: 考核落地执行率=当月实际考核设计落地数/当月考核设计落地目标数*100% | W86: 1 | X86: 完成部门考核100% | Y86: 无误 | Z86: 1 | AA86: 0.5 | AB86: 1
A87: FD-203809 | B87: 凡岛大学 | C87: 凡岛大学 | D87: 培训讲师 | E87: 王无双 | F87: 2026年07月 | G87: 凡岛大学-培训讲师绩效考核方案2606 | H87: 专业技能体系得分 | I87: 人资市场公关品牌管理部7月考核 | J87: 20次 | K87: 完成部门考核100%次 | L87: 课程： 高级经理课程《品牌在全渠道的管理》--辛小甜总监，4.72 《凡岛之路》--校长，4.9 《管理者的自我修炼》--陈一萌总监 5.0 《激活组织氛围》--校长 5.0 《价值判断与价值共识》--侯庆福总监，4.76 《品牌管理与产品》--廖丫，4.810 《品牌营销与传播》--唐娟总监，4.952 《渠道认知与实操》--松梅总监，5.0 | M87: 1 | N87: 0.15 | O87: 1 | P87: 0.83 | Q87: 0.83 | R87: 2490 | S87: 2490 | T87: 3000 | U87: 市场考核落地执行率 | V87: 考核落地执行率=当月实际考核设计落地数/当月考核设计落地目标数*100% | W87: 1 | X87: 完成部门考核100% | Y87: 无误 | Z87: 1 | AA87: 0.25 | AB87: 1
A88: FD-203809 | B88: 凡岛大学 | C88: 凡岛大学 | D88: 培训讲师 | E88: 王无双 | F88: 2026年07月 | G88: 凡岛大学-培训讲师绩效考核方案2606 | H88: 专业技能体系得分 | I88: 人资市场公关品牌管理部7月考核 | J88: 20次 | K88: 完成部门考核100%次 | L88: 课程： 高级经理课程《品牌在全渠道的管理》--辛小甜总监，4.72 《凡岛之路》--校长，4.9 《管理者的自我修炼》--陈一萌总监 5.0 《激活组织氛围》--校长 5.0 《价值判断与价值共识》--侯庆福总监，4.76 《品牌管理与产品》--廖丫，4.810 《品牌营销与传播》--唐娟总监，4.952 《渠道认知与实操》--松梅总监，5.0 | M88: 1 | N88: 0.15 | O88: 1 | P88: 0.83 | Q88: 0.83 | R88: 2490 | S88: 2490 | T88: 3000 | U88: 品牌管理考核落地执行率 | V88: 考核落地执行率=当月实际考核设计落地数/当月考核设计落地目标数*100% | W88: 100 | X88: 完成部门考核100% | Y88: 无误 | Z88: 1 | AA88: 0.25 | AB88: 100
A89: FD-203809 | B89: 凡岛大学 | C89: 凡岛大学 | D89: 培训讲师 | E89: 王无双 | F89: 2026年07月 | G89: 凡岛大学-培训讲师绩效考核方案2606 | H89: 项目类及其他关键工作 | I89: AI公开课 | L89: 课程： 高级经理课程《品牌在全渠道的管理》--辛小甜总监，4.72 《凡岛之路》--校长，4.9 《管理者的自我修炼》--陈一萌总监 5.0 《激活组织氛围》--校长 5.0 《价值判断与价值共识》--侯庆福总监，4.76 《品牌管理与产品》--廖丫，4.810 《品牌营销与传播》--唐娟总监，4.952 《渠道认知与实操》--松梅总监，5.0 | M89: 0.5 | N89: 0.2 | O89: 0.5 | P89: 0.83 | Q89: 0.83 | R89: 2490 | S89: 2490 | T89: 3000 | U89: 品牌管理考核落地执行率 | V89: 考核落地执行率=当月实际考核设计落地数/当月考核设计落地目标数*100% | W89: 100 | X89: 完成部门考核100% | Y89: 无误 | Z89: 1 | AA89: 0.25 | AB89: 100
A90: FD-203809 | B90: 凡岛大学 | C90: 凡岛大学 | D90: 培训讲师 | E90: 王无双 | F90: 2026年07月 | G90: 凡岛大学-培训讲师绩效考核方案2606 | H90: 项目类及其他关键工作 | I90: skill部门大赛 | L90: 课程： 高级经理课程《品牌在全渠道的管理》--辛小甜总监，4.72 《凡岛之路》--校长，4.9 《管理者的自我修炼》--陈一萌总监 5.0 《激活组织氛围》--校长 5.0 《价值判断与价值共识》--侯庆福总监，4.76 《品牌管理与产品》--廖丫，4.810 《品牌营销与传播》--唐娟总监，4.952 《渠道认知与实操》--松梅总监，5.0 | M90: 1 | N90: 0.3 | O90: 1 | P90: 0.83 | Q90: 0.83 | R90: 2490 | S90: 2490 | T90: 3000 | U90: 品牌管理考核落地执行率 | V90: 考核落地执行率=当月实际考核设计落地数/当月考核设计落地目标数*100% | W90: 100 | X90: 完成部门考核100% | Y90: 无误 | Z90: 1 | AA90: 0.25 | AB90: 100
A91: FD-203809 | B91: 凡岛大学 | C91: 凡岛大学 | D91: 培训讲师 | E91: 王无双 | F91: 2026年07月 | G91: 凡岛大学-培训讲师绩效考核方案2606 | H91: 全员培训 | I91: 学时完成率100% 优质授课率63% 总体完成得分：0.8 | J91: 4小时 | K91: 学时完成率100% 优质授课率63% 总体完成得分：0.8小时 | L91: 学时完成率100% 优质授课率63% 总体完成得分：0.8 | M91: 0.8 | N91: 0.35 | O91: 0.8 | P91: 0.83 | Q91: 0.83 | R91: 2490 | S91: 2490 | T91: 3000 | U91: 品牌管理考核落地执行率 | V91: 考核落地执行率=当月实际考核设计落地数/当月考核设计落地目标数*100% | W91: 100 | X91: 完成部门考核100% | Y91: 无误 | Z91: 1 | AA91: 0.25 | AB91: 100
A92: OD-007504 | B92: 凡岛大学 | C92: 凡岛大学 | D92: 课程助教 | E92: 梁夏晴 | F92: 2026年07月 | G92: 凡岛大学-课程助教绩效方案 | H92: 新岛民总优质授课率 | I92: 组织7月三期新岛民培训 | J92: 0.8 | K92: 0.8667 | L92: 三期15门课程，13门课程达到优质授课 | M92: 1.08 | N92: 0.3 | O92: 1.08 | P92: 1.024 | Q92: 1.02 | R92: 2040 | S92: 2040 | T92: 2000 | U92: 品牌管理考核落地执行率 | V92: 考核落地执行率=当月实际考核设计落地数/当月考核设计落地目标数*100% | W92: 100 | X92: 完成部门考核100% | Y92: 无误 | Z92: 1 | AA92: 0.25 | AB92: 100
A93: OD-007504 | B93: 凡岛大学 | C93: 凡岛大学 | D93: 课程助教 | E93: 梁夏晴 | F93: 2026年07月 | G93: 凡岛大学-课程助教绩效方案 | H93: 岗位实战技能竞技赛 | I93: FanDo Skill 搭建技能竞技赛顺利组织至公司初赛 | J93: 1 | L93: 顺利将赛程推进至公司初赛，并宣发完成 | M93: 1 | N93: 0.7 | O93: 1 | P93: 1.024 | Q93: 1.02 | R93: 2040 | S93: 2040 | T93: 2000 | U93: 品牌管理考核落地执行率 | V93: 考核落地执行率=当月实际考核设计落地数/当月考核设计落地目标数*100% | W93: 100 | X93: 完成部门考核100% | Y93: 无误 | Z93: 1 | AA93: 0.25 | AB93: 100
A94: FD-222057 | B94: AI效率流程部-AI效率流程D中心 | C94: AI效率流程部-AI效率流程D中心 | D94: AIBP | E94: 朱嘉琳 | F94: 2026年07月 | G94: 【AI效率流程D中心】绩效方案-fando推广版 | H94: skill达成数量 | I94: 帮业务搭建8个可复用的高价值skill | J94: 8个 | K94: 18个 | L94: 顺利将赛程推进至公司初赛，并宣发完成 | M94: 2.25 | N94: 0.4 | O94: 1.5 | P94: 1.669283 | Q94: 1.38 | R94: 4080 | S94: 4080 | T94: 3400 | U94: 品牌管理考核落地执行率 | V94: 考核落地执行率=当月实际考核设计落地数/当月考核设计落地目标数*100% | W94: 100 | X94: 完成部门考核100% | Y94: 无误 | Z94: 1 | AA94: 0.25 | AB94: 100
A95: FD-222057 | B95: AI效率流程部-AI效率流程D中心 | C95: AI效率流程部-AI效率流程D中心 | D95: AIBP | E95: 朱嘉琳 | F95: 2026年07月 | G95: 【AI效率流程D中心】绩效方案-fando推广版 | H95: 部门日活率 | I95: 部门日活率达到80% | J95: 0.8 | K95: 0.8059 | L95: 顺利将赛程推进至公司初赛，并宣发完成 | M95: 1.007375 | N95: 0.3 | O95: 1.1081 | P95: 1.669283 | Q95: 1.38 | R95: 4080 | S95: 4080 | T95: 3400 | U95: 品牌管理考核落地执行率 | V95: 考核落地执行率=当月实际考核设计落地数/当月考核设计落地目标数*100% | W95: 100 | X95: 完成部门考核100% | Y95: 无误 | Z95: 1 | AA95: 0.25 | AB95: 100
A96: FD-222057 | B96: AI效率流程部-AI效率流程D中心 | C96: AI效率流程部-AI效率流程D中心 | D96: AIBP | E96: 朱嘉琳 | F96: 2026年07月 | G96: 【AI效率流程D中心】绩效方案-fando推广版 | H96: 部门人均token消耗 | I96: 部门人均token消耗达到1500万 | J96: 1500万 | K96: 2335.39万 | L96: 顺利将赛程推进至公司初赛，并宣发完成 | M96: 1.5569 | N96: 0.3 | O96: 1.5 | P96: 1.669283 | Q96: 1.38 | R96: 4080 | S96: 4080 | T96: 3400 | U96: 品牌管理考核落地执行率 | V96: 考核落地执行率=当月实际考核设计落地数/当月考核设计落地目标数*100% | W96: 100 | X96: 完成部门考核100% | Y96: 无误 | Z96: 1 | AA96: 0.25 | AB96: 100
A97: OD-001113 | B97: 人资行政部-直播招聘中心 | C97: 人资行政部-直播招聘中心 | D97: 招聘专员 | E97: 蓝煜钧 | F97: 2026年07月 | G97: 直播招聘中心-高级主播模块-绩效考核方案 | H97: 个人猎聘目标完成率 | I97: 高级主播试播完成 | J97: 2人 | K97: 0 | L97: 顺利将赛程推进至公司初赛，并宣发完成 | M97: 0 | N97: 0.6 | O97: 0 | P97: 0.4 | Q97: 0.48 | R97: 1440 | S97: 1440 | T97: 3000 | U97: 品牌管理考核落地执行率 | V97: 考核落地执行率=当月实际考核设计落地数/当月考核设计落地目标数*100% | W97: 100 | X97: 完成部门考核100% | Y97: 无误 | Z97: 1 | AA97: 0.25 | AB97: 100
A98: OD-001113 | B98: 人资行政部-直播招聘中心 | C98: 人资行政部-直播招聘中心 | D98: 招聘专员 | E98: 蓝煜钧 | F98: 2026年07月 | G98: 直播招聘中心-高级主播模块-绩效考核方案 | H98: 个人猎聘目标完成率 | I98: 新人主播入职 | J98: 1人 | K98: 1 | L98: 入职1主播 | M98: 1 | N98: 0.4 | O98: 1.2 | P98: 0.4 | Q98: 0.48 | R98: 1440 | S98: 1440 | T98: 3000 | U98: 品牌管理考核落地执行率 | V98: 考核落地执行率=当月实际考核设计落地数/当月考核设计落地目标数*100% | W98: 100 | X98: 完成部门考核100% | Y98: 无误 | Z98: 1 | AA98: 0.25 | AB98: 100
A99: FD-223714 | B99: AI效率流程部-AI效率流程D中心 | C99: AI效率流程部-AI效率流程D中心 | D99: AIBP | E99: 叶森莹 | F99: 2026年07月 | G99: 【AI效率流程D中心】绩效方案-fando推广版 | H99: skill达成数量 | I99: 营销段高价值可复用的SKILL | J99: 8个 | K99: 18个个 | L99: 入职1主播 | M99: 2.25 | N99: 0.4 | O99: 1.5 | P99: 1.233183 | Q99: 1.28 | R99: 2720 | S99: 2720 | T99: 3400 | U99: 品牌管理考核落地执行率 | V99: 考核落地执行率=当月实际考核设计落地数/当月考核设计落地目标数*100% | W99: 100 | X99: 完成部门考核100% | Y99: 无误 | Z99: 1 | AA99: 0.25 | AB99: 100
A100: FD-223714 | B100: AI效率流程部-AI效率流程D中心 | C100: AI效率流程部-AI效率流程D中心 | D100: AIBP | E100: 叶森莹 | F100: 2026年07月 | G100: 【AI效率流程D中心】绩效方案-fando推广版 | H100: 部门日活率 | I100: 品牌营销部使用Fando日活率 | J100: 0.6 | K100: 0.6366 | L100: 入职1主播 | M100: 0.01061 | N100: 0.3 | O100: 1.1671 | P100: 1.233183 | Q100: 1.28 | R100: 2720 | S100: 2720 | T100: 3400 | U100: 品牌管理考核落地执行率 | V100: 考核落地执行率=当月实际考核设计落地数/当月考核设计落地目标数*100% | W100: 100 | X100: 完成部门考核100% | Y100: 无误 | Z100: 1 | AA100: 0.25 | AB100: 100
...

Sheet 系统-原始（副本）
A1: 工号 | B1: 部门 | C1: 中心 | D1: 岗位 | E1: 姓名 | F1: 所属周期 | G1: 绩效方案名称 | H1: 任务名称 | I1: 任务内容 | J1: 目标 | K1: 实际完成数值 | L1: 完成情况说明 | M1: 单项完成率 | N1: 权重 | O1: 单项最终得分 | P1: 总完成率 | Q1: 总得分 | R1: 绩效奖金 | S1: 总奖金 | T1: 绩效基数 | U1: 子指标名称 | V1: 子指标说明 | W1: 子指标目标 | X1: 子指标完成量 | Y1: 子指标完成情况说明 | Z1: 子指标完成率 | AA1: 子指标权重 | AB1: 子指标得分
A2: FD-096937 | B2: 产品供应部-计划中心 | C2: 产品供应部-计划中心 | D2: 计划经理 | E2: 郭翠 | F2: 2026年07月 | G2: 产品供应部计划经理绩效考核方案 | H2: 生产履约目标完成率 | I2: 成品订单履约率完成95% | J2: 95 | K2: 0.971 | L2: 卓多姿35条目标，完成34条，1条未完成。34/35=97.1% | M2: 1.022 | N2: 0.5 | O2: 1 | P2: 0.911 | Q2: 0.91 | R2: 2821 | S2: 2821 | T2: 3100 | U2: 子指标名称 | V2: 子指标说明 | W2: 子指标目标 | X2: 子指标完成量 | Y2: 子指标完成情况说明 | Z2: 子指标完成率 | AA2: 子指标权重 | AB2: 子指标得分
A3: FD-098593 | B3: 产品供应部-计划中心 | C3: 产品供应部-计划中心 | D3: 计划经理 | E3: 王妙芳 | F3: 2026年07月 | G3: 产品供应部计划经理绩效考核方案 | H3: 计划准确率完成率 | I3: 准确率目标88% | J3: 0.88 | K3: 100%%%%% | L3: 准确率完成情况是88.91% | M3: 1 | N3: 0.3 | O3: 1 | P3: 0.95 | Q3: 0.95 | R3: 2968.9 | S3: 2968.9 | T3: 3000 | U3: 子指标名称 | V3: 子指标说明 | W3: 子指标目标 | X3: 子指标完成量 | Y3: 子指标完成情况说明 | Z3: 子指标完成率 | AA3: 子指标权重 | AB3: 子指标得分
A4: FD-091691 | B4: 产品供应部-计划中心 | C4: 产品供应部-计划中心 | D4: 计划经理 | E4: 吴开智 | F4: 2026年07月 | G4: 产品供应部计划经理绩效考核方案 | H4: 总库存货值目标完成率 | I4: 1750 | J4: 1750万 | K4: 1548万万万 | M4: 1.13 | N4: 0.3 | O4: 1.13 | P4: 1.0025 | Q4: 0.85 | R4: 2550 | S4: 2550 | T4: 3000 | U4: 子指标名称 | V4: 子指标说明 | W4: 子指标目标 | X4: 子指标完成量 | Y4: 子指标完成情况说明 | Z4: 子指标完成率 | AA4: 子指标权重 | AB4: 子指标得分
A5: FD-085087 | B5: 产品供应部-计划中心 | C5: 产品供应部-计划中心 | D5: 计划经理 | E5: 张璐萍 | F5: 2026年07月 | G5: 产品供应部计划经理绩效考核方案 | H5: 部门关键项目完成率 | I5: 1、损耗率降低至1.5%以下-损耗分析输出。寻找降损点 2、KONO经典系列限定款去膜 -说服品牌方去膜 3、凡岛工厂与总部流程优化与执行-1. 第二模块的详细流程 4、加工厂基础跟产流程各类定义、解释和对应端口梳理（跟产名词、细节宝典）-完善第二板块，写第三板块 5、8g袋包降损-1. 推进袋包机购置方案 6、料体高损耗降损-1. 软管打样上级，测试损耗率 7、凡岛临期原料管理-1. 与工厂了解临期原料管理流程 2. 与供应端梳理新流程情况 3. 结合新流程重新共识 | J5: 1 | K5: 92%%% | L5: 1、损耗率降低至1.5%以下-损耗分析输出。寻找降损点（已完成） 2、KONO经典系列限定款去膜 -说服品牌方去膜 （已完成，项目暂停）3、凡岛工厂与总部流程优化与执行-1. 第二模块的详细流程 （已完成）4、加工厂基础跟产流程各类定义、解释和对应端口梳理（跟产名词、细节宝典）-完善第二板块，写第三板块 （已完成）5、8g袋包降损-1. 推进袋包机购置方案 （不推进购置，确认其他方案90%））6、料体高损耗降损-1. 软管打样上级，测试损耗率 （待测试结果，完成95%）7、凡岛临期原料管理-1. 与工厂了解临期原料管理流程 2. 与供应端梳理新流程情况 3. 结合新流程重新共识（待试运行，完成90%） | M5: 0.92 | N5: 0.2 | O5: 0.92 | P5: 0.9396 | Q5: 0.99 | R5: 3475.6 | S5: 3475.6 | T5: 3000 | U5: 子指标名称 | V5: 子指标说明 | W5: 子指标目标 | X5: 子指标完成量 | Y5: 子指标完成情况说明 | Z5: 子指标完成率 | AA5: 子指标权重 | AB5: 子指标得分
A6: FD-094730 | B6: 产品供应部-计划中心 | C6: 产品供应部-计划中心 | D6: 计划经理 | E6: 魏振涛 | F6: 2026年07月 | G6: 产品供应部计划经理绩效考核方案 | H6: 部门关键项目完成率 | I6: 1、TCO落地计算 2、找到1-1.5、1.5-2以及物料稳定出库方案 | J6: 2条 | K6: 95%条 | L6: TCO完成，效期出库只有物料还无出库方案，新增返工费用计算完成 | M6: 0.95 | N6: 0.4 | O6: 0.95 | P6: 0.905 | Q6: 0.91 | R6: 2730 | S6: 2730 | T6: 3000 | U6: 子指标名称 | V6: 子指标说明 | W6: 子指标目标 | X6: 子指标完成量 | Y6: 子指标完成情况说明 | Z6: 子指标完成率 | AA6: 子指标权重 | AB6: 子指标得分
A7: FD-177153 | B7: 产品供应部-计划中心 | C7: 产品供应部-计划中心 | D7: 计划经理 | E7: 马猷安 | F7: 2026年07月 | G7: 产品供应部计划经理绩效考核方案 | H7: 部门关键项目完成率 | I7: 1. 数据上金蝶 2. 加工厂库位管理 3. 生产端包材优化 4. 杜明、郭翠带教 | J7: 1 | K7: 85%% | L7: 包材成本优化板块 没有深入学习和拓展 | M7: 0.85 | N7: 0.6 | O7: 0.85 | P7: 0.972 | Q7: 0.98 | R7: 3058.9 | S7: 3058.9 | T7: 3000 | U7: 子指标名称 | V7: 子指标说明 | W7: 子指标目标 | X7: 子指标完成量 | Y7: 子指标完成情况说明 | Z7: 子指标完成率 | AA7: 子指标权重 | AB7: 子指标得分
A8: FD-097678 | B8: 产品供应部-计划中心 | C8: 产品供应部-计划中心 | D8: 管培生 | E8: 钟恩宝 | F8: 2026年07月 | G8: 产品供应部计划经理绩效考核方案 | H8: 部门关键项目完成率 | I8: 关键项目 | J8: 1 | K8: 90%%% | L8: 总目标金额5720， 实际损耗金额2119 | M8: 0.9 | N8: 0.4 | O8: 0.9 | P8: 1.00971 | Q8: 1.01 | R8: 5525.6 | S8: 5525.6 | T8: 5000 | U8: 子指标名称 | V8: 子指标说明 | W8: 子指标目标 | X8: 子指标完成量 | Y8: 子指标完成情况说明 | Z8: 子指标完成率 | AA8: 子指标权重 | AB8: 子指标得分
A9: FD-092488 | B9: 产品供应部-计划中心 | C9: 产品供应部-计划中心 | D9: 管培生 | E9: 林杜明 | F9: 2026年07月 | G9: 产品供应部计划经理绩效考核方案 | H9: 生产履约目标完成率 | I9: 沪汇加工厂履约率 | J9: 1 | K9: 1 | L9: 沪汇7月份履约率100% | M9: 1 | N9: 0.3 | O9: 1 | P9: 0.89 | Q9: 0.91 | R9: 0 | S9: 0 | T9: 5000 | U9: 子指标名称 | V9: 子指标说明 | W9: 子指标目标 | X9: 子指标完成量 | Y9: 子指标完成情况说明 | Z9: 子指标完成率 | AA9: 子指标权重 | AB9: 子指标得分
A10: OD-002451 | B10: 人资行政部-组织发展中心 | C10: 人资行政部-组织发展中心 | D10: SSC助理 | E10: 陆颖 | F10: 2026年07月 | G10: 人资行政部-组织发展中心-SSC助理 | H10: 例行工作及时率 | I10: 按照对应节点完成各项工作 | J10: 1 | K10: 0 | L10: 已按照节点完成 | M10: 1 | N10: 0.5 | O10: 1 | P10: 1 | Q10: 1 | R10: 1500 | S10: 1500 | T10: 1500 | U10: 转正管理及时率 | V10: 6.30完成7、8月转正名单更新；7.10完成6月转正考勤更新；7.29完成6月转正结果更新；7.30完成8、9月转正名单更新 | X10: 子指标完成量 | Y10: 6.30更新7、8月预计转正名单，7.9更新转正考勤，7.29更新转正结果，7.30更新8、9月转正名单 | Z10: 1 | AA10: 0.2 | AB10: 1
A11: OD-000664 | B11: 人资行政部-组织发展中心 | C11: 人资行政部-组织发展中心 | D11: SSC助理 | E11: 宋月 | F11: 2026年07月 | G11: 人资行政部-组织发展中心-SSC助理 | H11: 例行工作及时率 | I11: 季度评级：跟进OA岛民上级提交 定计划文档提交率80% 7.13完成绩效数据整理 | J11: 1 | K11: 0 | L11: 季度评级：跟进OA岛民上级提交 定计划文档提交率80% 7.13完成绩效数据整理 7.10完成 | M11: 1.075 | N11: 0.5 | O11: 1.075 | P11: 1.0285 | Q11: 1.03 | R11: 2060 | S11: 2060 | T11: 2000 | U11: 绩效数据汇总分析完成率 | X11: 准确完成 | Y11: 7.10完成 | Z11: 1.2 | AA11: 0.6 | AB11: 1.2
A12: OD-008606 | B12: 人资行政部-组织发展中心 | C12: 人资行政部-组织发展中心 | D12: SSC助理 | E12: 吴瑶华 | F12: 2026年07月 | G12: 人资行政部-组织发展中心-SSC助理 | H12: 例行工作及时率 | I12: 1、离职流程完结率 2、三方处理及时率 3、社保公积金缴纳及时率 3、社保公积金补缴及时率 4、生育津贴处理及时率 5、工伤申报处理及时率 | J12: 1 | K12: 0 | L12: 及时完成 | M12: 1 | N12: 0.5 | O12: 1 | P12: 0.9375 | Q12: 0.94 | R12: 1410 | S12: 1410 | T12: 1500 | U12: 离职流程完结率 | V12: - 计算公式：离职流程完结及时率=离职流程完结数/当月离职总人数*100% 1. 离职流程准时完结数：账号注销日期为最后工作日结束后的三个工作日内 账号注销：需要业务部门确认工作交接、财务确认报销流程完结、行政确认固定资产交接完结、组发核对考勤完结，开具离职证明后注销 1. 当月离职总人数：含正式、试用期、实习期、兼职等所有人员，以【飞书审批-离职交接、实习结束交接申请】数据为准 | W12: 1 | X12: 100 | Y12: "6.29-6.30离职24人，7月离职145人，剔除7.30及之后25人，离职的离职完结3天内的达126/144人，占比87.5% 岛民离职进度跟进表-SSC专用 " | Z12: 0.875 | AA12: 0.3 | AB12: 1
A13: FD-155599 | B13: 人资行政部-组织发展中心 | C13: 人资行政部-组织发展中心 | D13: COE专家 | E13: 王雅丽 | F13: 2026年07月 | G13: 人资行政部-组织发展中心-COE专家、SSC专家202606 | H13: 价值创造类 | I13: 社保公积金年度调基方案 | K13: 已完成 | L13: 及时完成 | M13: 1 | N13: 0.5 | O13: 1 | P13: 1 | Q13: 1 | R13: 3386 | S13: 3386 | T13: 3000 | U13: 社保公积金年度调基方案 | X13: 已完成 | Y13: 无误 | Z13: 1 | AA13: 1 | AB13: 1
A14: FD-156792 | B14: 人资行政部-组织发展中心 | C14: 人资行政部-组织发展中心 | D14: COE专家 | E14: 宫兆宜 | F14: 2026年07月 | G14: 人资行政部-组织发展中心-COE专家、SSC专家202606 | H14: 价值创造类 | I14: 绩效访谈的开展&分析报告的输出 | K14: 1 | L14: 完成方案的初版报告的生成（AI版本） | M14: 1 | N14: 0.7 | O14: 1 | P14: 1 | Q14: 1 | R14: 3386 | S14: 3386 | T14: 3000 | U14: 交付进度完成率 | X14: 1 | Y14: 无误 | Z14: 1 | AA14: 0.4 | AB14: 1
A15: FD-154391 | B15: 人资行政部-组织发展中心 | C15: 人资行政部-组织发展中心 | D15: SSC专家 | E15: 胡涵冰 | F15: 2026年07月 | G15: 人资行政部-组织发展中心-COE专家、SSC专家202606 | H15: 合同签订及时率 | I15: 把控跟进合同及协议签订流程 | J15: 1 | K15: 0.7943 | L15: 实际合同签订及时率为79.43% | M15: 0.7943 | N15: 0.3 | O15: 0.6354 | P15: 0.85829 | Q15: 0.81 | R15: 2128 | S15: 2128 | T15: 2200 | U15: 交付质量完成率 | X15: 100 | Y15: 无误 | Z15: 1 | AA15: 0.6 | AB15: 1
A16: FD-155628 | B16: 人资行政部-组织发展中心 | C16: 人资行政部-组织发展中心 | D16: 管培生 | E16: 杨宁 | F16: 2026年07月 | G16: 人资行政部-组织发展中心-COE专家、SSC专家202606 | H16: 关键工作完成率 | I16: 人岗匹配Q3分析报告 + 优化方案 | J16: 100 | K16: 80 | L16: 人岗匹配优化方案3.0+人才评估体系思考2.0 | M16: 0.8 | N16: 0.6 | O16: 0.8 | P16: 0.8 | Q16: 0.8 | R16: 4300 | S16: 4300 | T16: 5000 | U16: 交付质量完成率 | X16: 100 | Y16: 无误 | Z16: 1 | AA16: 0.6 | AB16: 1
A17: FD-083986 | B17: 新品牌事业部-设计中心 | C17: 新品牌事业部-设计中心 | D17: 产品设计师 | E17: 罗亦晨 | F17: 2026年07月 | G17: 新品牌事业部-设计中心-产品组各岗位设计师月度绩效考核方案 | H17: 核心设计项目产出 | I17: 可麦纸箱设计升级3.0 设计定版，下推打样 | J17: 1 | K17: 80 | M17: 0.4 | N17: 0.4 | O17: 0.4 | P17: 0.67 | Q17: 1.07 | R17: 3200 | S17: 3200 | T17: 2800 | U17: 交付质量完成率 | X17: 100 | Y17: 无误 | Z17: 1 | AA17: 0.6 | AB17: 1
A18: FD-080197 | B18: 新品牌事业部-设计中心 | C18: 新品牌事业部-设计中心 | D18: 产品设计师 | E18: 邓力欣 | F18: 2026年07月 | G18: 新品牌事业部-设计中心-产品组各岗位设计师月度绩效考核方案 | H18: 核心设计项目产出 | I18: 可麦纸箱设计升级3.0 设计定版，下推打样 | J18: 100& | K18: 80 | M18: 1 | N18: 0.4 | O18: 1 | P18: 0.67 | Q18: 0.77 | R18: 2216 | S18: 2216 | T18: 2800 | U18: 交付质量完成率 | X18: 100 | Y18: 无误 | Z18: 1 | AA18: 0.6 | AB18: 1
A19: FD-088054 | B19: 新品牌事业部-设计中心 | C19: 新品牌事业部-设计中心 | D19: 产品设计师 | E19: 余楚薰 | F19: 2026年07月 | G19: 新品牌事业部-设计中心-产品组各岗位设计师月度绩效考核方案 | H19: 核心设计项目产出 | I19: 可麦纸箱设计升级3.0 设计定版，下推打样 | J19: 1 | K19: 80 | M19: 0.4 | N19: 0.4 | O19: 0.4 | P19: 0.58 | Q19: 0.68 | R19: 0 | S19: 0 | T19: 2800 | U19: 交付质量完成率 | X19: 100 | Y19: 无误 | Z19: 1 | AA19: 0.6 | AB19: 1
A20: FD-085640 | B20: 新品牌事业部-设计中心 | C20: 新品牌事业部-设计中心 | D20: 首席平面设计师 | E20: 谢志达 | F20: 2026年07月 | G20: 新品牌事业部-设计中心-平面组各岗位设计师月度绩效考核方案 | H20: 核心设计项目产出 | I20: AI应用设计的项目流程优化方案-营销AI视频自动化 | J20: 1 | K20: 40%%% | L20: 1 | M20: 1 | N20: 0.3 | O20: 0.3 | P20: 0.7 | Q20: 0.75 | R20: 3810 | S20: 3810 | T20: 5000 | U20: 交付质量完成率 | X20: 100 | Y20: 无误 | Z20: 1 | AA20: 0.6 | AB20: 1
A21: FD-084584 | B21: 新品牌事业部-设计中心 | C21: 新品牌事业部-设计中心 | D21: 资深平面设计师 | E21: 张盛源 | F21: 2026年07月 | G21: 新品牌事业部-设计中心-平面组各岗位设计师月度绩效考核方案 | H21: 核心设计项目产出 | I21: 凡岛季度荣誉榜kv设计 | J21: 1 | K21: 完成荣誉榜KV*1+人物组合*3%%% | L21: 100%已完成 | M21: 1 | N21: 0.3 | O21: 1 | P21: 0.73 | Q21: 0.83 | R21: 2870 | S21: 2870 | T21: 3000 | U21: 交付质量完成率 | X21: 100 | Y21: 无误 | Z21: 1 | AA21: 0.6 | AB21: 1
A22: FD-084304 | B22: 新品牌事业部-设计中心 | C22: 新品牌事业部-设计中心 | D22: 资深平面设计师 | E22: 苏秋英 | F22: 2026年07月 | G22: 新品牌事业部-设计中心-平面组各岗位设计师月度绩效考核方案 | H22: 日常平面工单完成率 | I22: IRY日常平面工单完成率 100% | J22: 1 | K22: 100%% | L22: 100 | M22: 1 | N22: 0.3 | O22: 1 | P22: 1 | Q22: 1 | R22: 3400 | S22: 3400 | T22: 3000 | U22: 交付质量完成率 | X22: 100 | Y22: 无误 | Z22: 1 | AA22: 0.6 | AB22: 1
A23: FD-155034 | B23: 凡岛大学 | C23: 凡岛大学 | D23: 培训讲师 | E23: 蒋欣 | F23: 2026年07月 | G23: 凡岛大学-培训讲师绩效考核方案2606 | H23: 管理类培训-课程交付完成 | I23: 按计划完成管理课程开发100%(权重30%) | J23: 8门 | K23: 8门 | L23: 已完成8门课程的开发，并交付落地 | M23: 1 | N23: 0.3 | O23: 1 | P23: 1 | Q23: 1 | R23: 2000 | S23: 2000 | T23: 2000 | U23: 交付质量完成率 | X23: 100 | Y23: 无误 | Z23: 1 | AA23: 0.6 | AB23: 1
A24: FD-203809 | B24: 凡岛大学 | C24: 凡岛大学 | D24: 培训讲师 | E24: 王无双 | F24: 2026年07月 | G24: 凡岛大学-培训讲师绩效考核方案2606 | H24: 专业技能体系得分 | I24: 人资市场公关品牌管理部7月考核 | J24: 20次 | K24: 完成部门考核100%次 | L24: 课程： 高级经理课程《品牌在全渠道的管理》--辛小甜总监，4.72 《凡岛之路》--校长，4.9 《管理者的自我修炼》--陈一萌总监 5.0 《激活组织氛围》--校长 5.0 《价值判断与价值共识》--侯庆福总监，4.76 《品牌管理与产品》--廖丫，4.810 《品牌营销与传播》--唐娟总监，4.952 《渠道认知与实操》--松梅总监，5.0 | M24: 1 | N24: 0.15 | O24: 1 | P24: 0.83 | Q24: 0.83 | R24: 2490 | S24: 2490 | T24: 3000 | U24: 人资考核落地执行率 | V24: 考核落地执行率=当月实际考核设计落地数/当月考核设计落地目标数*100% | W24: 1 | X24: 完成部门考核100% | Y24: 无误 | Z24: 1 | AA24: 0.5 | AB24: 1
A25: OD-007504 | B25: 凡岛大学 | C25: 凡岛大学 | D25: 课程助教 | E25: 梁夏晴 | F25: 2026年07月 | G25: 凡岛大学-课程助教绩效方案 | H25: 新岛民总优质授课率 | I25: 组织7月三期新岛民培训 | J25: 0.8 | K25: 0.8667 | L25: 三期15门课程，13门课程达到优质授课 | M25: 1.08 | N25: 0.3 | O25: 1.08 | P25: 1.024 | Q25: 1.02 | R25: 2040 | S25: 2040 | T25: 2000 | U25: 品牌管理考核落地执行率 | V25: 考核落地执行率=当月实际考核设计落地数/当月考核设计落地目标数*100% | W25: 100 | X25: 完成部门考核100% | Y25: 无误 | Z25: 1 | AA25: 0.25 | AB25: 100
A26: FD-222057 | B26: AI效率流程部-AI效率流程D中心 | C26: AI效率流程部-AI效率流程D中心 | D26: AIBP | E26: 朱嘉琳 | F26: 2026年07月 | G26: 【AI效率流程D中心】绩效方案-fando推广版 | H26: skill达成数量 | I26: 帮业务搭建8个可复用的高价值skill | J26: 8个 | K26: 18个 | L26: 顺利将赛程推进至公司初赛，并宣发完成 | M26: 2.25 | N26: 0.4 | O26: 1.5 | P26: 1.669283 | Q26: 1.38 | R26: 4080 | S26: 4080 | T26: 3400 | U26: 品牌管理考核落地执行率 | V26: 考核落地执行率=当月实际考核设计落地数/当月考核设计落地目标数*100% | W26: 100 | X26: 完成部门考核100% | Y26: 无误 | Z26: 1 | AA26: 0.25 | AB26: 100
A27: OD-001113 | B27: 人资行政部-直播招聘中心 | C27: 人资行政部-直播招聘中心 | D27: 招聘专员 | E27: 蓝煜钧 | F27: 2026年07月 | G27: 直播招聘中心-高级主播模块-绩效考核方案 | H27: 个人猎聘目标完成率 | I27: 高级主播试播完成 | J27: 2人 | K27: 0 | L27: 顺利将赛程推进至公司初赛，并宣发完成 | M27: 0 | N27: 0.6 | O27: 0 | P27: 0.4 | Q27: 0.48 | R27: 1440 | S27: 1440 | T27: 3000 | U27: 品牌管理考核落地执行率 | V27: 考核落地执行率=当月实际考核设计落地数/当月考核设计落地目标数*100% | W27: 100 | X27: 完成部门考核100% | Y27: 无误 | Z27: 1 | AA27: 0.25 | AB27: 100
A28: FD-223714 | B28: AI效率流程部-AI效率流程D中心 | C28: AI效率流程部-AI效率流程D中心 | D28: AIBP | E28: 叶森莹 | F28: 2026年07月 | G28: 【AI效率流程D中心】绩效方案-fando推广版 | H28: skill达成数量 | I28: 营销段高价值可复用的SKILL | J28: 8个 | K28: 18个个 | L28: 入职1主播 | M28: 2.25 | N28: 0.4 | O28: 1.5 | P28: 1.233183 | Q28: 1.28 | R28: 2720 | S28: 2720 | T28: 3400 | U28: 品牌管理考核落地执行率 | V28: 考核落地执行率=当月实际考核设计落地数/当月考核设计落地目标数*100% | W28: 100 | X28: 完成部门考核100% | Y28: 无误 | Z28: 1 | AA28: 0.25 | AB28: 100
A29: FD-228363 | B29: AI效率流程部-AI效率流程D中心 | C29: AI效率流程部-AI效率流程D中心 | D29: AI工程师 | E29: 许国杨 | F29: 2026年07月 | G29: 6月-AI效率流程D中心绩效方案 | H29: 项目效果 | I29: 【AI微医生】24H新粉退后转化率 | J29: 0.11 | K29: 0.1312 | L29: Al: 24H-13.12% 【精英池:24H- 10.85%】 | M29: 1.1927 | N29: 0.2 | O29: 1.312 | P29: 1.04904 | Q29: 0.94 | R29: 4000 | S29: 4000 | T29: 4000 | U29: 品牌管理考核落地执行率 | V29: 考核落地执行率=当月实际考核设计落地数/当月考核设计落地目标数*100% | W29: 100 | X29: 完成部门考核100% | Y29: 无误 | Z29: 1 | AA29: 0.25 | AB29: 100
A30: FD-229844 | B30: AI效率流程部-AI效率流程D中心 | C30: AI效率流程部-AI效率流程D中心 | D30: AI工程师 | E30: 许阳 | F30: 2026年07月 | G30: 6月-AI效率流程D中心绩效方案 | H30: 项目效果 | I30: 【AI微医生】24H新粉退后转化率 | J30: 0.11 | K30: 0.1312 | L30: AI：24H-13.12% 【精英池：24H-10.85%】 | M30: 1.1927 | N30: 0.2 | O30: 1.312 | P30: 1.04904 | Q30: 0.94 | R30: 4000 | S30: 4000 | T30: 4000 | U30: 品牌管理考核落地执行率 | V30: 考核落地执行率=当月实际考核设计落地数/当月考核设计落地目标数*100% | W30: 100 | X30: 完成部门考核100% | Y30: 无误 | Z30: 1 | AA30: 0.25 | AB30: 100
A31: FD-227696 | B31: AI效率流程部-AI效率流程D中心 | C31: AI效率流程部-AI效率流程D中心 | D31: AIBP | E31: 张怡 | F31: 2026年07月 | G31: 6月-AI效率流程D中心绩效方案 | H31: 项目效果 | I31: 【AI微医生】新粉转化率11% | J31: 0.11 | K31: 13.12%% | L31: 1. 优化新粉不回复情况，更新价格疑虑skill，重构delay工具 2. 完成新粉商用需求对齐与规划 扣退后AI转化率：当天-11.95% 24H-13.12% | M31: 1.192 | N31: 0.2 | O31: 1.31 | P31: 1.0484 | Q31: 0.94 | R31: 3400 | S31: 3400 | T31: 3400 | U31: 品牌管理考核落地执行率 | V31: 考核落地执行率=当月实际考核设计落地数/当月考核设计落地目标数*100% | W31: 100 | X31: 完成部门考核100% | Y31: 无误 | Z31: 1 | AA31: 0.25 | AB31: 100
A32: FD-224360 | B32: AI效率流程部-AI效率流程D中心 | C32: AI效率流程部-AI效率流程D中心 | D32: AI工程师 | E32: 余粤 | F32: 2026年07月 | G32: 6月-AI效率流程D中心绩效方案 | H32: 项目效果 | I32: 【AI微医生】扣退后24H新粉转化率 | J32: 0.11 | K32: 0.1312 | L32: 1. 灵活激活上线，优化skill 2. 下单后总结修改地址和备注方案上线：可对于下单前用户提出的要求进行修改响应 3. 长期维护新增激活skill，"long-term-activation"，主要是根据不同用户类型去生成个性化激活话术，目前针对新粉未成交和使用过敏退款的用户都可生成较合适的激活话术 4. 优化月度活动激活 | M32: 1.1927 | N32: 0.2 | O32: 1.312 | P32: 1.04904 | Q32: 0.94 | R32: 5000 | S32: 5000 | T32: 5000 | U32: 品牌管理考核落地执行率 | V32: 考核落地执行率=当月实际考核设计落地数/当月考核设计落地目标数*100% | W32: 100 | X32: 完成部门考核100% | Y32: 无误 | Z32: 1 | AA32: 0.25 | AB32: 100
A33: FD-184644 | B33: 公共事务与品牌传播部 | C33: 公共事务与品牌传播部 | D33: 品牌公关经理 | E33: 黄靖雯 | F33: 2026年07月 | G33: 公共事务与品牌传播部-品牌公关经理岗位绩效方案 | H33: 项目管理关键节点完成率 | I33: fando宣传内容制作及上线 | J33: 1 | L33: 7月共计产出30张宣传海报，实战案例视频1条，凡动表情包1.0已上线（包含16个形象）。 内宣部分各楼层广告机以及飞书表情商店均已上线，外宣部分均已发布。 | M33: 1 | N33: 0.8 | O33: 1 | P33: 1 | Q33: 1 | R33: 5000 | S33: 5000 | T33: 5000 | U33: 品牌管理考核落地执行率 | V33: 考核落地执行率=当月实际考核设计落地数/当月考核设计落地目标数*100% | W33: 100 | X33: 完成部门考核100% | Y33: 无误 | Z33: 1 | AA33: 0.25 | AB33: 100
A34: FD-181227 | B34: 公共事务与品牌传播部 | C34: 公共事务与品牌传播部 | D34: 品牌公关经理 | E34: 杨颖晖 | F34: 2026年07月 | G34: 公共事务与品牌传播部-品牌公关经理岗位绩效方案 | H34: 项目管理关键节点完成率 | I34: KONO KOC小红书合作 | J34: 1 | L34: 笔记合作量：实际 100，目标 90，达成率 111.11% 笔记收片量：实际 86，目标 90，达成率 95.56% | M34: 1.0334 | N34: 0.25 | O34: 1.03 | P34: 1.000005 | Q34: 0.99 | R34: 4950 | S34: 4950 | T34: 5000 | U34: 品牌管理考核落地执行率 | V34: 考核落地执行率=当月实际考核设计落地数/当月考核设计落地目标数*100% | W34: 100 | X34: 完成部门考核100% | Y34: 无误 | Z34: 1 | AA34: 0.25 | AB34: 100
A35: FD-188611 | B35: 公共事务与品牌传播部 | C35: 公共事务与品牌传播部 | D35: 品牌公关经理 | E35: 郑胡斌 | F35: 2026年07月 | G35: 公共事务与品牌传播部-品牌公关经理岗位绩效方案 | H35: 项目管理关键节点完成率 | I35: WIS、赫系7月奖项申报和荣誉传播 | L35: 由于粤妆甄品项目终止参赛，其余7月周期内奖项申报均已完成，已完成奖项申报工作2品牌4个，公共传播事件2个； | M35: 1 | N35: 0.3 | O35: 1 | P35: 1 | Q35: 1 | R35: 0 | S35: 0 | T35: 3000 | U35: 品牌管理考核落地执行率 | V35: 考核落地执行率=当月实际考核设计落地数/当月考核设计落地目标数*100% | W35: 100 | X35: 完成部门考核100% | Y35: 无误 | Z35: 1 | AA35: 0.25 | AB35: 100
A36: FD-181490 | B36: 公共事务与品牌传播部 | C36: 公共事务与品牌传播部 | D36: 舆情数据经理 | E36: 吴晓升 | F36: 2026年07月 | G36: 公共事务与品牌传播部舆情数据经理绩效考核方案 | H36: 策略执行达成率 | I36: 跟踪各项核心任务的实际完成进度与质量，按月统计执行达成率，输出复盘报告并针对未达标项制定改进措施。 | J36: 0.9 | L36: 0.2 | M36: 1 | N36: 0.2 | O36: 1 | P36: 1 | Q36: 1 | R36: 2000 | S36: 2000 | T36: 2000 | U36: 品牌管理考核落地执行率 | V36: 考核落地执行率=当月实际考核设计落地数/当月考核设计落地目标数*100% | W36: 100 | X36: 完成部门考核100% | Y36: 无误 | Z36: 1 | AA36: 0.25 | AB36: 100
A37: FD-181047 | B37: 公共事务与品牌传播部 | C37: 公共事务与品牌传播部 | D37: 公共事务经理 | E37: 周璐涵 | F37: 2026年07月 | G37: 公共事务与品牌传播部公共事务经理绩效考核方案 | H37: 双向合作价值次数 | I37: 媒体双向合作 | J37: 4 | K37: 4 | L37: 0.2 | M37: 1 | N37: 0.4 | O37: 1 | P37: 1 | Q37: 1 | R37: 5000 | S37: 5000 | T37: 5000 | U37: 品牌管理考核落地执行率 | V37: 考核落地执行率=当月实际考核设计落地数/当月考核设计落地目标数*100% | W37: 100 | X37: 完成部门考核100% | Y37: 无误 | Z37: 1 | AA37: 0.25 | AB37: 100
A38: FD-094330 | B38: 产品供应部-供应中心 | C38: 产品供应部-供应中心 | D38: 供应链经理 | E38: 陆永泉 | F38: 2026年07月 | G38: 【产品供应部-供应中心】-供应链经理、管培生、见习高级经理绩效考核方案 | H38: 订单履约指标 | I38: 原料模块订单履约完成率=成品原料履约款数/当月总核算成品款数 | J38: 1 | K38: 0.9906 | L38: 合计107款，成品履约106款，履约率99.06% | M38: 0.9906 | N38: 0.5 | O38: 1 | P38: 0.9953 | Q38: 1.14 | R38: 3348.84 | S38: 3348.84 | T38: 3000 | U38: 品牌管理考核落地执行率 | V38: 考核落地执行率=当月实际考核设计落地数/当月考核设计落地目标数*100% | W38: 100 | X38: 完成部门考核100% | Y38: 无误 | Z38: 1 | AA38: 0.25 | AB38: 100
A39: FD-080606 | B39: 产品供应部-供应中心 | C39: 产品供应部-供应中心 | D39: 供应链经理 | E39: 龙美莹 | F39: 2026年07月 | G39: 【产品供应部-供应中心】-供应链经理、管培生、见习高级经理绩效考核方案 | H39: 订单履约指标 | I39: 本月目标 | J39: 0.98 | K39: 0.9957 | L39: 送货总条数231，未履约1条 | M39: 1 | N39: 0.4 | O39: 1 | P39: 0.98314 | Q39: 1.14 | R39: 3069.77 | S39: 3069.77 | T39: 3000 | U39: 品牌管理考核落地执行率 | V39: 考核落地执行率=当月实际考核设计落地数/当月考核设计落地目标数*100% | W39: 100 | X39: 完成部门考核100% | Y39: 无误 | Z39: 1 | AA39: 0.25 | AB39: 100
A40: FD-153639 | B40: 产品供应部-供应中心 | C40: 产品供应部-供应中心 | D40: 供应链经理 | E40: 翁承梅 | F40: 2026年07月 | G40: 【产品供应部-供应中心】-供应链经理、管培生、见习高级经理绩效考核方案 | H40: 订单履约指标 | I40: 订单履约率 | J40: 0.99 | K40: 0.9741 | L40: 1、金冠-隐形水润经典款24片 2、雅纯-隐形水润经典款十片3、从化-KONO经典洗护套装（彩盒） | M40: 0.9839 | N40: 0.5 | O40: 0.8855 | P40: 0.99195 | Q40: 0.97 | R40: 2511.63 | S40: 2511.63 | T40: 3000 | U40: 品牌管理考核落地执行率 | V40: 考核落地执行率=当月实际考核设计落地数/当月考核设计落地目标数*100% | W40: 100 | X40: 完成部门考核100% | Y40: 无误 | Z40: 1 | AA40: 0.25 | AB40: 100
A41: FD-097865 | B41: 产品供应部-供应中心 | C41: 产品供应部-供应中心 | D41: 供应链经理 | E41: 曾静柔 | F41: 2026年07月 | G41: 【产品供应部-供应中心】-供应链经理、管培生、见习高级经理绩效考核方案 | H41: 订单履约指标 | I41: 订单履约率99% | J41: 0.99 | K41: 0.99 | L41: 1、金冠-隐形水润经典款24片 2、雅纯-隐形水润经典款十片3、从化-KONO经典洗护套装（彩盒） | M41: 1 | N41: 0.4 | O41: 1 | P41: 0.967 | Q41: 1 | R41: 2790.7 | S41: 2790.7 | T41: 3000 | U41: 品牌管理考核落地执行率 | V41: 考核落地执行率=当月实际考核设计落地数/当月考核设计落地目标数*100% | W41: 100 | X41: 完成部门考核100% | Y41: 无误 | Z41: 1 | AA41: 0.25 | AB41: 100
A42: FD-098144 | B42: 产品供应部-供应中心 | C42: 产品供应部-供应中心 | D42: 供应链经理 | E42: 李红菊 | F42: 2026年07月 | G42: 【产品供应部-供应中心】-供应链经理、管培生、见习高级经理绩效考核方案 | H42: 订单履约指标 | I42: 订单履约率 | J42: 0.995 | K42: 1 | L42: 1、金冠-隐形水润经典款24片 2、雅纯-隐形水润经典款十片3、从化-KONO经典洗护套装（彩盒） | M42: 1 | N42: 0.4 | O42: 1 | P42: 0.97492 | Q42: 1.17 | R42: 3627.91 | S42: 3627.91 | T42: 3000 | U42: 品牌管理考核落地执行率 | V42: 考核落地执行率=当月实际考核设计落地数/当月考核设计落地目标数*100% | W42: 100 | X42: 完成部门考核100% | Y42: 无误 | Z42: 1 | AA42: 0.25 | AB42: 100
A43: FD-095713 | B43: 产品供应部-供应中心 | C43: 产品供应部-供应中心 | D43: 管培生 | E43: 刘星瑶 | F43: 2026年07月 | G43: 【产品供应部-供应中心】-供应链经理、管培生、见习高级经理绩效考核方案 | H43: 订单履约指标 | I43: 原料模块订单履约完成率=成品原料履约款数/当月总核算成品款数 | J43: 1 | K43: 100%% | L43: 1、金冠-隐形水润经典款24片 2、雅纯-隐形水润经典款十片3、从化-KONO经典洗护套装（彩盒） | M43: 1 | N43: 0.4 | O43: 1 | P43: 0.98 | Q43: 1.01 | R43: 4651.16 | S43: 4651.16 | T43: 5000 | U43: 品牌管理考核落地执行率 | V43: 考核落地执行率=当月实际考核设计落地数/当月考核设计落地目标数*100% | W43: 100 | X43: 完成部门考核100% | Y43: 无误 | Z43: 1 | AA43: 0.25 | AB43: 100
A44: FD-096436 | B44: 产品供应部-供应中心 | C44: 产品供应部-供应中心 | D44: 供应链经理 | E44: 林江龙 | F44: 2026年07月 | G44: 【产品供应部-供应中心】-供应链经理、管培生、见习高级经理绩效考核方案 | H44: 订单履约指标 | I44: 原料订单履约率100% | J44: 1 | K44: 1 | L44: 原料订单履约率100% | M44: 1 | N44: 0.2 | O44: 1 | P44: 1 | Q44: 1 | R44: 0 | S44: 0 | T44: 3000 | U44: 品牌管理考核落地执行率 | V44: 考核落地执行率=当月实际考核设计落地数/当月考核设计落地目标数*100% | W44: 100 | X44: 完成部门考核100% | Y44: 无误 | Z44: 1 | AA44: 0.25 | AB44: 100
A45: FD-221937 | B45: AI效率流程部-AI效率流程E中心 | C45: AI效率流程部-AI效率流程E中心 | D45: AI工程师 | E45: 刘铎 | F45: 2026年07月 | G45: 【AI效率流程E中心】绩效方案（fando推广+其他项目版） | H45: 部门人均token消耗 | I45: token目标 负责部门:财务部、品牌管理部、总经办、线下渠道部 目标:当日人均token消耗量2000万,。(线下渠道部:当日人均token消耗量1200万) | J45: 1 | K45: 财务部：2073w 品牌管理部：2571w 线下渠道部：814w | L45: 财务部：2073w 品牌管理部：2571w 线下渠道部：814w | M45: 1 | N45: 0.25 | O45: 1 | P45: 0.959375 | Q45: 0.96 | R45: 5000 | S45: 5000 | T45: 5000 | U45: 品牌管理考核落地执行率 | V45: 考核落地执行率=当月实际考核设计落地数/当月考核设计落地目标数*100% | W45: 100 | X45: 完成部门考核100% | Y45: 无误 | Z45: 1 | AA45: 0.25 | AB45: 100
A46: FD-085458 | B46: 海外事业部-营销中心 | C46: 海外事业部-营销中心 | D46: 海外高级经理 | E46: 鲍睿 | F46: 2026年07月 | G46: 海外事业部-营销中心-高级经理-06 | H46: 项目扣退销售额完成率-6月新版本 | I46: 达播销售额目标 | J46: 60万元 | K46: 33.87万元 | L46: 扣退后，达播完成情况为338733元。 | M46: 0.5645 | N46: 0.4 | O46: 0.5645 | P46: 0.64741 | Q46: 0.65 | R46: 3237 | S46: 3237 | T46: 5000 | U46: 品牌管理考核落地执行率 | V46: 考核落地执行率=当月实际考核设计落地数/当月考核设计落地目标数*100% | W46: 100 | X46: 完成部门考核100% | Y46: 无误 | Z46: 1 | AA46: 0.25 | AB46: 100
A47: FD-218877 | B47: 海外事业部-运营中心 | C47: 海外事业部-运营中心 | D47: 跨境电商经理 | E47: 张馨雨 | F47: 2026年07月 | G47: 海外事业部-运营中心-跨境电商经理 | H47: 项目销售额 | I47: Shopee越南 | J47: 120000元 | K47: 107508元 | L47: 扣退后，达播完成情况为338733元。 | M47: 0.896 | N47: 0.3 | O47: 0.8959 | P47: 1.0252 | Q47: 1.03 | R47: 3000 | S47: 3000 | T47: 3000 | U47: 品牌管理考核落地执行率 | V47: 考核落地执行率=当月实际考核设计落地数/当月考核设计落地目标数*100% | W47: 100 | X47: 完成部门考核100% | Y47: 无误 | Z47: 1 | AA47: 0.25 | AB47: 100
A48: FD-071455 | B48: 海外事业部-海外开拓中心 | C48: 海外事业部-海外开拓中心 | D48: 跨境商务经理 | E48: 张宜静 | F48: 2026年07月 | G48: 海外事业部-海外开拓中心-海外商务经理 | H48: TEMU中东美国上架 | I48: TEMU平台出货2000元 | J48: 0.269 | K48: 0 | L48: 外标签完成，本体标签需重新设计和返工，预计出货时间延期至8月15日【新项目延期特殊批准按50%计算得分】 | M48: 0.5 | N48: 1 | O48: 0.5 | P48: 0.5 | Q48: 0.5 | R48: 2500 | S48: 2500 | T48: 5000 | U48: 品牌管理考核落地执行率 | V48: 考核落地执行率=当月实际考核设计落地数/当月考核设计落地目标数*100% | W48: 100 | X48: 完成部门考核100% | Y48: 无误 | Z48: 1 | AA48: 0.25 | AB48: 100
A49: FD-214672 | B49: 海外事业部-营销中心 | C49: 海外事业部-营销中心 | D49: 跨境营销经理 | E49: 易姑姑 | F49: 2026年07月 | G49: 海外事业部-营销中心-跨境营销经理/管培生 | H49: 个人贡献销售额 | I49: tt美区个人贡献销售额 | J49: 20000人民币 | K49: 15631.15人民币 | L49: 外标签完成，本体标签需重新设计和返工，预计出货时间延期至8月15日【新项目延期特殊批准按50%计算得分】 | M49: 0.7816 | N49: 0.7 | O49: 0.7816 | P49: 0.54712 | Q49: 0.55 | R49: 2750 | S49: 2750 | T49: 5000 | U49: 品牌管理考核落地执行率 | V49: 考核落地执行率=当月实际考核设计落地数/当月考核设计落地目标数*100% | W49: 100 | X49: 完成部门考核100% | Y49: 无误 | Z49: 1 | AA49: 0.25 | AB49: 100
A50: FD-216450 | B50: 海外事业部-营销中心 | C50: 海外事业部-营销中心 | D50: 管培生 | E50: 蔡沛心 | F50: 2026年07月 | G50: 海外事业部-营销中心-跨境营销经理/管培生 | H50: 个人贡献销售额 | I50: 6/7月自产素材 GMV≥20000元 50% | J50: 20000元 | K50: 35615元 | M50: 1 | N50: 0.5 | O50: 0.5 | P50: 0.922 | Q50: 0.93 | R50: 4650 | S50: 4650 | T50: 5000 | U50: 品牌管理考核落地执行率 | V50: 考核落地执行率=当月实际考核设计落地数/当月考核设计落地目标数*100% | W50: 100 | X50: 完成部门考核100% | Y50: 无误 | Z50: 1 | AA50: 0.25 | AB50: 100
A51: FD-217752 | B51: 海外事业部-运营中心 | C51: 海外事业部-运营中心 | D51: 跨境电商经理 | E51: 刘仁甫 | F51: 2026年07月 | G51: 海外事业部-营销中心-跨境营销经理/管培生 | H51: 个人贡献销售额 | I51: tt美区个人贡献销售额 | J51: 20000CNY | K51: 0CNY | M51: 0 | N51: 0.7 | O51: 0 | P51: 0 | Q51: 0 | R51: 0 | S51: 0 | T51: 4000 | U51: 品牌管理考核落地执行率 | V51: 考核落地执行率=当月实际考核设计落地数/当月考核设计落地目标数*100% | W51: 100 | X51: 完成部门考核100% | Y51: 无误 | Z51: 1 | AA51: 0.25 | AB51: 100
A52: FD-169942 | B52: AI效率流程部-AI效率流程E中心 | C52: AI效率流程部-AI效率流程E中心 | D52: AI工程师 | E52: 许伟淇 | F52: 2026年07月 | G52: AI效率流程部E中心绩效方案 | H52: 项目功能如期达标 | I52: 【AI客服】维护如期达成 【AI外呼】如期完成开发 | J52: 1 | K52: 0个 | L52: 外呼开发已完成；客服维护已完成 | M52: 0.9 | N52: 0.5 | O52: 0.9 | P52: 0.95 | Q52: 0.95 | R52: 4000 | S52: 4000 | T52: 4000 | U52: 品牌管理考核落地执行率 | V52: 考核落地执行率=当月实际考核设计落地数/当月考核设计落地目标数*100% | W52: 100 | X52: 完成部门考核100% | Y52: 无误 | Z52: 1 | AA52: 0.25 | AB52: 100
A53: FD-050189 | B53: 市场拓展部-资源开拓中心 | C53: 市场拓展部-资源开拓中心 | D53: 商务经理 | E53: 徐德志 | F53: 2026年07月 | G53: 市场拓展部-资源开拓中心-商务经理、管培生、见习高级经理-2606 | H53: 情报分析板块指标2606 | I53: 组织媒体&代理复盘-输出有价值的情报报告 | K53: 1 | L53: 视频BI开发已完成 | M53: 1 | N53: 0.3 | O53: 1 | P53: 0.84 | Q53: 0.84 | R53: 2400.24 | S53: 2400.24 | T53: 3000 | U53: 代理商返点变化&政策拆解; | W53: 1 | X53: 1 | Y53: 无误 | Z53: 1 | AA53: 0.3 | AB53: 100
A54: FD-052229 | B54: 市场拓展部-资源开拓中心 | C54: 市场拓展部-资源开拓中心 | D54: 管培生 | E54: 韦慕琪 | F54: 2026年07月 | G54: 市场拓展部-资源开拓中心-商务经理、管培生、见习高级经理-2606 | H54: 情报分析板块指标2606 | I54: 组织媒体&代理复盘-输出有价值的情报报告(共同指标，得分上限1.2)聚焦:1各平台信息&机会点;2代理商返点变化&政策拆解;3代理深入合作模式&机会【评分标准参考代理情报分析得分指标，需包括竞品合作信息】 | K54: 100 | L54: WIS水润面膜AI素材 合作渔悦轻舟 KONO视频号 AI混剪 合作云顶 | M54: 1 | N54: 0.3 | O54: 1 | P54: 0.6883 | Q54: 0.89 | R54: 5599.76 | S54: 5599.76 | T54: 5000 | U54: 100 | X54: 100 | Y54: 无误 | Z54: 1 | AA54: 0.3 | AB54: 100
A55: FD-050705 | B55: 市场拓展部-资源开拓中心 | C55: 市场拓展部-资源开拓中心 | D55: 管培生 | E55: 谷春炎 | F55: 2026年07月 | G55: 市场拓展部-资源开拓中心-商务经理、管培生、见习高级经理-2606 | H55: 兼职人员管理业务板块指标-方案2 | I55: 模特/主播/助播流程优化 | K55: 1 | L55: 7月新增合作需求剧饱饱，3条AI视频，7200，因客观需求原因未有新增需求，做部分折算 | M55: 1 | N55: 0.1 | O55: 1 | P55: 0.68172 | Q55: 0.85 | R55: 0 | S55: 0 | T55: 5000 | U55: 交付质量完成率 | V55: 100 | X55: 100 | Y55: 无误 | Z55: 1 | AA55: 0.7 | AB55: 100
A56: FD-054477 | B56: 市场拓展部-资源开拓中心 | C56: 市场拓展部-资源开拓中心 | D56: 数据助理 | E56: 王家雯 | F56: 2026年07月 | G56: 市场拓展部-资源开拓中心-数据助理 | H56: 数据助理-业绩考核 | I56: 项目需求(得分上限1.2) 主要:魔渍&墨雪-代运营,是否接入符合品牌要求供应商,并推进合作。 接入1家,0.6;接入2家;0.8,接入3家,1; 个人获取重要权益(经总监判断),额外+0.2 | J56: 1 | K56: 1 | L56: 媒介对接、5号需要出11月核账表初版,7号出11月最终可请款版;按时无误别完成品牌单下单;及时高效处理投放需求 | M56: 0.0125 | N56: 0.6 | O56: 1.25 | P56: 0.4935 | Q56: 1.5 | R56: 1800 | S56: 1800 | T56: 1200 | U56: 媒介对接 | V56: 处理充值、开户的及时性；按时统计数据、汇报数据的准确性；及时跟进品牌单下单及其他紧急需求 | W56: 日常行为符合公司价值观，在关键节点或压力下仍能坚持原则，有跨部门正向反馈 | X56: 100 | Y56: 无误 | Z56: 1.25 | AA56: 0.006 | AB56: 0.42
A57: OD-007945 | B57: 市场拓展部-资源开拓中心 | C57: 市场拓展部-资源开拓中心 | D57: 商务专员 | E57: 张佳丽 | F57: 2026年07月 | G57: 市场拓展部-资源开拓中心-兼职管理组-商务专员 | H57: 兼职管理组-上级考核指标 | I57: 评定项目 详细描述 得分 价值观 个人积极践行公司奋进、正直、自我批判、以用户为中心的核心价值观 直属上级评分 | J57: 1 | K57: 0 | L57: 媒介对接、5号需要出11月核账表初版,7号出11月最终可请款版;按时无误别完成品牌单下单;及时高效处理投放需求 | M57: 1 | N57: 0.1 | O57: 1 | P57: 1 | Q57: 1.1 | R57: 0 | S57: 0 | T57: 1200 | U57: 主动思考/创新思维 | V57: 是否具备流程优化等创新思维 | W57: 遇到流程卡点或异常情况时，能主动分析原因并提出解决思路，解决思路有比较好的实践结果 | X57: 0.4 | Y57: 无误 | Z57: 1 | AA57: 0.0025 | AB57: 0.3
A58: FD-233625 | B58: 凡岛研究院-机理研究实验室 | C58: 凡岛研究院-机理研究实验室 | D58: 研究员 | E58: 余宇潇 | F58: 2026年07月 | G58: 凡岛研究院机理研究实验室研究员考核方案3.1 | H58: 价值探索项目 | I58: KONO防脱低共熔萃取技术开发 | J58: 1 | K58: 0 | L58: 7.10体系确定和初提成功；7.28完成提取技术优化方案制定，完成HPLC体系构建，并完成标准曲线和提取率的测定。 | M58: 1 | N58: 0.5 | O58: 1 | P58: 1 | Q58: 1 | R58: 2800 | S58: 2800 | T58: 3500 | U58: 主动思考/创新思维 | V58: 是否具备流程优化等创新思维 | W58: 遇到流程卡点或异常情况时，能主动分析原因并提出解决思路，解决思路有比较好的实践结果 | X58: 0.4 | Y58: 无误 | Z58: 1 | AA58: 0.0025 | AB58: 0.3
A59: FD-238128 | B59: 凡岛研究院-机理研究实验室 | C59: 凡岛研究院-机理研究实验室 | D59: 研究员 | E59: 张立青 | F59: 2026年07月 | G59: 凡岛研究院机理研究实验室研究员考核方案3.1 | H59: 技术开发项目 | I59: 7月28日前完成蓬松度测试方法学优化，建立稳定可靠的评价体系 | J59: 1 | K59: 0 | L59: 1 | M59: 1 | N59: 0.2 | O59: 1 | P59: 0.97 | Q59: 0.97 | R59: 2716 | S59: 2716 | T59: 3500 | U59: 主动思考/创新思维 | V59: 是否具备流程优化等创新思维 | W59: 遇到流程卡点或异常情况时，能主动分析原因并提出解决思路，解决思路有比较好的实践结果 | X59: 0.4 | Y59: 无误 | Z59: 1 | AA59: 0.0025 | AB59: 0.3
A60: FD-235981 | B60: 凡岛研究院-机理研究实验室 | C60: 凡岛研究院-机理研究实验室 | D60: 研究员 | E60: 蒋孟坪 | F60: 2026年07月 | G60: 凡岛研究院机理研究实验室研究员考核方案3.1 | H60: 技术开发项目 | I60: 7.28前完成KONO香氛洗发水升级方案 | J60: 1 | K60: 0 | L60: 完成调研和香精筛选，项目中止 | M60: 0.3 | N60: 0.3 | O60: 0.3 | P60: 0.79 | Q60: 0.79 | R60: 2212 | S60: 2212 | T60: 3500 | U60: 主动思考/创新思维 | V60: 是否具备流程优化等创新思维 | W60: 遇到流程卡点或异常情况时，能主动分析原因并提出解决思路，解决思路有比较好的实践结果 | X60: 0.4 | Y60: 无误 | Z60: 1 | AA60: 0.0025 | AB60: 0.3
A61: FD-236367 | B61: 凡岛研究院 | C61: 凡岛研究院 | D61: 科学传播经理 | E61: 李温情 | F61: 2026年07月 | G61: 科学传播绩效方案 | H61: 活动组织 | I61: 一、Q2研发实力调研 1. 收集Q2季度公司岛民对内、对外的研发实力认可度 2. 形成调研分析报告，剖析科传工作潜在问题及改进方案 3. 召开组织研讨会，优化下半年工作改进方案 二、KONO白皮书/标准的制定 1. 跟进品牌科学背书资源立项意向 2. 对接第三方沟通合作形式和报价 3. 持续跟进后续科学背书动作 | J61: 1 | K61: 0 | L61: 已完成分享 | M61: 1 | N61: 0.5 | O61: 1 | P61: 1 | Q61: 1 | R61: 3000 | S61: 3000 | T61: 3000 | U61: 主动思考/创新思维 | V61: 是否具备流程优化等创新思维 | W61: 遇到流程卡点或异常情况时，能主动分析原因并提出解决思路，解决思路有比较好的实践结果 | X61: 0.4 | Y61: 无误 | Z61: 1 | AA61: 0.0025 | AB61: 0.3
A62: FD-035770 | B62: 广告策划部-创新B中心 | C62: 广告策划部-创新B中心 | D62: 管培生 | E62: 高智琪 | F62: 2026年07月 | G62: 创新B营销经理绩效方案-5月 | H62: 团队关键工作-营业额/利润类 | I62: 达人GSV360w（整体成交*0.88） | J62: 360万元 | K62: 379万元 | L62: 达人计划+原片投放/分发，统计均按gmv*0.88，详见附件 | M62: 1.05 | N62: 0.3 | O62: 1.05 | P62: 0.915 | Q62: 0.92 | R62: 8400 | S62: 8400 | T62: 6000 | U62: 主动思考/创新思维 | V62: 是否具备流程优化等创新思维 | W62: 遇到流程卡点或异常情况时，能主动分析原因并提出解决思路，解决思路有比较好的实践结果 | X62: 0.4 | Y62: 无误 | Z62: 1 | AA62: 0.0025 | AB62: 0.3
A63: FD-038821 | B63: 广告策划部-创新B中心 | C63: 广告策划部-创新B中心 | D63: 管培生 | E63: 陈秋汛 | F63: 2026年07月 | G63: 创新B营销经理绩效方案-5月 | H63: 个人GSV达成率得分 | I63: 达人成交GSV70w（计划净成交＜2.1总ROI＜2.1不纳入计算） | J63: 70万元 | K63: 59万元 | M63: 0.85 | N63: 0.5 | O63: 0.85 | P63: 0.721 | Q63: 0.67 | R63: 3600 | S63: 3600 | T63: 6000 | U63: 主动思考/创新思维 | V63: 是否具备流程优化等创新思维 | W63: 遇到流程卡点或异常情况时，能主动分析原因并提出解决思路，解决思路有比较好的实践结果 | X63: 0.4 | Y63: 无误 | Z63: 1 | AA63: 0.0025 | AB63: 0.3
A64: FD-030061 | B64: 广告策划部-创新B中心 | C64: 广告策划部-创新B中心 | D64: 管培生 | E64: 林亦菲 | F64: 2026年07月 | G64: 创新B营销经理绩效方案-5月 | H64: 个人GSV达成率得分 | I64: 成交20w | J64: 20万元 | K64: 16.4938万元 | M64: 0.825 | N64: 0.6 | O64: 0.825 | P64: 0.6008 | Q64: 0.6 | R64: 0 | S64: 0 | T64: 6000 | U64: 主动思考/创新思维 | V64: 是否具备流程优化等创新思维 | W64: 遇到流程卡点或异常情况时，能主动分析原因并提出解决思路，解决思路有比较好的实践结果 | X64: 0.4 | Y64: 无误 | Z64: 1 | AA64: 0.0025 | AB64: 0.3
A65: FD-034631 | B65: 广告策划部-创新B中心 | C65: 广告策划部-创新B中心 | D65: 管培生 | E65: 朱晴 | F65: 2026年07月 | G65: 创新B营销经理绩效方案-5月 | H65: 个人GSV达成率得分 | I65: 个人达人GSV70w | J65: 70万元 | K65: 13.65万元 | M65: 0.195 | N65: 0.5 | O65: 0.195 | P65: 0.314 | Q65: 0.31 | R65: 0 | S65: 0 | T65: 6000 | U65: 主动思考/创新思维 | V65: 是否具备流程优化等创新思维 | W65: 遇到流程卡点或异常情况时，能主动分析原因并提出解决思路，解决思路有比较好的实践结果 | X65: 0.4 | Y65: 无误 | Z65: 1 | AA65: 0.0025 | AB65: 0.3
A66: FD-030900 | B66: 广告策划部-创新B中心 | C66: 广告策划部-创新B中心 | D66: 营销经理 | E66: 肖烨涛 | F66: 2026年07月 | G66: 创新B营销经理绩效方案-5月 | H66: 团队关键工作-营业额/利润类 | I66: 视频号渠道GSV 90W； | J66: 90万元 | K66: 1750720.56万元 | L66: 7月视频号总成交：1750720.56 | M66: 1.5 | N66: 0.3 | O66: 1.5 | P66: 0.93 | Q66: 0.93 | R66: 0 | S66: 0 | T66: 5000 | U66: 主动思考/创新思维 | V66: 是否具备流程优化等创新思维 | W66: 遇到流程卡点或异常情况时，能主动分析原因并提出解决思路，解决思路有比较好的实践结果 | X66: 0.4 | Y66: 无误 | Z66: 1 | AA66: 0.0025 | AB66: 0.3
A67: OD-005497 | B67: 广告策划部-创新B中心 | C67: 广告策划部-创新B中心 | D67: 营销策划 | E67: 曾秀芬 | F67: 2026年07月 | G67: 创新B营销策划绩效方案 | H67: 个人GSV达成率得分 | I67: 搭建FANDO工作流，跑出3条成交＞5w的素材 | J67: 15万元 | K67: 75.45万元 | L67: 搭建批量替换产品和自动创建数字人skill但是需要走fando路线；未能产出爆量素材 | M67: 5.03 | N67: 0.7 | O67: 5.03 | P67: 3.821 | Q67: 3.82 | R67: 2855.17 | S67: 3155.17 | T67: 1200 | U67: 主动思考/创新思维 | V67: 是否具备流程优化等创新思维 | W67: 遇到流程卡点或异常情况时，能主动分析原因并提出解决思路，解决思路有比较好的实践结果 | X67: 0.4 | Y67: 无误 | Z67: 1 | AA67: 0.0025 | AB67: 0.3
A68: OD-000819 | B68: 广告策划部-创新B中心 | C68: 广告策划部-创新B中心 | D68: 营销策划 | E68: 彭于宴 | F68: 2026年07月 | G68: 创新B营销策划绩效方案 | H68: 个人GSV达成率得分 | I68: 个人GSV达成15W | J68: 15W | K68: 59.2W | L68: 搭建批量替换产品和自动创建数字人skill但是需要走fando路线；未能产出爆量素材 | M68: 3.94 | N68: 0.7 | O68: 3.94 | P68: 3.358 | Q68: 3.36 | R68: 2637.93 | S68: 3537.93 | T68: 1500 | U68: 主动思考/创新思维 | V68: 是否具备流程优化等创新思维 | W68: 遇到流程卡点或异常情况时，能主动分析原因并提出解决思路，解决思路有比较好的实践结果 | X68: 0.4 | Y68: 无误 | Z68: 1 | AA68: 0.0025 | AB68: 0.3
A69: OD-003105 | B69: 广告策划部-创新B中心 | C69: 广告策划部-创新B中心 | D69: 营销策划 | E69: 邢维琪 | F69: 2026年07月 | G69: 创新B营销策划绩效方案 | H69: 个人GSV达成率得分 | I69: KOC扣退销售额70w | J69: 70万元 | K69: 73万元 | L69: 大于70w | M69: 1.05 | N69: 0.2 | O69: 1.1471 | P69: 0.51 | Q69: 0.56 | R69: 1706.9 | S69: 1706.9 | T69: 1500 | U69: 主动思考/创新思维 | V69: 是否具备流程优化等创新思维 | W69: 遇到流程卡点或异常情况时，能主动分析原因并提出解决思路，解决思路有比较好的实践结果 | X69: 0.4 | Y69: 无误 | Z69: 1 | AA69: 0.0025 | AB69: 0.3
A70: OD-004552 | B70: 广告策划部-创新B中心 | C70: 广告策划部-创新B中心 | D70: 营销策划 | E70: 邓小妹 | F70: 2026年07月 | G70: 创新B营销策划绩效方案 | H70: 个人GSV达成率得分 | I70: GSV15w | J70: 15万元 | K70: 24.6万元 | L70: 交片只有2个 | M70: 1.64 | N70: 0.7 | O70: 1.5 | P70: 1.148 | Q70: 1.05 | R70: 2172.41 | S70: 2172.41 | T70: 1500 | U70: 主动思考/创新思维 | V70: 是否具备流程优化等创新思维 | W70: 遇到流程卡点或异常情况时，能主动分析原因并提出解决思路，解决思路有比较好的实践结果 | X70: 0.4 | Y70: 无误 | Z70: 1 | AA70: 0.0025 | AB70: 0.3
A71: OD-008726 | B71: 广告策划部-创新B中心 | C71: 广告策划部-创新B中心 | D71: 营销策划 | E71: 王陈陈 | F71: 2026年07月 | G71: 创新B营销策划绩效方案 | H71: 个人GSV达成率得分 | I71: GSV10w | J71: 10万元 | K71: 7.7万元 | L71: 交片只有2个 | M71: 0.77 | N71: 0.7 | O71: 0.616 | P71: 0.539 | Q71: 0.43 | R71: 1241.38 | S71: 1241.38 | T71: 1500 | U71: 主动思考/创新思维 | V71: 是否具备流程优化等创新思维 | W71: 遇到流程卡点或异常情况时，能主动分析原因并提出解决思路，解决思路有比较好的实践结果 | X71: 0.4 | Y71: 无误 | Z71: 1 | AA71: 0.0025 | AB71: 0.3
A72: OD-007783 | B72: 广告策划部-创新B中心 | C72: 广告策划部-创新B中心 | D72: 营销策划 | E72: 王德玉 | F72: 2026年07月 | G72: 创新B营销策划绩效方案 | H72: 个人GSV达成率得分 | I72: GSV15w | J72: 15万元 | K72: 2万元 | L72: 交片只有2个 | M72: 0.134 | N72: 0.7 | O72: 0.1067 | P72: 0.0938 | Q72: 0.07 | R72: 310.34 | S72: 310.34 | T72: 1500 | U72: 主动思考/创新思维 | V72: 是否具备流程优化等创新思维 | W72: 遇到流程卡点或异常情况时，能主动分析原因并提出解决思路，解决思路有比较好的实践结果 | X72: 0.4 | Y72: 无误 | Z72: 1 | AA72: 0.0025 | AB72: 0.3
A73: OD-006016 | B73: 广告策划部-创新B中心 | C73: 广告策划部-创新B中心 | D73: 营销策划 | E73: 周安 | F73: 2026年07月 | G73: 创新B营销策划绩效方案 | H73: 个人GSV达成率得分 | I73: 净gsv15w | J73: 15万元 | K73: 0.35万元 | L73: 交片只有2个 | M73: 0.035 | N73: 0.7 | O73: 0.028 | P73: 0.0245 | Q73: 0.02 | R73: 0 | S73: 0 | T73: 1500 | U73: 主动思考/创新思维 | V73: 是否具备流程优化等创新思维 | W73: 遇到流程卡点或异常情况时，能主动分析原因并提出解决思路，解决思路有比较好的实践结果 | X73: 0.4 | Y73: 无误 | Z73: 1 | AA73: 0.0025 | AB73: 0.3
A74: OD-001875 | B74: 广告策划部-创新B中心 | C74: 广告策划部-创新B中心 | D74: 营销策划 | E74: 吴培鑫 | F74: 2026年07月 | G74: 创新B营销策划绩效方案 | H74: 个人GSV达成率得分 | I74: KPI指标: GSV10w | J74: 10万元 | K74: 3.1万元 | L74: 交片只有2个 | M74: 0.31 | N74: 0.7 | O74: 0.248 | P74: 0.217 | Q74: 0.17 | R74: 775.86 | S74: 775.86 | T74: 1500 | U74: 主动思考/创新思维 | V74: 是否具备流程优化等创新思维 | W74: 遇到流程卡点或异常情况时，能主动分析原因并提出解决思路，解决思路有比较好的实践结果 | X74: 0.4 | Y74: 无误 | Z74: 1 | AA74: 0.0025 | AB74: 0.3
A75: FD-045919 | B75: 新品牌事业部-品牌创意中心 | C75: 新品牌事业部-品牌创意中心 | D75: 产品经理 | E75: 缪心雨 | F75: 2026年07月 | G75: 【新品牌事业部-品牌创意中心】产品经理、供应链经理绩效考核方案 | H75: 品牌背书与卖点方案策划 | I75: 品牌与产品背书落地推进与持续挖掘 | K75: 85 | L75: 已通过的方案落地完成，新的背书正在下推中 | M75: 0.85 | N75: 0.4 | O75: 0.85 | P75: 0.845 | Q75: 0.8 | R75: 3990.1 | S75: 3990.1 | T75: 5000 | U75: 1. 已明确方案-50%：（网媒&商标）根据项目甘特图计算完成率 | X75: 90 | Y75: 无误 | Z75: 0.9 | AA75: 0.5 | AB75: 0.3
A76: FD-081018 | B76: 新品牌事业部-品牌创意中心 | C76: 新品牌事业部-品牌创意中心 | D76: 管培生 | E76: 廖佳睿 | F76: 2026年07月 | G76: 【新品牌事业部-品牌创意中心】产品经理、供应链经理绩效考核方案 | H76: 品牌背书与卖点方案策划 | I76: 可麦品牌宣讲会 | K76: 0.8 | L76: 提案通过，但是缺少香味渠道测试方案 | M76: 0.8 | N76: 0.4 | O76: 0.8 | P76: 0.845 | Q76: 0.85 | R76: 4782.4 | S76: 4782.4 | T76: 5000 | U76: 品牌宣讲会资料准备&对齐 | V76: 确定宣讲会的结构、流程、内容，并制作讲稿&ppt，与上级对齐后通过 | X76: 0.5 | Y76: 无误 | Z76: 1 | AA76: 0.5 | AB76: 0.3
A77: FD-082754 | B77: 新品牌事业部-品牌创意中心 | C77: 新品牌事业部-品牌创意中心 | D77: 供应链经理 | E77: 张丽丽 | F77: 2026年07月 | G77: 【新品牌事业部-品牌创意中心】产品经理、供应链经理绩效考核方案 | H77: 库存健康周转 | I77: 1. 主品-洗发水+护发素（80%）：周转天数控制在10-20天（护发素可以在10-25天；洗发水新旧品过渡期间可不算）；2. 延展品（20%）：400g规格落地，并保证基础安全库存数量 | K77: 93.4 | L77: 1. 甄选款洗发水周转天数在10-20天范围内共29天，达标率93.5%。 2. 护发素周转天数在10-25天范围内共23天，达标率100%。 [图片] 3. 延展品库存情况达标率80%。 - 沐浴露、云柔规格已换； - 净屑已生产完毕； - 防脱当前库存周转满足需求，且400g瓶子已生产，泵头已生产，成品待生产； - 轻悦需求低，当前总库存7000左右，满足需求，且有多余旧版包材，可随时做货。 | M77: 0.934 | N77: 0.3 | O77: 0.934 | P77: 0.8822 | Q77: 0.82 | R77: 3071.3 | S77: 3071.3 | T77: 3000 | U77: 主推品周转健康天数率 | V77: 针对主推产品满足周转天数范围 | X77: 96.75 | Y77: 1. 甄选款洗发水周转天数在10-20天范围内共29天，达标率93.5%。 2. 护发素周转天数在10-25天范围内共23天，达标率100%。 | Z77: 0.9675 | AA77: 0.8 | AB77: 96.75
A78: FD-083319 | B78: 新品牌事业部-品牌创意中心 | C78: 新品牌事业部-品牌创意中心 | D78: 供应链经理 | E78: 许蕊 | F78: 2026年07月 | G78: 【新品牌事业部-品牌创意中心】产品经理、供应链经理绩效考核方案 | H78: 产品开发落地 | I78: P0项目 1.墨雪8,9号箱打样完成 2.奢享款泵头限度样确认 3.鑫凯泵头跟色 4.400g标贴上机测试 5.奢享款瓶子打样测试（沪汇） | K78: 87.5 | L78: 1. 打样已完成 2. 第二模具奢享款，护发素品控测试完成 3. 三家已上机测试，嘉信，花田已输出报价 4. 鑫凯奢享款已做货 | M78: 0.88 | N78: 0.4 | O78: 0.88 | P78: 0.841 | Q78: 0.84 | R78: 3234.5 | S78: 3234.5 | T78: 3000 | U78: 可麦包材消耗方案 | X78: 80 | Y78: 3. 延展品库存情况达标率80%。 - 沐浴露、云柔规格已换； - 净屑已生产完毕； - 防脱当前库存周转满足需求，且400g瓶子已生产，泵头已生产，成品待生产； - 轻悦需求低，当前总库存7000左右，满足需求，且有多余旧版包材，可随时做货。 | Z78: 0.8 | AA78: 0.4 | AB78: 32
A79: FD-086548 | B79: 新品牌事业部-品牌创意中心 | C79: 新品牌事业部-品牌创意中心 | D79: 供应链经理 | E79: 覃京旺 | F79: 2026年07月 | G79: 【新品牌事业部-品牌创意中心】产品经理、供应链经理绩效考核方案 | H79: 库存健康周转 | I79: 周转天数控制在7-40天（魔渍、墨雪各占比50%） 如魔渍因为新品/前端需求变动，适当调整得分情况 | K79: 1 | L79: 1、墨雪按时到货，周转健康。2、魔渍机制调整，后续不投入资源，以消耗为主 | M79: 1 | N79: 0.3 | O79: 1 | P79: 0.84 | Q79: 0.84 | R79: 3350.9 | S79: 3350.9 | T79: 3000 | U79: 主推品周转健康天数率 | V79: 针对主推产品满足周转天数范围 | X79: 1 | Y79: 主推品周转保持健康，墨雪正常到货 | Z79: 1 | AA79: 0.8 | AB79: 80
A80: OD-004665 | B80: 新品牌事业部-品牌创意中心 | C80: 新品牌事业部-品牌创意中心 | D80: 订单交付员 | E80: 张晓琳 | F80: 2026年07月 | G80: 【新品牌事业部-品牌创意中心】订单交付员绩效考核方案 | H80: 物料盘点与监控 | I80: 资产负债表完成、安全库存储备 | J80: 0.3 | K80: 1 | L80: 7月资产负债表-卡板、包材、周转箱已完成；可麦库存数量 | M80: 1 | N80: 0.3 | O80: 100 | P80: 0.888 | Q80: 88.8 | R80: 852.5 | S80: 852.5 | T80: 1200 | U80: 资产负债表完成准时率 | X80: 100 | Y80: 1、包材供应商确认无法回收2、推动墨雪线下洗护、洗护沐周转箱、墨雪1号周转箱的测算，并测试合格后将信息同步给物流中心进行消耗。3、盖子与供应部确认，供应部在测试，预计8月8号出结果，测试能用的话预计能消耗10万 | Z80: 1 | AA80: 0.4 | AB80: 100
A81: OD-001988 | B81: 新品牌事业部-品牌创意中心 | C81: 新品牌事业部-品牌创意中心 | D81: 订单交付员 | E81: 黄林欣 | F81: 2026年07月 | G81: 【新品牌事业部-品牌创意中心】订单交付员绩效考核方案 | H81: 物料盘点与监控 | I81: 可麦独有原料监控 | J81: 0.3 | K81: 0.3 | L81: 资产负债表按时提交，每月物料监控有序完成 | M81: 1 | N81: 0.3 | O81: 1 | P81: 0.9825 | Q81: 0.98 | R81: 1482.2 | S81: 1482.2 | T81: 1500 | U81: 资产负债表完成准时率 | W81: 0.4 | X81: 40 | Y81: 准时提交 | Z81: 0.4 | AA81: 0.4 | AB81: 100
A82: SQ-008075 | B82: 财务部-财务分析中心 | C82: 财务部-财务分析中心 | D82: 财务实习生 | E82: 姜诺诺 | F82: 2026年07月 | G82: 财务分析中心绩效考核方案-07 | H82: 重要项目完成率 | I82: 每月20%权重：10%报表出具+10%核对无误 | K82: 0.975 | L82: MVE试产原料延期送达，准时率95。 | M82: 1 | N82: 0.8 | O82: 80 | P82: 0.96 | Q82: 0.96 | R82: 0 | S82: 0 | T82: 0 | U82: 关键物料安全库存达标率 | W82: 0.6 | X82: 60 | Y82: 准时提交 | Z82: 0.6 | AA82: 0.6 | AB82: 100
A83: FD-082560 | B83: 电商发展部-达播中心 | C83: 电商发展部-达播中心 | D83: 商务经理 | E83: 李国斌 | F83: 2026年07月 | G83: 达播商务绩效考核方案V3 | H83: GSV目标完成率【达播】 | I83: WIS达播GSV | J83: 3000000元 | K83: 646854元 | L83: MVE试产原料延期送达，准时率95。 | M83: 0.215618 | N83: 0.25 | O83: 0.2156 | P83: 0.373905 | Q83: 0.37 | R83: 3534.14 | S83: 3534.14 | T83: 5000 | U83: 关键物料安全库存达标率 | W83: 0.6 | X83: 60 | Y83: 准时提交 | Z83: 0.6 | AA83: 0.6 | AB83: 100
A84: FD-154390 | B84: 电商发展部-达播中心 | C84: 电商发展部-达播中心 | D84: 商务经理 | E84: 慎轩 | F84: 2026年07月 | G84: 达播商务绩效考核方案V3 | H84: GSV目标完成率【达播】 | I84: 赫系达播GSV | J84: 400000元 | K84: 99500.76元 | L84: MVE试产原料延期送达，准时率95。 | M84: 0.248752 | N84: 0.25 | O84: 0.2488 | P84: 0.118188 | Q84: 0.12 | R84: 2208.84 | S84: 2208.84 | T84: 5000 | U84: 关键物料安全库存达标率 | W84: 0.6 | X84: 60 | Y84: 准时提交 | Z84: 0.6 | AA84: 0.6 | AB84: 100
A85: FD-058439 | B85: 电商发展部-达播中心 | C85: 电商发展部-达播中心 | D85: 管培生 | E85: 赵麒翔 | F85: 2026年07月 | G85: 达播商务绩效考核方案V3 | H85: GSV目标完成率【达播】 | I85: KONO销售额 | J85: 650000元 | K85: 731596.7元 | L85: MVE试产原料延期送达，准时率95。 | M85: 1.125533 | N85: 0.25 | O85: 1.1255 | P85: 1.620468 | Q85: 0.97 | R85: 7068.27 | S85: 7068.27 | T85: 5000 | U85: 关键物料安全库存达标率 | W85: 0.6 | X85: 60 | Y85: 准时提交 | Z85: 0.6 | AA85: 0.6 | AB85: 100
A86: FD-054520 | B86: 电商发展部-达播中心 | C86: 电商发展部-达播中心 | D86: 商务PR | E86: 李暄 | F86: 2026年07月 | G86: 达播商务绩效考核方案V3 | H86: GSV目标完成率【达播】 | I86: 赫系GSV | J86: 500000元 | K86: 400059.93元 | L86: MVE试产原料延期送达，准时率95。 | M86: 0.80012 | N86: 0.25 | O86: 0.8001 | P86: 1.08337 | Q86: 1.06 | R86: 3887.55 | S86: 3887.55 | T86: 2000 | U86: 关键物料安全库存达标率 | W86: 0.6 | X86: 60 | Y86: 准时提交 | Z86: 0.6 | AA86: 0.6 | AB86: 100
A87: FD-052083 | B87: 电商发展部-达播中心 | C87: 电商发展部-达播中心 | D87: 商务经理 | E87: 许敏丽 | F87: 2026年07月 | G87: 达播商务绩效考核方案V3 | H87: GSV目标完成率【达播】 | I87: KONO达播GSV | J87: 400000元 | K87: 260626.5元 | L87: MVE试产原料延期送达，准时率95。 | M87: 0.651566 | N87: 0.25 | O87: 0.6516 | P87: 0.62279 | Q87: 0.62 | R87: 5301.2 | S87: 5301.2 | T87: 5000 | U87: 关键物料安全库存达标率 | W87: 0.6 | X87: 60 | Y87: 准时提交 | Z87: 0.6 | AA87: 0.6 | AB87: 100
A88: FD-061817 | B88: 电商发展部-达播中心 | C88: 电商发展部-达播中心 | D88: 管培生 | E88: 付文雅 | F88: 2026年07月 | G88: 达播商务绩效考核方案V3 | H88: GSV目标完成率【达播】 | I88: WIS达播GSV | J88: 300000元 | K88: 201714元 | L88: MVE试产原料延期送达，准时率95。 | M88: 0.67238 | N88: 0.25 | O88: 0.6724 | P88: 0.408095 | Q88: 0.41 | R88: 0 | S88: 0 | T88: 5000 | U88: 关键物料安全库存达标率 | W88: 0.6 | X88: 60 | Y88: 准时提交 | Z88: 0.6 | AA88: 0.6 | AB88: 100
A89: FD-067782 | B89: 电商发展部-达播中心 | C89: 电商发展部-达播中心 | D89: 商务PR | E89: 劳浩桓 | F89: 2026年07月 | G89: 达播商务绩效考核方案V3 | H89: GSV目标完成率【达播】 | I89: 赫系&WIS达播GSV | J89: 100000元 | K89: 50475.3元 | L89: MVE试产原料延期送达，准时率95。 | M89: 0.504753 | N89: 0.25 | O89: 0.5048 | P89: 0.286188 | Q89: 0.29 | R89: 0 | S89: 0 | T89: 2000 | U89: 关键物料安全库存达标率 | W89: 0.6 | X89: 60 | Y89: 准时提交 | Z89: 0.6 | AA89: 0.6 | AB89: 100
A90: FD-051468 | B90: 电商发展部-达播中心 | C90: 电商发展部-达播中心 | D90: 商务PR | E90: 张晓璐 | F90: 2026年07月 | G90: 日播绩效考核方案V3 | H90: GSV目标完成率【日播】 | I90: 赫系日播gsv | J90: 3500000元 | K90: 4057637.47元 | L90: MVE试产原料延期送达，准时率95。 | M90: 1.159325 | N90: 0.35 | O90: 1.1593 | P90: 1.282671 | Q90: 1.38 | R90: 2400 | S90: 2400 | T90: 2000 | U90: 关键物料安全库存达标率 | W90: 0.6 | X90: 60 | Y90: 准时提交 | Z90: 0.6 | AA90: 0.6 | AB90: 100
A91: FD-060719 | B91: 电商发展部-达播中心 | C91: 电商发展部-达播中心 | D91: 商务PR | E91: 郑若蓥 | F91: 2026年07月 | G91: 日播绩效考核方案V3 | H91: GSV目标完成率【日播】 | I91: WIS日播GSV | J91: 1300000元 | K91: 1169390元 | L91: MVE试产原料延期送达，准时率95。 | M91: 0.899531 | N91: 0.35 | O91: 0.8995 | P91: 0.850534 | Q91: 0.85 | R91: 0 | S91: 0 | T91: 2000 | U91: 关键物料安全库存达标率 | W91: 0.6 | X91: 60 | Y91: 准时提交 | Z91: 0.6 | AA91: 0.6 | AB91: 100
A92: FD-057312 | B92: 电商发展部-达播中心 | C92: 电商发展部-达播中心 | D92: 管培生 | E92: 张子晗 | F92: 2026年07月 | G92: 组长绩效考核方案V3 | H92: GSV目标完成率【组长】 | I92: KONO销售额 | J92: 1500000元 | K92: 1368869元 | L92: MVE试产原料延期送达，准时率95。 | M92: 0.912579 | N92: 0.3 | O92: 0.9126 | P92: 0.813489 | Q92: 0.81 | R92: 8000 | S92: 8000 | T92: 5000 | U92: 关键物料安全库存达标率 | W92: 0.6 | X92: 60 | Y92: 准时提交 | Z92: 0.6 | AA92: 0.6 | AB92: 100
A93: FD-050397 | B93: 电商发展部-达播中心 | C93: 电商发展部-达播中心 | D93: 管培生 | E93: 肖茹梦 | F93: 2026年07月 | G93: 组长绩效考核方案V3 | H93: GSV目标完成率【组长】 | I93: 赫系销售额 | J93: 4500000元 | K93: 4757312.708元 | L93: MVE试产原料延期送达，准时率95。 | M93: 1.057181 | N93: 0.3 | O93: 1.0572 | P93: 0.651226 | Q93: 0.65 | R93: 2000 | S93: 2000 | T93: 5000 | U93: 关键物料安全库存达标率 | W93: 0.6 | X93: 60 | Y93: 准时提交 | Z93: 0.6 | AA93: 0.6 | AB93: 100
A94: FD-055641 | B94: 电商发展部-达播中心 | C94: 电商发展部-达播中心 | D94: 管培生 | E94: 戴琼瑶 | F94: 2026年07月 | G94: 组长绩效考核方案V3 | H94: GSV目标完成率【组长】 | I94: WIS销售额 | J94: 2500000元 | K94: 1759105元 | L94: MVE试产原料延期送达，准时率95。 | M94: 0.703642 | N94: 0.3 | O94: 0.7036 | P94: 0.671785 | Q94: 0.66 | R94: 5000 | S94: 5000 | T94: 5000 | U94: 关键物料安全库存达标率 | W94: 0.6 | X94: 60 | Y94: 准时提交 | Z94: 0.6 | AA94: 0.6 | AB94: 100
A95: FD-012998 | B95: 总经办-总助模块 | C95: 总经办-总助模块 | D95: 内控审计经理 | E95: 杜益 | F95: 2026年07月 | G95: 内控审计经理绩效考核方案-7月 | H95: 内控关键工作得分 | I95: O1：完成内控BI看板的制作和更新运行 O2：开课一节；撰写部门内控手册模板 O3：跨部门业务穿行测试准备与计划 | L95: MVE试产原料延期送达，准时率95。 | M95: 1 | N95: 0.4 | O95: 1 | P95: 0.7505 | Q95: 0.8 | R95: 4000 | S95: 4000 | T95: 5000 | U95: 关键物料安全库存达标率 | W95: 0.6 | X95: 60 | Y95: 准时提交 | Z95: 0.6 | AA95: 0.6 | AB95: 100
A96: FD-015700 | B96: 总经办-总助模块 | C96: 总经办-总助模块 | D96: 高级经理 | E96: 丁小恬 | F96: 2026年07月 | G96: 战略落地小组绩效考核方案 | H96: AI工作流指标 | I96: 全公司单日token | J96: 200亿token | K96: 188亿token | L96: 7月16日达7月最高188亿token | M96: 0.94 | N96: 0.3 | O96: 0.94 | P96: 0.9584 | Q96: 1.02 | R96: 5020 | S96: 5020 | T96: 5000 | U96: 关键物料安全库存达标率 | W96: 0.6 | X96: 60 | Y96: 准时提交 | Z96: 0.6 | AA96: 0.6 | AB96: 100
A97: FD-010340 | B97: 总经办-总助模块 | C97: 总经办-总助模块 | D97: 总经理助理 | E97: 王伊瑄 | F97: 2026年07月 | G97: 战略落地小组绩效考核方案 | H97: 共识传播指标 | I97: 高管团建 | J97: 1 | K97: 1 | L97: 已完成 | M97: 1 | N97: 0.1 | O97: 1 | P97: 0.62425 | Q97: 0.61 | R97: 4610 | S97: 4610 | T97: 5000 | U97: 关键物料安全库存达标率 | W97: 0.6 | X97: 60 | Y97: 准时提交 | Z97: 0.6 | AA97: 0.6 | AB97: 100
A98: FD-046307 | B98: 总经办-总助模块 | C98: 总经办-总助模块 | D98: 总经理助理 | E98: 李奥宇 | F98: 2026年07月 | G98: 战略落地小组绩效考核方案 | H98: 有效决议梳理 | I98: 助理团队能力及凝聚力提升方案 | J98: 1个 | K98: 1个 | L98: AI视频精品未完成；根数据，公关和投资完成逐字稿梳理，公关完成根数据整理，其余均未完成 | M98: 1 | N98: 0.5 | O98: 1 | P98: 1 | Q98: 1 | R98: 5000 | S98: 5000 | T98: 5000 | U98: 关键物料安全库存达标率 | W98: 0.6 | X98: 60 | Y98: 准时提交 | Z98: 0.6 | AA98: 0.6 | AB98: 100
A99: FD-179378 | B99: 总经办-总助模块 | C99: 总经办-总助模块 | D99: 顾问 | E99: 高璐 | F99: 2026年07月 | G99: 战略落地小组绩效考核方案 | H99: 战略项目完成率 | I99: 1. 根数据品牌营销完成应用 | J99: 1 | L99: 存储调用不达预期, 未全部完成 | M99: 0.5 | N99: 0.25 | O99: 0.4 | P99: 0.877 | Q99: 0.94 | R99: 10820 | S99: 10820 | T99: 11000 | U99: 关键物料安全库存达标率 | W99: 0.6 | X99: 60 | Y99: 准时提交 | Z99: 0.6 | AA99: 0.6 | AB99: 100
A100: FD-025283 | B100: 总经办-总助模块 | C100: 总经办-总助模块 | D100: 高级经理 | E100: 李楠 | F100: 2026年07月 | G100: 战略落地小组绩效考核方案 | H100: 战略项目完成率 | I100: 营销内容创作体系AI化 AI基建（凡动+API平台） 各品牌新品打造 | J100: 1 | L100: 营销内容创作体系AI化：70%；凡动（MCP、凡动管理后台、数据上报、会议纪要）：100%； 各品牌新品打造：80% | M100: 0.83 | N100: 0.5 | O100: 0.83 | P100: 1.0016 | Q100: 0.95 | R100: 4950 | S100: 4950 | T100: 5000 | U100: 关键物料安全库存达标率 | W100: 0.6 | X100: 60 | Y100: 准时提交 | Z100: 0.6 | AA100: 0.6 | AB100: 100
...

Sheet 整合-原始
A1: 工号旧 | B1: 工号-新 | C1: 部门 | D1: 中心查找 | E1: 岗位查找 | F1: 姓名 | G1: 总完成率 | H1: 总得分 | I1: 总奖金 | J1: 绩效基数 | K1: 新工号查找 | L1: 核查 | M1: 部门查找 | N1: 核查 | O1: 中心查找 | P1: 核查 | Q1: 岗位查找 | R1: 核查 | S1: 工号旧 | T1: 核查
B2: FD-043687 | C2: 品牌创意部-直播中心 | D2: 品牌创意部-直播中心 | E2: 主播 | F2: 张丹 | G2: 1 | H2: 373 | I2: 13000 | J2: 10000
B3: FD-031919 | C3: 品牌创意部-直播中心 | D3: 品牌创意部-直播中心 | E3: 高级主播 | F3: 庄少丽 | G3: 1 | H3: 343 | I3: 60000 | J3: 55000
B4: FD-043134 | C4: 品牌创意部-直播中心 | D4: 品牌创意部-直播中心 | E4: 主播 | F4: 黄羽丹 | G4: 1 | H4: 321.5 | I4: 40500 | J4: 10000
B5: FD-042958 | C5: 品牌创意部-直播中心 | D5: 品牌创意部-直播中心 | E5: 高级主播 | F5: 赵雅萱 | G5: 1 | H5: 319 | I5: 30000 | J5: 100000
B6: FD-041967 | C6: 品牌创意部-直播中心 | D6: 品牌创意部-直播中心 | E6: 高级主播 | F6: 赵弘睿 | G6: 1 | H6: 313.5 | I6: 20500 | J6: 55000
B7: FD-047686 | C7: 品牌创意部-直播中心 | D7: 品牌创意部-直播中心 | E7: 主播 | F7: 辛宜静 | G7: 1 | H7: 310 | I7: 10000 | J7: 10000
B8: FD-046625 | C8: 品牌创意部-直播中心 | D8: 品牌创意部-直播中心 | E8: 主播 | F8: 赵凯悦 | G8: 1 | H8: 293 | I8: 8200 | J8: 10000
B9: FD-040324 | C9: 品牌创意部-直播中心 | D9: 品牌创意部-直播中心 | E9: 主播 | F9: 魏海燕 | G9: 1 | H9: 288 | I9: 200 | J9: 10000
B10: FD-047330 | C10: 品牌创意部-直播中心 | D10: 品牌创意部-直播中心 | E10: 主播 | F10: 雷丽娟 | G10: 1 | H10: 280 | I10: 6000 | J10: 10000
B11: FD-041335 | C11: 品牌创意部-直播中心 | D11: 品牌创意部-直播中心 | E11: 主播 | F11: 张郑庆 | G11: 1 | H11: 265.5 | I11: 2500 | J11: 10000
B12: FD-041568 | C12: 品牌创意部-直播中心 | D12: 品牌创意部-直播中心 | E12: 高级主播 | F12: 周晓纯 | G12: 1 | H12: 254 | I12: 14000 | J12: 55000
B13: FD-045322 | C13: 品牌创意部-直播中心 | D13: 品牌创意部-直播中心 | E13: 主播 | F13: 吴雨璠 | G13: 1 | H13: 254 | I13: 0 | J13: 10000
... B171: FD-017532 | C171: 市场拓展部 | D171: 市场拓展部 | E171: 总监助理 | F171: 马菲阳 | G171: 1.0894 | H171: 1.2 | I171: 4000 | J171: 3000
F172: 朱丹萍 | G172: 1.2 | H172: 1.2 | I172: 5400 | J172: 5000
B173: FD-091571 | C173: 产品供应部-物流中心 | D173: 产品供应部-物流中心 | E173: 物流高级经理 | F173: 吴永星 | G173: 1.18696 | H173: 1.19 | I173: 5200 | J173: 5000
B174: FD-036124 | C174: 广告策划部-创新C中心 | D174: 广告策划部-创新C中心 | E174: 营销高级经理 | F174: 唐基翔 | G174: 1.191 | H174: 1.19 | I174: 5400 | J174: 5000
B175: FD-054711 | C175: 市场拓展部-先锋中心 | D175: 市场拓展部-先锋中心 | E175: 市场高级经理 | F175: 苏静微 | G175: 2.44875 | H175: 1.19 | I175: 6160 | J175: 5000
B176: FD-051657 | C176: 市场拓展部-媒介中心 | D176: 市场拓展部-媒介中心 | E176: 管培生 | F176: 冯馨怡 | G176: 0.880912 | H176: 1.19 | I176: 3653.62 | J176: 5000
B177: FD-056244 | C177: 市场拓展部-媒介中心 | D177: 市场拓展部-媒介中心 | E177: 商务PR | F177: 李欣 | G177: 0.87908 | H177: 1.19 | I177: 2316.82 | J177: 2000
F178: 吴永星 | G178: 1.187 | H178: 1.19 | I178: 5200 | J178: 5000
B179: FD-157175 | C179: 人资行政部-综合招聘中心 | D179: 人资行政部-综合招聘中心 | E179: 招聘经理 | F179: 陈学锦 | G179: 1.175 | H179: 1.18 | I179: 4454.55 | J179: 3000
B180: FD-096682 | C180: 产品供应部-采购中心 | D180: 产品供应部-采购中心 | E180: 采购经理 | F180: 巫文鑫 | G180: 1.222222 | H180: 1.18 | I180: 3461.54 | J180: 3000
B181: FD-044712 | C181: 电商发展部-赫系渠道A中心 | D181: 电商发展部-赫系渠道A中心 | E181: 电商高级经理 | F181: 许立榕 | G181: 1.120302 | H181: 1.18 | I181: 8000 | J181: 5000
B182: FD-098144 | C182: 产品供应部-供应中心 | D182: 产品供应部-供应中心 | E182: 供应链经理 | F182: 李红菊 | G182: 0.97492 | H182: 1.17 | I182: 3627.91 | J182: 3000
B183: FD-107532 | C183: 凡岛研究院-配方研究实验室 | D183: 凡岛研究院-配方研究实验室 | E183: 研发工程师 | F183: 王嘉俊 | G183: 1 | H183: 1.17 | I183: 2457 | J183: 3000
B184: FD-021226 | C184: 品牌营销部-营销中心J | D184: 品牌营销部-营销中心J | E184: 视频编辑 | F184: 唐茹 | G184: 1.449 | H184: 1.17 | I184: 5520 | J184: 2000
B185: FD-057590 | C185: 市场拓展部-明星中心 | D185: 市场拓展部-明星中心 | E185: 管培生 | F185: 张媛 | G185: 1.21286 | H185: 1.17 | I185: 4000 | J185: 5000
B186: FD-043442 | C186: 品牌创意部-赫系营销A中心 | D186: 品牌创意部-赫系营销A中心 | E186: 营销经理 | F186: 谭航 | G186: 1.58961 | H186: 1.17 | I186: 5758.6 | J186: 5000
B187: FD-082125 | C187: 新品牌事业部-品牌管理中心 | D187: 新品牌事业部-品牌管理中心 | E187: 品牌高级经理 | F187: 林少瑶 | G187: 1.172 | H187: 1.17 | I187: 6460 | J187: 3000
B188: FD-125310 | C188: 电商发展部-设计中心 | D188: 电商发展部-设计中心 | E188: 首席平面设计师 | F188: 谢海燕 | G188: 0.7175 | H188: 1.17 | I188: 6400 | J188: 4000
B189: FD-079664 | C189: 线下渠道部-KONO-KONO销售A中心-华东区 | D189: 线下渠道部-KONO-KONO销售A中心-华东区 | E189: KA商务经理 | F189: 高智慧 | G189: 1.183 | H189: 1.16 | I189: 8638.35 | J189: 6000
B190: FD-074107 | C190: 线下渠道部-WIS-WIS销售B中心 | D190: 线下渠道部-WIS-WIS销售B中心 | E190: 零售高级经理 | F190: 华珊 | G190: 2.05047 | H190: 1.15 | I190: 9291.67 | J190: 5000
... B223: FD-013392 | C223: 品牌创意部 | D223: 品牌创意部 | E223: 总监助理 | F223: 林睿媛 | G223: 1.1036 | H223: 1.1 | I223: 0 | J223: 3000
F224: 黄晓莲 | G224: 1.099 | H224: 1.1 | I224: 2200 | J224: 2000
F225: 谢昊 | G225: 1.1 | H225: 1.1 | I225: 5200 | J225: 5000
B226: FD-077703 | C226: 线下渠道部-渠道运作中心 | D226: 线下渠道部-渠道运作中心 | E226: 市场监察经理 | F226: 蓝文阳 | G226: 1.105 | H226: 1.09 | I226: 2400 | J226: 3000
B227: FD-157065 | C227: 人资行政部-HRBP中心 | D227: 人资行政部-HRBP中心 | E227: HR经理 | F227: 霍雨佳 | G227: 0.98708 | H227: 1.09 | I227: 3629.03 | J227: 3000
B228: FD-092873 | C228: 人资行政部-从化中心 | D228: 人资行政部-从化中心 | E228: 行政专员 | F228: 邝少芬 | G228: 0.9665 | H228: 1.08 | I228: 864 | J228: 800
B229: FD-172589 | C229: 财务部-财务分析中心 | D229: 财务部-财务分析中心 | E229: 财务BP | F229: 宋霄宇 | G229: 0.93073 | H229: 1.08 | I229: 3692.31 | J229: 3000
B230: FD-058236 | C230: 市场拓展部-先锋中心 | D230: 市场拓展部-先锋中心 | E230: 商务PR | F230: 陈增铭 | G230: 1.08697 | H230: 1.08 | I230: 0 | J230: 2000
B231: FD-121609 | C231: 电商发展部-设计中心 | D231: 电商发展部-设计中心 | E231: 资深平面设计师 | F231: 梁丹萍 | G231: 0.72275 | H231: 1.08 | I231: 3600 | J231: 4000
B232: FD-109059 | C232: 凡岛研究院 | D232: 凡岛研究院 | E232: 总监助理 | F232: 蔡爱存 | G232: 1.084 | H232: 1.08 | I232: 3360 | J232: 3000
B233: FD-083986 | C233: 新品牌事业部-设计中心 | D233: 新品牌事业部-设计中心 | E233: 产品设计师 | F233: 罗亦晨 | G233: 0.67 | H233: 1.07 | I233: 3200 | J233: 2800
B234: FD-154287 | C234: 人资行政部-综合招聘中心 | D234: 人资行政部-综合招聘中心 | E234: 招聘BP | F234: 涂欣瑶 | G234: 0.973389 | H234: 1.07 | I234: 4140.85 | J234: 3000
B235: OD-006285 | C235: 人资行政部-HRBP中心 | D235: 人资行政部-HRBP中心 | E235: 招聘专员 | F235: 马茵桐 | G235: 1.028 | H235: 1.07 | I235: 2000 | J235: 2000
B236: OD-001052 | C236: 广告策划部-营销C中心 | D236: 广告策划部-营销C中心 | E236: 营销策划 | F236: 金晶 | G236: 1.07 | H236: 1.07 | I236: 2765 | J236: 1500
B237: OD-000127 | C237: 产品供应部-供应中心 | D237: 产品供应部-供应中心 | E237: 请款对账员 | F237: 罗杨佳 | G237: 0.815 | H237: 1.07 | I237: 1200 | J237: 1200
... B249: SX-007716 | C249: 品牌营销部-营销中心A | D249: 品牌营销部-营销中心A | E249: 营销策划实习生 | F249: 杨丹妮 | G249: 1.177 | H249: 1.06 | I249: 500 | J249: 500
F250: 陈远连 | G250: 1.0581 | H250: 1.06 | I250: 2570.61 | J250: 0.51412298
B251: OD-004552 | C251: 广告策划部-创新B中心 | D251: 广告策划部-创新B中心 | E251: 营销策划 | F251: 邓小妹 | G251: 1.148 | H251: 1.05 | I251: 2172.41 | J251: 1500
B252: FD-023018 | C252: 品牌营销部-视频中心 | D252: 品牌营销部-视频中心 | E252: 视频编辑 | F252: 陈广聪 | G252: 1.3 | H252: 1.05 | I252: 0 | J252: 2000
B253: FD-091970 | C253: 产品供应部-品控中心 | D253: 产品供应部-品控中心 | E253: 品控高级经理 | F253: 郑烁纯 | G253: 1.1 | H253: 1.05 | I253: 2100 | J253: 2000
B254: FD-029514 | C254: 品牌营销部-营销中心J | D254: 品牌营销部-营销中心J | E254: 营销经理 | F254: 张鑫露 | G254: 1.045 | H254: 1.05 | I254: 3262.5 | J254: 5000
B255: OD-004267 | C255: 品牌营销部-营销中心J | D255: 品牌营销部-营销中心J | E255: 营销策划 | F255: 陈静诗 | G255: 1.575082 | H255: 1.05 | I255: 2190 | J255: 1500
B256: FD-011386 | C256: 总经办-创业模块 | D256: 总经办-创业模块 | E256: 活动运营经理 | F256: 彭琨 | G256: 0.010527 | H256: 1.05 | I256: 3300 | J256: 3300
B257: FD-068941 | C257: 电商发展部-WIS渠道A中心 | D257: 电商发展部-WIS渠道A中心 | E257: 电商经理 | F257: 李祥顺 | G257: 1.17765 | H257: 1.05 | I257: 0 | J257: 5000
F258: 郑烁纯 | G258: 1.05 | H258: 1.05 | I258: 2100 | J258: 2000
B259: OD-000664 | C259: 人资行政部-组织发展中心 | D259: 人资行政部-组织发展中心 | E259: SSC助理 | F259: 宋月 | G259: 1.0285 | H259: 1.03 | I259: 2060 | J259: 2000
B260: FD-218877 | C260: 海外事业部-运营中心 | D260: 海外事业部-运营中心 | E260: 跨境电商经理 | F260: 张馨雨 | G260: 1.0252 | H260: 1.03 | I260: 3000 | J260: 3000
B261: FD-098373 | C261: 产品供应部-采购中心 | D261: 产品供应部-采购中心 | E261: 采购经理 | F261: 郑思梅 | G261: 1.025 | H261: 1.03 | I261: 2596.15 | J261: 3000
B262: FD-024035 | C262: 品牌营销部-直播中心 | D262: 品牌营销部-直播中心 | E262: 主播教练 | F262: 曾泳淇 | G262: 1.07461 | H262: 1.03 | I262: 3210 | J262: 3000
B263: FD-097041 | C263: 产品供应部-寻源中心 | D263: 产品供应部-寻源中心 | E263: 寻源经理 | F263: 龚卉彤 | G263: 0.866 | H263: 1.03 | I263: 3361.11 | J263: 3000
B264: FD-151475 | C264: 人资行政部-猎聘中心 | D264: 人资行政部-猎聘中心 | E264: 猎聘高级经理 | F264: 杨明月 | G264: 1.105 | H264: 1.03 | I264: 5690.52 | J264: 5000
B265: FD-031435 | C265: 广告策划部-创新B中心 | D265: 广告策划部-创新B中心 | E265: 营销高级经理 | F265: 李慧娟 | G265: 1.028846 | H265: 1.03 | I265: 4200 | J265: 5000
B266: FD-110540 | C266: 电商发展部-设计中心 | D266: 电商发展部-设计中心 | E266: 资深平面设计师 | F266: 杨永梅 | G266: 0.665 | H266: 1.03 | I266: 2400 | J266: 4000
B267: FD-057588 | C267: 市场拓展部-媒介中心 | D267: 市场拓展部-媒介中心 | E267: 商务PR | F267: 黄美琪 | G267: 0.724728 | H267: 1.03 | I267: 1837.97 | J267: 2000
B268: OD-007504 | C268: 凡岛大学 | D268: 凡岛大学 | E268: 课程助教 | F268: 梁夏晴 | G268: 1.024 | H268: 1.02 | I268: 2040 | J268: 2000
B269: FD-015700 | C269: 总经办-总助模块 | D269: 总经办-总助模块 | E269: 高级经理 | F269: 丁小恬 | G269: 0.9584 | H269: 1.02 | I269: 5020 | J269: 5000
B270: FD-091904 | C270: 产品供应部-计划中心 | D270: 产品供应部-计划中心 | E270: 计划高级经理 | F270: 陈林文 | G270: 1.17 | H270: 1.02 | I270: 5100 | J270: 5000
B271: FD-238869 | C271: 品牌管理部-KONO品牌中心 | D271: 品牌管理部-KONO品牌中心 | E271: 管培生 | F271: 王冬悦 | G271: 1.02215 | H271: 1.02 | I271: 6120 | J271: 6000
F272: 陈林文 | G272: 1.0206 | H272: 1.02 | I272: 5100 | J272: 5000
B273: FD-097678 | C273: 产品供应部-计划中心 | D273: 产品供应部-计划中心 | E273: 管培生 | F273: 钟恩宝 | G273: 1.00971 | H273: 1.01 | I273: 5525.6 | J273: 5000
B274: FD-095713 | C274: 产品供应部-供应中心 | D274: 产品供应部-供应中心 | E274: 管培生 | F274: 刘星瑶 | G274: 0.98 | H274: 1.01 | I274: 4651.16 | J274: 5000
B275: FD-074879 | C275: 线下渠道部-WIS-WIS销售B中心 | D275: 线下渠道部-WIS-WIS销售B中心 | E275: 管培生 | F275: 杨雨婷 | G275: 2.127 | H275: 1.01 | I275: 6424.73 | J275: 5000
B276: OD-001008 | C276: 人资行政部-直播招聘中心 | D276: 人资行政部-直播招聘中心 | E276: 招聘专员 | F276: 王巧微 | G276: 1.0375 | H276: 1.01 | I276: 2000 | J276: 2000
B277: FD-093433 | C277: 产品供应部-开发中心 | D277: 产品供应部-开发中心 | E277: 开发高级经理 | F277: 杨尚儒 | G277: 1.013 | H277: 1.01 | I277: 5000 | J277: 5000
B278: FD-227829 | C278: AI效率流程部-AI效率流程B中心 | D278: AI效率流程部-AI效率流程B中心 | E278: AI工程师 | F278: 崔经瀚 | G278: 1.01 | H278: 1.01 | I278: 5910 | J278: 5000
B279: FD-237186 | C279: 凡岛研究院-产品设计中心 | D279: 凡岛研究院-产品设计中心 | E279: 产品设计师 | F279: 张雯 | G279: 0.958 | H279: 1.01 | I279: 1960 | J279: 2800
B280: OD-000649 | C280: 人资行政部-综合招聘中心 | D280: 人资行政部-综合招聘中心 | E280: 招聘专员 | F280: 杨尚儒 | G280: 1.013 | H280: 1.01 | I280: 5000 | J280: 5000
B281: OD-002451 | C281: 人资行政部-组织发展中心 | D281: 人资行政部-组织发展中心 | E281: SSC助理 | F281: 陆颖 | G281: 1 | H281: 1 | I281: 1500 | J281: 1500
B282: FD-155599 | C282: 人资行政部-组织发展中心 | D282: 人资行政部-组织发展中心 | E282: COE专家 | F282: 王雅丽 | G282: 1 | H282: 1 | I282: 3386 | J282: 3000
B283: FD-156792 | C283: 人资行政部-组织发展中心 | D283: 人资行政部-组织发展中心 | E283: COE专家 | F283: 宫兆宜 | G283: 1 | H283: 1 | I283: 3386 | J283: 3000
B284: FD-084304 | C284: 新品牌事业部-设计中心 | D284: 新品牌事业部-设计中心 | E284: 资深平面设计师 | F284: 苏秋英 | G284: 1 | H284: 1 | I284: 3400 | J284: 3000
... B357: FD-059032 | C357: 市场拓展部-媒介中心 | D357: 市场拓展部-媒介中心 | E357: 商务PR | F357: 麦绮雯 | G357: 0.913322 | H357: 1 | I357: 1401.52 | J357: 2000
F358: 杨雄贤 | G358: 1 | H358: 1 | I358: 2429.39 | J358: 0.48587702
B359: FD-085087 | C359: 产品供应部-计划中心 | D359: 产品供应部-计划中心 | E359: 计划经理 | F359: 张璐萍 | G359: 0.9396 | H359: 0.99 | I359: 3475.6 | J359: 3000
B360: FD-181227 | C360: 公共事务与品牌传播部 | D360: 公共事务与品牌传播部 | E360: 品牌公关经理 | F360: 杨颖晖 | G360: 1.000005 | H360: 0.99 | I360: 4950 | J360: 5000
B361: OD-000799 | C361: 电商发展部-渠道支持中心 | D361: 电商发展部-渠道支持中心 | E361: 运营助理 | F361: 林妙华 | G361: 0.99 | H361: 0.99 | I361: 1188 | J361: 1200
B362: OD-002925 | C362: 电商发展部-渠道支持中心 | D362: 电商发展部-渠道支持中心 | E362: 运营助理 | F362: 张小蝶 | G362: 0.99 | H362: 0.99 | I362: 1188 | J362: 1200
B363: OD-008900 | C363: 电商发展部-渠道支持中心 | D363: 电商发展部-渠道支持中心 | E363: 运营助理 | F363: 黄玉容 | G363: 0.99 | H363: 0.99 | I363: 1188 | J363: 1200
B364: OD-003628 | C364: 电商发展部-渠道支持中心 | D364: 电商发展部-渠道支持中心 | E364: 运营助理 | F364: 陈诗君 | G364: 0.833 | H364: 0.99 | I364: 1188 | J364: 1000
B365: FD-158753 | C365: 人资行政部-HRBP中心 | D365: 人资行政部-HRBP中心 | E365: HR经理 | F365: 张玉 | G365: 1.44321 | H365: 0.99 | I365: 2721.77 | J365: 3000
B366: FD-091451 | C366: 产品供应部-寻源中心 | D366: 产品供应部-寻源中心 | E366: 管培生 | F366: 刘言钰 | G366: 0.98 | H366: 0.99 | I366: 0 | J366: 5000
B367: FD-095594 | C367: 产品供应部-物流中心 | D367: 产品供应部-物流中心 | E367: 物流经理 | F367: 梁柱耀 | G367: 0.99 | H367: 0.99 | I367: 0 | J367: 3000
B368: OD-001978 | C368: 品牌创意部-赫系营销D中心 | D368: 品牌创意部-赫系营销D中心 | E368: 营销助理 | F368: 陈之桐 | G368: 0.983 | H368: 0.99 | I368: 2339.13 | J368: 1200
B369: FD-222398 | C369: AI效率流程部-AI研究中心 | D369: AI效率流程部-AI研究中心 | E369: AI产品经理 | F369: 王砺 | G369: 0.7738 | H369: 0.99 | I369: 0 | J369: 3400
B370: FD-039822 | C370: 品牌管理部-KONO品牌中心 | D370: 品牌管理部-KONO品牌中心 | E370: 营销高级经理 | F370: 唐青蔚 | G370: 0.993839 | H370: 0.99 | I370: 4925 | J370: 5000
... B591: OD-004744 | C591: 品牌营销部-视频中心 | D591: 品牌营销部-视频中心 | E591: 摄像师 | F591: 黄鸿鑫 | G591: 0.85 | H591: 0.8 | I591: 1600 | J591: 2000
F592: 王誉炫 | G592: 0.8 | H592: 0.8 | I592: 4000 | J592: 4000
...

Sheet 整合-校准（副本）
A1: 工号旧 | B1: 工号-新 | C1: 年份 | D1: 月份 | E1: 部门 | F1: 中心查找 | G1: 岗位查找 | H1: 姓名 | I1: 总完成率 | J1: 总得分 | K1: 总得分 | L1: 总奖金 | M1: 绩效基数 | N1: 新工号查找 | O1: 核查 | P1: 部门查找 | Q1: 核查 | R1: 中心查找 | S1: 核查 | U1: 岗位查找 | V1: 核查 | W1: 备注 | X1: 工号旧 | Y1: 核查
B2: FD-043687 | C2: 26年 | D2: 7月 | E2: 品牌创意部 | F2: 直播中心 | G2: 主播 | H2: 张丹 | I2: 1 | J2: 373 | K2: =K2:J2% | L2: 13000 | M2: 10000 | N2: {=_xlfn.XLOOKUP(H2,'OA名单'!C:C,'OA名单'!B:B,1)} | O2: =IF(N2=B2,1) | P2: {=_xlfn.XLOOKUP(N2,'OA名单'!B:B,'OA名单'!G:G)} | Q2: =IF(P2=E2,1) | R2: {=_xlfn.XLOOKUP(B2,'OA名单'!B:B,'OA名单'!F:F)} | S2: =IF(R2=F2,1) | U2: {=_xlfn.XLOOKUP(N2,'OA名单'!B:B,'OA名单'!E:E)} | V2: =IF(U2=G2,1) | Y2: =IF(X2=K2,1)
B3: FD-031919 | C3: 26年 | D3: 7月 | E3: 品牌创意部 | F3: 直播中心 | G3: 高级主播 | H3: 庄少丽 | I3: 1 | J3: 343 | K3: =K3:J3% | L3: 60000 | M3: 55000 | N3: {=_xlfn.XLOOKUP(H3,'OA名单'!C:C,'OA名单'!B:B,1)} | O3: =IF(N3=B3,1) | P3: {=_xlfn.XLOOKUP(N3,'OA名单'!B:B,'OA名单'!G:G)} | Q3: =IF(P3=E3,1) | R3: {=_xlfn.XLOOKUP(B3,'OA名单'!B:B,'OA名单'!F:F)} | S3: =IF(R3=F3,1) | U3: {=_xlfn.XLOOKUP(N3,'OA名单'!B:B,'OA名单'!E:E)} | V3: =IF(U3=G3,1)
B4: FD-043134 | C4: 26年 | D4: 7月 | E4: 品牌创意部 | F4: 直播中心 | G4: 主播 | H4: 黄羽丹 | I4: 1 | J4: 321.5 | K4: =K4:J4% | L4: 40500 | M4: 10000 | N4: {=_xlfn.XLOOKUP(H4,'OA名单'!C:C,'OA名单'!B:B,1)} | O4: =IF(N4=B4,1) | P4: {=_xlfn.XLOOKUP(N4,'OA名单'!B:B,'OA名单'!G:G)} | Q4: =IF(P4=E4,1) | R4: {=_xlfn.XLOOKUP(B4,'OA名单'!B:B,'OA名单'!F:F)} | S4: =IF(R4=F4,1) | U4: {=_xlfn.XLOOKUP(N4,'OA名单'!B:B,'OA名单'!E:E)} | V4: =IF(U4=G4,1)
B5: FD-042958 | C5: 26年 | D5: 7月 | E5: 品牌创意部 | F5: 直播中心 | G5: 高级主播 | H5: 赵雅萱 | I5: 1 | J5: 319 | K5: =K5:J5% | L5: 30000 | M5: 100000 | N5: {=_xlfn.XLOOKUP(H5,'OA名单'!C:C,'OA名单'!B:B,1)} | O5: =IF(N5=B5,1) | P5: {=_xlfn.XLOOKUP(N5,'OA名单'!B:B,'OA名单'!G:G)} | Q5: =IF(P5=E5,1) | R5: {=_xlfn.XLOOKUP(B5,'OA名单'!B:B,'OA名单'!F:F)} | S5: =IF(R5=F5,1) | U5: {=_xlfn.XLOOKUP(N5,'OA名单'!B:B,'OA名单'!E:E)} | V5: =IF(U5=G5,1)
B6: FD-041967 | C6: 26年 | D6: 7月 | E6: 品牌创意部 | F6: 直播中心 | G6: 高级主播 | H6: 赵弘睿 | I6: 1 | J6: 313.5 | K6: =K6:J6% | L6: 20500 | M6: 55000 | N6: {=_xlfn.XLOOKUP(H6,'OA名单'!C:C,'OA名单'!B:B,1)} | O6: =IF(N6=B6,1) | P6: {=_xlfn.XLOOKUP(N6,'OA名单'!B:B,'OA名单'!G:G)} | Q6: =IF(P6=E6,1) | R6: {=_xlfn.XLOOKUP(B6,'OA名单'!B:B,'OA名单'!F:F)} | S6: =IF(R6=F6,1) | U6: {=_xlfn.XLOOKUP(N6,'OA名单'!B:B,'OA名单'!E:E)} | V6: =IF(U6=G6,1)
B7: FD-047686 | C7: 26年 | D7: 7月 | E7: 品牌创意部 | F7: 直播中心 | G7: 主播 | H7: 辛宜静 | I7: 1 | J7: 310 | K7: =K7:J7% | L7: 10000 | M7: 10000 | N7: {=_xlfn.XLOOKUP(H7,'OA名单'!C:C,'OA名单'!B:B,1)} | O7: =IF(N7=B7,1) | P7: {=_xlfn.XLOOKUP(N7,'OA名单'!B:B,'OA名单'!G:G)} | Q7: =IF(P7=E7,1) | R7: {=_xlfn.XLOOKUP(B7,'OA名单'!B:B,'OA名单'!F:F)} | S7: =IF(R7=F7,1) | U7: {=_xlfn.XLOOKUP(N7,'OA名单'!B:B,'OA名单'!E:E)} | V7: =IF(U7=G7,1)
B8: FD-046625 | C8: 26年 | D8: 7月 | E8: 品牌创意部 | F8: 直播中心 | G8: 主播 | H8: 赵凯悦 | I8: 1 | J8: 293 | K8: =K8:J8% | L8: 8200 | M8: 10000 | N8: {=_xlfn.XLOOKUP(H8,'OA名单'!C:C,'OA名单'!B:B,1)} | O8: =IF(N8=B8,1) | P8: {=_xlfn.XLOOKUP(N8,'OA名单'!B:B,'OA名单'!G:G)} | Q8: =IF(P8=E8,1) | R8: {=_xlfn.XLOOKUP(B8,'OA名单'!B:B,'OA名单'!F:F)} | S8: =IF(R8=F8,1) | U8: {=_xlfn.XLOOKUP(N8,'OA名单'!B:B,'OA名单'!E:E)} | V8: =IF(U8=G8,1)
B9: FD-040324 | C9: 26年 | D9: 7月 | E9: 品牌创意部 | F9: 直播中心 | G9: 主播 | H9: 魏海燕 | I9: 1 | J9: 288 | K9: =K9:J9% | L9: 200 | M9: 10000 | N9: {=_xlfn.XLOOKUP(H9,'OA名单'!C:C,'OA名单'!B:B,1)} | O9: =IF(N9=B9,1) | P9: {=_xlfn.XLOOKUP(N9,'OA名单'!B:B,'OA名单'!G:G)} | Q9: =IF(P9=E9,1) | R9: {=_xlfn.XLOOKUP(B9,'OA名单'!B:B,'OA名单'!F:F)} | S9: =IF(R9=F9,1) | U9: {=_xlfn.XLOOKUP(N9,'OA名单'!B:B,'OA名单'!E:E)} | V9: =IF(U9=G9,1)
B10: FD-047330 | C10: 26年 | D10: 7月 | E10: 品牌创意部 | F10: 直播中心 | G10: 主播 | H10: 雷丽娟 | I10: 1 | J10: 280 | K10: =K10:J10% | L10: 6000 | M10: 10000 | N10: {=_xlfn.XLOOKUP(H10,'OA名单'!C:C,'OA名单'!B:B,1)} | O10: =IF(N10=B10,1) | P10: {=_xlfn.XLOOKUP(N10,'OA名单'!B:B,'OA名单'!G:G)} | Q10: =IF(P10=E10,1) | R10: {=_xlfn.XLOOKUP(B10,'OA名单'!B:B,'OA名单'!F:F)} | S10: =IF(R10=F10,1) | U10: {=_xlfn.XLOOKUP(N10,'OA名单'!B:B,'OA名单'!E:E)} | V10: =IF(U10=G10,1)
B11: FD-041335 | C11: 26年 | D11: 7月 | E11: 品牌创意部 | F11: 直播中心 | G11: 主播 | H11: 张郑庆 | I11: 1 | J11: 265.5 | K11: =K11:J11% | L11: 2500 | M11: 10000 | N11: {=_xlfn.XLOOKUP(H11,'OA名单'!C:C,'OA名单'!B:B,1)} | O11: =IF(N11=B11,1) | P11: {=_xlfn.XLOOKUP(N11,'OA名单'!B:B,'OA名单'!G:G)} | Q11: =IF(P11=E11,1) | R11: {=_xlfn.XLOOKUP(B11,'OA名单'!B:B,'OA名单'!F:F)} | S11: =IF(R11=F11,1) | U11: {=_xlfn.XLOOKUP(N11,'OA名单'!B:B,'OA名单'!E:E)} | V11: =IF(U11=G11,1)
B12: FD-041568 | C12: 26年 | D12: 7月 | E12: 品牌创意部 | F12: 直播中心 | G12: 高级主播 | H12: 周晓纯 | I12: 1 | J12: 254 | K12: =K12:J12% | L12: 14000 | M12: 55000 | N12: {=_xlfn.XLOOKUP(H12,'OA名单'!C:C,'OA名单'!B:B,1)} | O12: =IF(N12=B12,1) | P12: {=_xlfn.XLOOKUP(N12,'OA名单'!B:B,'OA名单'!G:G)} | Q12: =IF(P12=E12,1) | R12: {=_xlfn.XLOOKUP(B12,'OA名单'!B:B,'OA名单'!F:F)} | S12: =IF(R12=F12,1) | U12: {=_xlfn.XLOOKUP(N12,'OA名单'!B:B,'OA名单'!E:E)} | V12: =IF(U12=G12,1)
B13: FD-045322 | C13: 26年 | D13: 7月 | E13: 品牌创意部 | F13: 直播中心 | G13: 主播 | H13: 吴雨璠 | I13: 1 | J13: 254 | K13: =K13:J13% | L13: 0 | M13: 10000 | N13: {=_xlfn.XLOOKUP(H13,'OA名单'!C:C,'OA名单'!B:B,1)} | O13: =IF(N13=B13,1) | P13: {=_xlfn.XLOOKUP(N13,'OA名单'!B:B,'OA名单'!G:G)} | Q13: =IF(P13=E13,1) | R13: {=_xlfn.XLOOKUP(B13,'OA名单'!B:B,'OA名单'!F:F)} | S13: =IF(R13=F13,1) | U13: {=_xlfn.XLOOKUP(N13,'OA名单'!B:B,'OA名单'!E:E)} | V13: =IF(U13=G13,1)
B14: FD-044791 | C14: 26年 | D14: 7月 | E14: 品牌创意部 | F14: 直播中心 | G14: 主播 | H14: 王丽媛 | I14: 1 | J14: 249 | K14: =K14:J14% | L14: 16000 | M14: 10000 | N14: {=_xlfn.XLOOKUP(H14,'OA名单'!C:C,'OA名单'!B:B,1)} | O14: =IF(N14=B14,1) | P14: {=_xlfn.XLOOKUP(N14,'OA名单'!B:B,'OA名单'!G:G)} | Q14: =IF(P14=E14,1) | R14: {=_xlfn.XLOOKUP(B14,'OA名单'!B:B,'OA名单'!F:F)} | S14: =IF(R14=F14,1) | U14: {=_xlfn.XLOOKUP(N14,'OA名单'!B:B,'OA名单'!E:E)} | V14: =IF(U14=G14,1)
... B43: FD-031047 | C43: 26年 | D43: 7月 | E43: 广告策划部 | F43: 直播A中心 | G43: 主播 | H43: 王佳怡 | I43: 1 | J43: 100 | K43: =K43:J43% | L43: 0 | M43: 10000 | N43: {=_xlfn.XLOOKUP(H43,'OA名单'!C:C,'OA名单'!B:B,1)} | O43: =IF(N43=B43,1) | P43: {=_xlfn.XLOOKUP(N43,'OA名单'!B:B,'OA名单'!G:G)} | Q43: =IF(P43=E43,1) | R43: {=_xlfn.XLOOKUP(B43,'OA名单'!B:B,'OA名单'!F:F)} | S43: =IF(R43=F43,1) | U43: {=_xlfn.XLOOKUP(N43,'OA名单'!B:B,'OA名单'!E:E)} | V43: =IF(U43=G43,1)
B44: FD-042321 | C44: 26年 | D44: 7月 | E44: 品牌创意部 | F44: 直播中心 | G44: 直播助理 | H44: 陈真坪 | I44: 1 | J44: 100 | K44: =K44:J44% | L44: 1000 | M44: 1000 | N44: {=_xlfn.XLOOKUP(H44,'OA名单'!C:C,'OA名单'!B:B,1)} | O44: =IF(N44=B44,1) | P44: {=_xlfn.XLOOKUP(N44,'OA名单'!B:B,'OA名单'!G:G)} | Q44: =IF(P44=E44,1) | R44: {=_xlfn.XLOOKUP(B44,'OA名单'!B:B,'OA名单'!F:F)} | S44: =IF(R44=F44,1) | T44: {=_xlfn.XLOOKUP(B44,'系统-原始（副本）'!A:A,'系统-原始（副本）'!B:B)} | U44: {=_xlfn.XLOOKUP(N44,'OA名单'!B:B,'OA名单'!E:E)} | V44: =IF(U44=G44,1)
B45: FD-042172 | C45: 26年 | D45: 7月 | E45: 品牌创意部 | F45: 直播中心 | G45: 直播助理 | H45: 陈思思 | I45: 0.99315 | J45: 99.32 | K45: =K45:J45% | L45: 2200 | M45: 1000 | N45: {=_xlfn.XLOOKUP(H45,'OA名单'!C:C,'OA名单'!B:B,1)} | O45: =IF(N45=B45,1) | P45: {=_xlfn.XLOOKUP(N45,'OA名单'!B:B,'OA名单'!G:G)} | Q45: =IF(P45=E45,1) | R45: {=_xlfn.XLOOKUP(B45,'OA名单'!B:B,'OA名单'!F:F)} | S45: =IF(R45=F45,1) | T45: {=_xlfn.XLOOKUP(B45,'系统-原始（副本）'!A:A,'系统-原始（副本）'!B:B)} | U45: {=_xlfn.XLOOKUP(N45,'OA名单'!B:B,'OA名单'!E:E)} | V45: =IF(U45=G45,1)
B46: FD-043476 | C46: 26年 | D46: 7月 | E46: 品牌创意部 | F46: 直播中心 | G46: 直播助理 | H46: 袁志彬 | I46: 0.9929 | J46: 99.29 | K46: =K46:J46% | L46: 1750 | M46: 1000 | N46: {=_xlfn.XLOOKUP(H46,'OA名单'!C:C,'OA名单'!B:B,1)} | O46: =IF(N46=B46,1) | P46: {=_xlfn.XLOOKUP(N46,'OA名单'!B:B,'OA名单'!G:G)} | Q46: =IF(P46=E46,1) | R46: {=_xlfn.XLOOKUP(B46,'OA名单'!B:B,'OA名单'!F:F)} | S46: =IF(R46=F46,1) | U46: {=_xlfn.XLOOKUP(N46,'OA名单'!B:B,'OA名单'!E:E)} | V46: =IF(U46=G46,1)
B47: FD-035562 | C47: 26年 | D47: 7月 | E47: 广告策划部 | F47: 直播A中心 | G47: 直播助理 | H47: 赵晓旭 | I47: 0.9788 | J47: 98.88 | K47: =K47:J47% | L47: 1900 | M47: 1000 | N47: {=_xlfn.XLOOKUP(H47,'OA名单'!C:C,'OA名单'!B:B,1)} | O47: =IF(N47=B47,1) | P47: {=_xlfn.XLOOKUP(N47,'OA名单'!B:B,'OA名单'!G:G)} | Q47: =IF(P47=E47,1) | R47: {=_xlfn.XLOOKUP(B47,'OA名单'!B:B,'OA名单'!F:F)} | S47: =IF(R47=F47,1) | T47: {=_xlfn.XLOOKUP(B47,'系统-原始（副本）'!A:A,'系统-原始（副本）'!B:B)} | U47: {=_xlfn.XLOOKUP(N47,'OA名单'!B:B,'OA名单'!E:E)} | V47: =IF(U47=G47,1)
B48: FD-043242 | C48: 26年 | D48: 7月 | E48: 品牌创意部 | F48: 直播中心 | G48: 直播助理 | H48: 刘韵莹 | I48: 0.98615 | J48: 98.62 | K48: =K48:J48% | L48: 1500 | M48: 1000 | N48: {=_xlfn.XLOOKUP(H48,'OA名单'!C:C,'OA名单'!B:B,1)} | O48: =IF(N48=B48,1) | P48: {=_xlfn.XLOOKUP(N48,'OA名单'!B:B,'OA名单'!G:G)} | Q48: =IF(P48=E48,1) | R48: {=_xlfn.XLOOKUP(B48,'OA名单'!B:B,'OA名单'!F:F)} | S48: =IF(R48=F48,1) | U48: {=_xlfn.XLOOKUP(N48,'OA名单'!B:B,'OA名单'!E:E)} | V48: =IF(U48=G48,1)
B49: FD-047323 | C49: 26年 | D49: 7月 | E49: 品牌创意部 | F49: 直播中心 | G49: 直播助理 | H49: 秦国鸠 | I49: 0.98565 | J49: 98.57 | K49: =K49:J49% | L49: 1650 | M49: 1000 | N49: {=_xlfn.XLOOKUP(H49,'OA名单'!C:C,'OA名单'!B:B,1)} | O49: =IF(N49=B49,1) | P49: {=_xlfn.XLOOKUP(N49,'OA名单'!B:B,'OA名单'!G:G)} | Q49: =IF(P49=E49,1) | R49: {=_xlfn.XLOOKUP(B49,'OA名单'!B:B,'OA名单'!F:F)} | S49: =IF(R49=F49,1) | T49: {=_xlfn.XLOOKUP(B49,'系统-原始（副本）'!A:A,'系统-原始（副本）'!B:B)} | U49: {=_xlfn.XLOOKUP(N49,'OA名单'!B:B,'OA名单'!E:E)} | V49: =IF(U49=G49,1)
B50: FD-041125 | C50: 26年 | D50: 7月 | E50: 品牌创意部 | F50: 直播中心 | G50: 直播助理 | H50: 刘源 | I50: 0.9853 | J50: 98.53 | K50: =K50:J50% | L50: 1425 | M50: 1000 | N50: {=_xlfn.XLOOKUP(H50,'OA名单'!C:C,'OA名单'!B:B,1)} | O50: =IF(N50=B50,1) | P50: {=_xlfn.XLOOKUP(N50,'OA名单'!B:B,'OA名单'!G:G)} | Q50: =IF(P50=E50,1) | R50: {=_xlfn.XLOOKUP(B50,'OA名单'!B:B,'OA名单'!F:F)} | S50: =IF(R50=F50,1) | U50: {=_xlfn.XLOOKUP(N50,'OA名单'!B:B,'OA名单'!E:E)} | V50: =IF(U50=G50,1)
B51: FD-037854 | C51: 26年 | D51: 7月 | E51: 广告策划部 | F51: 直播A中心 | G51: 直播助理 | H51: 祝愿 | I51: 0.98 | J51: 98.5 | K51: =K51:J51% | L51: 1900 | M51: 1000 | N51: {=_xlfn.XLOOKUP(H51,'OA名单'!C:C,'OA名单'!B:B,1)} | O51: =IF(N51=B51,1) | P51: {=_xlfn.XLOOKUP(N51,'OA名单'!B:B,'OA名单'!G:G)} | Q51: =IF(P51=E51,1) | R51: {=_xlfn.XLOOKUP(B51,'OA名单'!B:B,'OA名单'!F:F)} | S51: =IF(R51=F51,1) | T51: {=_xlfn.XLOOKUP(B51,'系统-原始（副本）'!A:A,'系统-原始（副本）'!B:B)} | U51: {=_xlfn.XLOOKUP(N51,'OA名单'!B:B,'OA名单'!E:E)} | V51: =IF(U51=G51,1)
B52: FD-044987 | C52: 26年 | D52: 7月 | E52: 品牌创意部 | F52: 直播中心 | G52: 直播助理 | H52: 何乐妍 | I52: 0.9844 | J52: 98.44 | K52: =K52:J52% | L52: 1225 | M52: 1000 | N52: {=_xlfn.XLOOKUP(H52,'OA名单'!C:C,'OA名单'!B:B,1)} | O52: =IF(N52=B52,1) | P52: {=_xlfn.XLOOKUP(N52,'OA名单'!B:B,'OA名单'!G:G)} | Q52: =IF(P52=E52,1) | R52: {=_xlfn.XLOOKUP(B52,'OA名单'!B:B,'OA名单'!F:F)} | S52: =IF(R52=F52,1) | U52: {=_xlfn.XLOOKUP(N52,'OA名单'!B:B,'OA名单'!E:E)} | V52: =IF(U52=G52,1)
B53: FD-039959 | C53: 26年 | D53: 7月 | E53: 广告策划部 | F53: 直播A中心 | G53: 直播助理 | H53: 谭程宝 | I53: 0.9782 | J53: 98.32 | K53: =K53:J53% | L53: 1300 | M53: 1000 | N53: {=_xlfn.XLOOKUP(H53,'OA名单'!C:C,'OA名单'!B:B,1)} | O53: =IF(N53=B53,1) | P53: {=_xlfn.XLOOKUP(N53,'OA名单'!B:B,'OA名单'!G:G)} | Q53: =IF(P53=E53,1) | R53: {=_xlfn.XLOOKUP(B53,'OA名单'!B:B,'OA名单'!F:F)} | S53: =IF(R53=F53,1) | U53: {=_xlfn.XLOOKUP(N53,'OA名单'!B:B,'OA名单'!E:E)} | V53: =IF(U53=G53,1)
B54: FD-044428 | C54: 26年 | D54: 7月 | E54: 品牌创意部 | F54: 直播中心 | G54: 直播助理 | H54: 文灿 | I54: 0.9811 | J54: 98.11 | K54: =K54:J54% | L54: 1100 | M54: 1000 | N54: {=_xlfn.XLOOKUP(H54,'OA名单'!C:C,'OA名单'!B:B,1)} | O54: =IF(N54=B54,1) | P54: {=_xlfn.XLOOKUP(N54,'OA名单'!B:B,'OA名单'!G:G)} | Q54: =IF(P54=E54,1) | R54: {=_xlfn.XLOOKUP(B54,'OA名单'!B:B,'OA名单'!F:F)} | S54: =IF(R54=F54,1) | U54: {=_xlfn.XLOOKUP(N54,'OA名单'!B:B,'OA名单'!E:E)} | V54: =IF(U54=G54,1)
B55: FD-030834 | C55: 26年 | D55: 7月 | E55: 广告策划部 | F55: 直播A中心 | G55: 直播助理 | H55: 郑岚珊 | I55: 0.9779 | J55: 98.04 | K55: =K55:J55% | L55: 1600 | M55: 1000 | N55: {=_xlfn.XLOOKUP(H55,'OA名单'!C:C,'OA名单'!B:B,1)} | O55: =IF(N55=B55,1) | P55: {=_xlfn.XLOOKUP(N55,'OA名单'!B:B,'OA名单'!G:G)} | Q55: =IF(P55=E55,1) | R55: {=_xlfn.XLOOKUP(B55,'OA名单'!B:B,'OA名单'!F:F)} | S55: =IF(R55=F55,1) | U55: {=_xlfn.XLOOKUP(N55,'OA名单'!B:B,'OA名单'!E:E)} | V55: =IF(U55=G55,1)
B56: FD-041846 | C56: 26年 | D56: 7月 | E56: 品牌创意部 | F56: 直播中心 | G56: 直播助理 | H56: 王佳豪 | I56: 0.9802 | J56: 98.02 | K56: =K56:J56% | L56: 700 | M56: 1000 | N56: {=_xlfn.XLOOKUP(H56,'OA名单'!C:C,'OA名单'!B:B,1)} | O56: =IF(N56=B56,1) | P56: {=_xlfn.XLOOKUP(N56,'OA名单'!B:B,'OA名单'!G:G)} | Q56: =IF(P56=E56,1) | R56: {=_xlfn.XLOOKUP(B56,'OA名单'!B:B,'OA名单'!F:F)} | S56: =IF(R56=F56,1) | U56: {=_xlfn.XLOOKUP(N56,'OA名单'!B:B,'OA名单'!E:E)} | V56: =IF(U56=G56,1)
B57: FD-035782 | C57: 26年 | D57: 7月 | E57: 广告策划部 | F57: 直播A中心 | G57: 直播助理 | H57: 刘天乐 | I57: 0.9788 | J57: 97.88 | K57: =K57:J57% | L57: 1000 | M57: 1000 | N57: {=_xlfn.XLOOKUP(H57,'OA名单'!C:C,'OA名单'!B:B,1)} | O57: =IF(N57=B57,1) | P57: {=_xlfn.XLOOKUP(N57,'OA名单'!B:B,'OA名单'!G:G)} | Q57: =IF(P57=E57,1) | R57: {=_xlfn.XLOOKUP(B57,'OA名单'!B:B,'OA名单'!F:F)} | S57: =IF(R57=F57,1) | U57: {=_xlfn.XLOOKUP(N57,'OA名单'!B:B,'OA名单'!E:E)} | V57: =IF(U57=G57,1)
B58: FD-032844 | C58: 26年 | D58: 7月 | E58: 广告策划部 | F58: 直播A中心 | G58: 直播助理 | H58: 秦璐璐 | I58: 0.9782 | J58: 97.82 | K58: =K58:J58% | L58: 2400 | M58: 1000 | N58: {=_xlfn.XLOOKUP(H58,'OA名单'!C:C,'OA名单'!B:B,1)} | O58: =IF(N58=B58,1) | P58: {=_xlfn.XLOOKUP(N58,'OA名单'!B:B,'OA名单'!G:G)} | Q58: =IF(P58=E58,1) | R58: {=_xlfn.XLOOKUP(B58,'OA名单'!B:B,'OA名单'!F:F)} | S58: =IF(R58=F58,1) | T58: {=_xlfn.XLOOKUP(B58,'系统-原始（副本）'!A:A,'系统-原始（副本）'!B:B)} | U58: {=_xlfn.XLOOKUP(N58,'OA名单'!B:B,'OA名单'!E:E)} | V58: =IF(U58=G58,1)
B59: FD-048165 | C59: 26年 | D59: 7月 | E59: 品牌创意部 | F59: 直播中心 | G59: 直播助理 | H59: 黎柳琴 | I59: 0.9778 | J59: 97.78 | K59: =K59:J59% | L59: 700 | M59: 1000 | N59: {=_xlfn.XLOOKUP(H59,'OA名单'!C:C,'OA名单'!B:B,1)} | O59: =IF(N59=B59,1) | P59: {=_xlfn.XLOOKUP(N59,'OA名单'!B:B,'OA名单'!G:G)} | Q59: =IF(P59=E59,1) | R59: {=_xlfn.XLOOKUP(B59,'OA名单'!B:B,'OA名单'!F:F)} | S59: =IF(R59=F59,1) | T59: {=_xlfn.XLOOKUP(B59,'系统-原始（副本）'!A:A,'系统-原始（副本）'!B:B)} | U59: {=_xlfn.XLOOKUP(N59,'OA名单'!B:B,'OA名单'!E:E)} | V59: =IF(U59=G59,1)
B60: FD-039267 | C60: 26年 | D60: 7月 | E60: 广告策划部 | F60: 直播A中心 | G60: 直播助理 | H60: 陈昌桧 | I60: 0.9776 | J60: 97.76 | K60: =K60:J60% | L60: 2100 | M60: 1000 | N60: {=_xlfn.XLOOKUP(H60,'OA名单'!C:C,'OA名单'!B:B,1)} | O60: =IF(N60=B60,1) | P60: {=_xlfn.XLOOKUP(N60,'OA名单'!B:B,'OA名单'!G:G)} | Q60: =IF(P60=E60,1) | R60: {=_xlfn.XLOOKUP(B60,'OA名单'!B:B,'OA名单'!F:F)} | S60: =IF(R60=F60,1) | U60: {=_xlfn.XLOOKUP(N60,'OA名单'!B:B,'OA名单'!E:E)} | V60: =IF(U60=G60,1)
B61: FD-048727 | C61: 26年 | D61: 7月 | E61: 品牌创意部 | F61: 直播中心 | G61: 直播助理 | H61: 李松雨 | I61: 0.9775 | J61: 97.75 | K61: =K61:J61% | L61: 300 | M61: 1000 | N61: {=_xlfn.XLOOKUP(H61,'OA名单'!C:C,'OA名单'!B:B,1)} | O61: =IF(N61=B61,1) | P61: {=_xlfn.XLOOKUP(N61,'OA名单'!B:B,'OA名单'!G:G)} | Q61: =IF(P61=E61,1) | R61: {=_xlfn.XLOOKUP(B61,'OA名单'!B:B,'OA名单'!F:F)} | S61: =IF(R61=F61,1) | U61: {=_xlfn.XLOOKUP(N61,'OA名单'!B:B,'OA名单'!E:E)} | V61: =IF(U61=G61,1)
B62: FD-049969 | C62: 26年 | D62: 7月 | E62: 品牌创意部 | F62: 直播中心 | G62: 直播助理 | H62: 李婕 | I62: 0.9768 | J62: 97.68 | K62: =K62:J62% | L62: 1000 | M62: 1000 | N62: {=_xlfn.XLOOKUP(H62,'OA名单'!C:C,'OA名单'!B:B,1)} | O62: =IF(N62=B62,1) | P62: {=_xlfn.XLOOKUP(N62,'OA名单'!B:B,'OA名单'!G:G)} | Q62: =IF(P62=E62,1) | R62: {=_xlfn.XLOOKUP(B62,'OA名单'!B:B,'OA名单'!F:F)} | S62: =IF(R62=F62,1) | T62: {=_xlfn.XLOOKUP(B62,'系统-原始（副本）'!A:A,'系统-原始（副本）'!B:B)} | U62: {=_xlfn.XLOOKUP(N62,'OA名单'!B:B,'OA名单'!E:E)} | V62: =IF(U62=G62,1)
B63: FD-027509 | C63: 26年 | D63: 7月 | E63: 品牌营销部 | F63: 直播中心 | G63: 直播助理 | H63: 刘楠 | I63: 0.95942 | J63: 97.5 | K63: 0.975 | L63: 3100 | M63: 1000 | N63: {=_xlfn.XLOOKUP(H63,'OA名单'!C:C,'OA名单'!B:B,1)} | O63: =IF(N63=B63,1) | P63: {=_xlfn.XLOOKUP(N63,'OA名单'!B:B,'OA名单'!G:G)} | Q63: =IF(P63=E63,1) | R63: {=_xlfn.XLOOKUP(B63,'OA名单'!B:B,'OA名单'!F:F)} | S63: =IF(R63=F63,1) | T63: {=_xlfn.XLOOKUP(B63,'系统-原始（副本）'!A:A,'系统-原始（副本）'!B:B)} | U63: {=_xlfn.XLOOKUP(N63,'OA名单'!B:B,'OA名单'!E:E)} | V63: =IF(U63=G63,1)
B64: FD-035758 | C64: 26年 | D64: 7月 | E64: 广告策划部 | F64: 直播A中心 | G64: 直播助理 | H64: 陈民晓 | I64: 0.9738 | J64: 97.38 | K64: =K64:J64% | L64: 1300 | M64: 1000 | N64: {=_xlfn.XLOOKUP(H64,'OA名单'!C:C,'OA名单'!B:B,1)} | O64: =IF(N64=B64,1) | P64: {=_xlfn.XLOOKUP(N64,'OA名单'!B:B,'OA名单'!G:G)} | Q64: =IF(P64=E64,1) | R64: {=_xlfn.XLOOKUP(B64,'OA名单'!B:B,'OA名单'!F:F)} | S64: =IF(R64=F64,1) | T64: {=_xlfn.XLOOKUP(B64,'系统-原始（副本）'!A:A,'系统-原始（副本）'!B:B)} | U64: {=_xlfn.XLOOKUP(N64,'OA名单'!B:B,'OA名单'!E:E)} | V64: =IF(U64=G64,1)
B65: FD-026227 | C65: 26年 | D65: 7月 | E65: 品牌营销部 | F65: 直播中心 | G65: 直播助理 | H65: 张佳黎 | I65: 0.9727 | J65: 97.27 | K65: 0.9727 | L65: 1550 | M65: 1000 | N65: {=_xlfn.XLOOKUP(H65,'OA名单'!C:C,'OA名单'!B:B,1)} | O65: =IF(N65=B65,1) | P65: {=_xlfn.XLOOKUP(N65,'OA名单'!B:B,'OA名单'!G:G)} | Q65: =IF(P65=E65,1) | R65: {=_xlfn.XLOOKUP(B65,'OA名单'!B:B,'OA名单'!F:F)} | S65: =IF(R65=F65,1) | T65: {=_xlfn.XLOOKUP(B65,'系统-原始（副本）'!A:A,'系统-原始（副本）'!B:B)} | U65: {=_xlfn.XLOOKUP(N65,'OA名单'!B:B,'OA名单'!E:E)} | V65: =IF(U65=G65,1)
B66: FD-025427 | C66: 26年 | D66: 7月 | E66: 品牌营销部 | F66: 直播中心 | G66: 直播助理 | H66: 曾梦怡 | I66: 0.9727 | J66: 97.27 | K66: 0.9727 | L66: 1550 | M66: 1000 | N66: {=_xlfn.XLOOKUP(H66,'OA名单'!C:C,'OA名单'!B:B,1)} | O66: =IF(N66=B66,1) | P66: {=_xlfn.XLOOKUP(N66,'OA名单'!B:B,'OA名单'!G:G)} | Q66: =IF(P66=E66,1) | R66: {=_xlfn.XLOOKUP(B66,'OA名单'!B:B,'OA名单'!F:F)} | S66: =IF(R66=F66,1) | T66: {=_xlfn.XLOOKUP(B66,'系统-原始（副本）'!A:A,'系统-原始（副本）'!B:B)} | U66: {=_xlfn.XLOOKUP(N66,'OA名单'!B:B,'OA名单'!E:E)} | V66: =IF(U66=G66,1)
B67: FD-035287 | C67: 26年 | D67: 7月 | E67: 广告策划部 | F67: 直播A中心 | G67: 直播助理 | H67: 吴淑敏 | I67: 0.9726 | J67: 97.26 | K67: =K67:J67% | L67: 1400 | M67: 1000 | N67: {=_xlfn.XLOOKUP(H67,'OA名单'!C:C,'OA名单'!B:B,1)} | O67: =IF(N67=B67,1) | P67: {=_xlfn.XLOOKUP(N67,'OA名单'!B:B,'OA名单'!G:G)} | Q67: =IF(P67=E67,1) | R67: {=_xlfn.XLOOKUP(B67,'OA名单'!B:B,'OA名单'!F:F)} | S67: =IF(R67=F67,1) | T67: {=_xlfn.XLOOKUP(B67,'系统-原始（副本）'!A:A,'系统-原始（副本）'!B:B)} | U67: {=_xlfn.XLOOKUP(N67,'OA名单'!B:B,'OA名单'!E:E)} | V67: =IF(U67=G67,1)
B68: FD-039977 | C68: 26年 | D68: 7月 | E68: 广告策划部 | F68: 直播A中心 | G68: 直播助理 | H68: 曾善美 | I68: 0.9711 | J68: 97.11 | K68: =K68:J68% | L68: 1100 | M68: 1000 | N68: {=_xlfn.XLOOKUP(H68,'OA名单'!C:C,'OA名单'!B:B,1)} | O68: =IF(N68=B68,1) | P68: {=_xlfn.XLOOKUP(N68,'OA名单'!B:B,'OA名单'!G:G)} | Q68: =IF(P68=E68,1) | R68: {=_xlfn.XLOOKUP(B68,'OA名单'!B:B,'OA名单'!F:F)} | S68: =IF(R68=F68,1) | T68: {=_xlfn.XLOOKUP(B68,'系统-原始（副本）'!A:A,'系统-原始（副本）'!B:B)} | U68: {=_xlfn.XLOOKUP(N68,'OA名单'!B:B,'OA名单'!E:E)} | V68: =IF(U68=G68,1)
B69: FD-035302 | C69: 26年 | D69: 7月 | E69: 广告策划部 | F69: 直播A中心 | G69: 直播助理 | H69: 吴洋 | I69: 0.9702 | J69: 97.02 | K69: =K69:J69% | L69: 1500 | M69: 1000 | N69: {=_xlfn.XLOOKUP(H69,'OA名单'!C:C,'OA名单'!B:B,1)} | O69: =IF(N69=B69,1) | P69: {=_xlfn.XLOOKUP(N69,'OA名单'!B:B,'OA名单'!G:G)} | Q69: =IF(P69=E69,1) | R69: {=_xlfn.XLOOKUP(B69,'OA名单'!B:B,'OA名单'!F:F)} | S69: =IF(R69=F69,1) | U69: {=_xlfn.XLOOKUP(N69,'OA名单'!B:B,'OA名单'!E:E)} | V69: =IF(U69=G69,1)
B70: FD-020791 | C70: 26年 | D70: 7月 | E70: 品牌营销部 | F70: 直播中心 | G70: 直播助理 | H70: 杨意肖 | I70: 0.9699 | J70: 96.99 | K70: 0.9699 | L70: 800 | M70: 1000 | N70: {=_xlfn.XLOOKUP(H70,'OA名单'!C:C,'OA名单'!B:B,1)} | O70: =IF(N70=B70,1) | P70: {=_xlfn.XLOOKUP(N70,'OA名单'!B:B,'OA名单'!G:G)} | Q70: =IF(P70=E70,1) | R70: {=_xlfn.XLOOKUP(B70,'OA名单'!B:B,'OA名单'!F:F)} | S70: =IF(R70=F70,1) | T70: {=_xlfn.XLOOKUP(B70,'系统-原始（副本）'!A:A,'系统-原始（副本）'!B:B)} | U70: {=_xlfn.XLOOKUP(N70,'OA名单'!B:B,'OA名单'!E:E)} | V70: =IF(U70=G70,1)
B71: FD-033796 | C71: 26年 | D71: 7月 | E71: 广告策划部 | F71: 直播A中心 | G71: 直播助理 | H71: 刘丙贵 | I71: 0.9698 | J71: 96.98 | K71: =K71:J71% | L71: 1000 | M71: 1000 | N71: {=_xlfn.XLOOKUP(H71,'OA名单'!C:C,'OA名单'!B:B,1)} | O71: =IF(N71=B71,1) | P71: {=_xlfn.XLOOKUP(N71,'OA名单'!B:B,'OA名单'!G:G)} | Q71: =IF(P71=E71,1) | R71: {=_xlfn.XLOOKUP(B71,'OA名单'!B:B,'OA名单'!F:F)} | S71: =IF(R71=F71,1) | U71: {=_xlfn.XLOOKUP(N71,'OA名单'!B:B,'OA名单'!E:E)} | V71: =IF(U71=G71,1)
B72: FD-027564 | C72: 26年 | D72: 7月 | E72: 品牌营销部 | F72: 直播中心 | G72: 直播助理 | H72: 蒙万叶 | I72: 0.96567 | J72: 96.56 | K72: 0.9656 | L72: 2800 | M72: 1000 | N72: {=_xlfn.XLOOKUP(H72,'OA名单'!C:C,'OA名单'!B:B,1)} | O72: =IF(N72=B72,1) | P72: {=_xlfn.XLOOKUP(N72,'OA名单'!B:B,'OA名单'!G:G)} | Q72: =IF(P72=E72,1) | R72: {=_xlfn.XLOOKUP(B72,'OA名单'!B:B,'OA名单'!F:F)} | S72: =IF(R72=F72,1) | T72: {=_xlfn.XLOOKUP(B72,'系统-原始（副本）'!A:A,'系统-原始（副本）'!B:B)} | U72: {=_xlfn.XLOOKUP(N72,'OA名单'!B:B,'OA名单'!E:E)} | V72: =IF(U72=G72,1)
B73: FD-035340 | C73: 26年 | D73: 7月 | E73: 广告策划部 | F73: 直播A中心 | G73: 直播助理 | H73: 廖晓佳 | I73: 0.9648 | J73: 96.48 | K73: =K73:J73% | L73: 700 | M73: 1000 | N73: {=_xlfn.XLOOKUP(H73,'OA名单'!C:C,'OA名单'!B:B,1)} | O73: =IF(N73=B73,1) | P73: {=_xlfn.XLOOKUP(N73,'OA名单'!B:B,'OA名单'!G:G)} | Q73: =IF(P73=E73,1) | R73: {=_xlfn.XLOOKUP(B73,'OA名单'!B:B,'OA名单'!F:F)} | S73: =IF(R73=F73,1) | U73: {=_xlfn.XLOOKUP(N73,'OA名单'!B:B,'OA名单'!E:E)} | V73: =IF(U73=G73,1)
B74: FD-021069 | C74: 26年 | D74: 7月 | E74: 品牌营销部 | F74: 直播中心 | G74: 直播助理 | H74: 杨冰 | I74: 0.963795 | J74: 96.38 | K74: 0.9638 | L74: 3350 | M74: 1000 | N74: {=_xlfn.XLOOKUP(H74,'OA名单'!C:C,'OA名单'!B:B,1)} | O74: =IF(N74=B74,1) | P74: {=_xlfn.XLOOKUP(N74,'OA名单'!B:B,'OA名单'!G:G)} | Q74: =IF(P74=E74,1) | R74: {=_xlfn.XLOOKUP(B74,'OA名单'!B:B,'OA名单'!F:F)} | S74: =IF(R74=F74,1) | T74: {=_xlfn.XLOOKUP(B74,'系统-原始（副本）'!A:A,'系统-原始（副本）'!B:B)} | U74: {=_xlfn.XLOOKUP(N74,'OA名单'!B:B,'OA名单'!E:E)} | V74: =IF(U74=G74,1)
B75: FD-037851 | C75: 26年 | D75: 7月 | E75: 广告策划部 | F75: 直播A中心 | G75: 直播助理 | H75: 陈宇恩 | I75: 0.9589 | J75: 96.3 | K75: =K75:J75% | L75: 1400 | M75: 1000 | N75: {=_xlfn.XLOOKUP(H75,'OA名单'!C:C,'OA名单'!B:B,1)} | O75: =IF(N75=B75,1) | P75: {=_xlfn.XLOOKUP(N75,'OA名单'!B:B,'OA名单'!G:G)} | Q75: =IF(P75=E75,1) | R75: {=_xlfn.XLOOKUP(B75,'OA名单'!B:B,'OA名单'!F:F)} | S75: =IF(R75=F75,1) | U75: {=_xlfn.XLOOKUP(N75,'OA名单'!B:B,'OA名单'!E:E)} | V75: =IF(U75=G75,1)
B76: FD-045169 | C76: 26年 | D76: 7月 | E76: 品牌营销部 | F76: 直播中心 | G76: 直播助理 | H76: 李雪儿 | I76: 0.9615 | J76: 96.15 | K76: =K76:J76% | L76: 625 | M76: 1000 | N76: {=_xlfn.XLOOKUP(H76,'OA名单'!C:C,'OA名单'!B:B,1)} | O76: =IF(N76=B76,1) | P76: {=_xlfn.XLOOKUP(N76,'OA名单'!B:B,'OA名单'!G:G)} | Q76: =IF(P76=E76,1) | R76: {=_xlfn.XLOOKUP(B76,'OA名单'!B:B,'OA名单'!F:F)} | S76: =IF(R76=F76,1) | U76: {=_xlfn.XLOOKUP(N76,'OA名单'!B:B,'OA名单'!E:E)} | V76: =IF(U76=G76,1)
B77: FD-021148 | C77: 26年 | D77: 7月 | E77: 品牌营销部 | F77: 直播中心 | G77: 直播助理 | H77: 吴建斌 | I77: 0.908725 | J77: 95.87 | K77: 0.9587 | L77: 1300 | M77: 1000 | N77: {=_xlfn.XLOOKUP(H77,'OA名单'!C:C,'OA名单'!B:B,1)} | O77: =IF(N77=B77,1) | P77: {=_xlfn.XLOOKUP(N77,'OA名单'!B:B,'OA名单'!G:G)} | Q77: =IF(P77=E77,1) | R77: {=_xlfn.XLOOKUP(B77,'OA名单'!B:B,'OA名单'!F:F)} | S77: =IF(R77=F77,1) | T77: {=_xlfn.XLOOKUP(B77,'系统-原始（副本）'!A:A,'系统-原始（副本）'!B:B)} | U77: {=_xlfn.XLOOKUP(N77,'OA名单'!B:B,'OA名单'!E:E)} | V77: =IF(U77=G77,1)
B78: FD-026842 | C78: 26年 | D78: 7月 | E78: 品牌营销部 | F78: 直播中心 | G78: 直播助理 | H78: 刘诗雨 | I78: 0.908725 | J78: 95.87 | K78: 0.9587 | L78: 1300 | M78: 1000 | N78: {=_xlfn.XLOOKUP(H78,'OA名单'!C:C,'OA名单'!B:B,1)} | O78: =IF(N78=B78,1) | P78: {=_xlfn.XLOOKUP(N78,'OA名单'!B:B,'OA名单'!G:G)} | Q78: =IF(P78=E78,1) | R78: {=_xlfn.XLOOKUP(B78,'OA名单'!B:B,'OA名单'!F:F)} | S78: =IF(R78=F78,1) | T78: {=_xlfn.XLOOKUP(B78,'系统-原始（副本）'!A:A,'系统-原始（副本）'!B:B)} | U78: {=_xlfn.XLOOKUP(N78,'OA名单'!B:B,'OA名单'!E:E)} | V78: =IF(U78=G78,1)
B79: FD-028768 | C79: 26年 | D79: 7月 | E79: 品牌营销部 | F79: 直播中心 | G79: 化妆师 | H79: 刘玉婷 | I79: 0.958125 | J79: 95.75 | K79: =K79:J79% | L79: 1806 | M79: 1000 | N79: {=_xlfn.XLOOKUP(H79,'OA名单'!C:C,'OA名单'!B:B,1)} | O79: =IF(N79=B79,1) | P79: {=_xlfn.XLOOKUP(N79,'OA名单'!B:B,'OA名单'!G:G)} | Q79: =IF(P79=E79,1) | R79: {=_xlfn.XLOOKUP(B79,'OA名单'!B:B,'OA名单'!F:F)} | S79: =IF(R79=F79,1) | U79: {=_xlfn.XLOOKUP(N79,'OA名单'!B:B,'OA名单'!E:E)} | V79: =IF(U79=G79,1)
B80: FD-021632 | C80: 26年 | D80: 7月 | E80: 品牌营销部 | F80: 直播中心 | G80: 直播助理 | H80: 刘子菁 | I80: 0.94423 | J80: 95.33 | K80: =K80:J80% | L80: 1900 | M80: 1000 | N80: {=_xlfn.XLOOKUP(H80,'OA名单'!C:C,'OA名单'!B:B,1)} | O80: =IF(N80=B80,1) | P80: {=_xlfn.XLOOKUP(N80,'OA名单'!B:B,'OA名单'!G:G)} | Q80: =IF(P80=E80,1) | R80: {=_xlfn.XLOOKUP(B80,'OA名单'!B:B,'OA名单'!F:F)} | S80: =IF(R80=F80,1) | U80: {=_xlfn.XLOOKUP(N80,'OA名单'!B:B,'OA名单'!E:E)} | V80: =IF(U80=G80,1)
B81: FD-023139 | C81: 26年 | D81: 7月 | E81: 品牌营销部 | F81: 直播中心 | G81: 直播助理 | H81: 李玥滢 | I81: 0.903475 | J81: 95.12 | K81: 0.9512 | L81: 700 | M81: 1000 | N81: {=_xlfn.XLOOKUP(H81,'OA名单'!C:C,'OA名单'!B:B,1)} | O81: =IF(N81=B81,1) | P81: {=_xlfn.XLOOKUP(N81,'OA名单'!B:B,'OA名单'!G:G)} | Q81: =IF(P81=E81,1) | R81: {=_xlfn.XLOOKUP(B81,'OA名单'!B:B,'OA名单'!F:F)} | S81: =IF(R81=F81,1) | T81: {=_xlfn.XLOOKUP(B81,'系统-原始（副本）'!A:A,'系统-原始（副本）'!B:B)} | U81: {=_xlfn.XLOOKUP(N81,'OA名单'!B:B,'OA名单'!E:E)} | V81: =IF(U81=G81,1)
B82: FD-022757 | C82: 26年 | D82: 7月 | E82: 品牌营销部 | F82: 直播中心 | G82: 化妆师 | H82: 肖慧萍 | I82: 0.947875 | J82: 94.82 | K82: =K82:J82% | L82: 1462 | M82: 1000 | N82: {=_xlfn.XLOOKUP(H82,'OA名单'!C:C,'OA名单'!B:B,1)} | O82: =IF(N82=B82,1) | P82: {=_xlfn.XLOOKUP(N82,'OA名单'!B:B,'OA名单'!G:G)} | Q82: =IF(P82=E82,1) | R82: {=_xlfn.XLOOKUP(B82,'OA名单'!B:B,'OA名单'!F:F)} | S82: =IF(R82=F82,1) | U82: {=_xlfn.XLOOKUP(N82,'OA名单'!B:B,'OA名单'!E:E)} | V82: =IF(U82=G82,1)
B83: FD-025351 | C83: 26年 | D83: 7月 | E83: 品牌营销部 | F83: 直播中心 | G83: 直播助理 | H83: 陈嘉欣 | I83: 0.946919 | J83: 94.69 | K83: 0.9469 | L83: 2500 | M83: 1000 | N83: {=_xlfn.XLOOKUP(H83,'OA名单'!C:C,'OA名单'!B:B,1)} | O83: =IF(N83=B83,1) | P83: {=_xlfn.XLOOKUP(N83,'OA名单'!B:B,'OA名单'!G:G)} | Q83: =IF(P83=E83,1) | R83: {=_xlfn.XLOOKUP(B83,'OA名单'!B:B,'OA名单'!F:F)} | S83: =IF(R83=F83,1) | T83: {=_xlfn.XLOOKUP(B83,'系统-原始（副本）'!A:A,'系统-原始（副本）'!B:B)} | U83: {=_xlfn.XLOOKUP(N83,'OA名单'!B:B,'OA名单'!E:E)} | V83: =IF(U83=G83,1)
B84: FD-029073 | C84: 26年 | D84: 7月 | E84: 品牌营销部 | F84: 直播中心 | G84: 直播助理 | H84: 谭雅彬 | I84: 0.898225 | J84: 94.37 | K84: 0.9437 | L84: 550 | M84: 1000 | N84: {=_xlfn.XLOOKUP(H84,'OA名单'!C:C,'OA名单'!B:B,1)} | O84: =IF(N84=B84,1) | P84: {=_xlfn.XLOOKUP(N84,'OA名单'!B:B,'OA名单'!G:G)} | Q84: =IF(P84=E84,1) | R84: {=_xlfn.XLOOKUP(B84,'OA名单'!B:B,'OA名单'!F:F)} | S84: =IF(R84=F84,1) | T84: {=_xlfn.XLOOKUP(B84,'系统-原始（副本）'!A:A,'系统-原始（副本）'!B:B)} | U84: {=_xlfn.XLOOKUP(N84,'OA名单'!B:B,'OA名单'!E:E)} | V84: =IF(U84=G84,1)
B85: FD-028735 | C85: 26年 | D85: 7月 | E85: 品牌营销部 | F85: 直播中心 | G85: 直播助理 | H85: 尹珩瑞 | I85: 0.94317 | J85: 94.31 | K85: 0.9431 | L85: 2050 | M85: 1000 | N85: {=_xlfn.XLOOKUP(H85,'OA名单'!C:C,'OA名单'!B:B,1)} | O85: =IF(N85=B85,1) | P85: {=_xlfn.XLOOKUP(N85,'OA名单'!B:B,'OA名单'!G:G)} | Q85: =IF(P85=E85,1) | R85: {=_xlfn.XLOOKUP(B85,'OA名单'!B:B,'OA名单'!F:F)} | S85: =IF(R85=F85,1) | T85: {=_xlfn.XLOOKUP(B85,'系统-原始（副本）'!A:A,'系统-原始（副本）'!B:B)} | U85: {=_xlfn.XLOOKUP(N85,'OA名单'!B:B,'OA名单'!E:E)} | V85: =IF(U85=G85,1)
B86: FD-092712 | C86: 26年 | D86: 7月 | E86: 产品供应部 | F86: 服务中心 | G86: 客服经理 | H86: 蓝文诗 | I86: 0.943 | J86: 94.2 | K86: =K86:J86% | L86: 2364 | M86: 2000 | N86: {=_xlfn.XLOOKUP(H86,'OA名单'!C:C,'OA名单'!B:B,1)} | O86: =IF(N86=B86,1) | P86: {=_xlfn.XLOOKUP(N86,'OA名单'!B:B,'OA名单'!G:G)} | Q86: =IF(P86=E86,1) | R86: {=_xlfn.XLOOKUP(B86,'OA名单'!B:B,'OA名单'!F:F)} | S86: =IF(R86=F86,1) | T86: {=_xlfn.XLOOKUP(B86,'系统-原始（副本）'!A:A,'系统-原始（副本）'!B:B)} | U86: {=_xlfn.XLOOKUP(N86,'OA名单'!B:B,'OA名单'!E:E)} | V86: =IF(U86=G86,1)
B87: FD-099565 | C87: 26年 | D87: 7月 | E87: 产品供应部 | F87: 服务中心 | G87: 客服专员 | H87: 温颖妍 | I87: 0.94 | J87: 94 | K87: =K87:J87% | L87: 1551 | M87: 1200 | N87: {=_xlfn.XLOOKUP(H87,'OA名单'!C:C,'OA名单'!B:B,1)} | O87: =IF(N87=B87,1) | P87: {=_xlfn.XLOOKUP(N87,'OA名单'!B:B,'OA名单'!G:G)} | Q87: =IF(P87=E87,1) | R87: {=_xlfn.XLOOKUP(B87,'OA名单'!B:B,'OA名单'!F:F)} | S87: =IF(R87=F87,1) | T87: {=_xlfn.XLOOKUP(B87,'系统-原始（副本）'!A:A,'系统-原始（副本）'!B:B)} | U87: {=_xlfn.XLOOKUP(N87,'OA名单'!B:B,'OA名单'!E:E)} | V87: =IF(U87=G87,1)
B88: FD-098975 | C88: 26年 | D88: 7月 | E88: 产品供应部 | F88: 服务中心 | G88: 客服专员 | H88: 邓泽丽 | I88: 0.94 | J88: 94 | K88: =K88:J88% | L88: 1646 | M88: 1200 | N88: {=_xlfn.XLOOKUP(H88,'OA名单'!C:C,'OA名单'!B:B,1)} | O88: =IF(N88=B88,1) | P88: {=_xlfn.XLOOKUP(N88,'OA名单'!B:B,'OA名单'!G:G)} | Q88: =IF(P88=E88,1) | R88: {=_xlfn.XLOOKUP(B88,'OA名单'!B:B,'OA名单'!F:F)} | S88: =IF(R88=F88,1) | U88: {=_xlfn.XLOOKUP(N88,'OA名单'!B:B,'OA名单'!E:E)} | V88: =IF(U88=G88,1)
B89: FD-092596 | C89: 26年 | D89: 7月 | E89: 产品供应部 | F89: 服务中心 | G89: 客服专员 | H89: 简韵 | I89: 0.425 | J89: 94 | K89: =K89:J89% | L89: 1479 | M89: 1200 | N89: {=_xlfn.XLOOKUP(H89,'OA名单'!C:C,'OA名单'!B:B,1)} | O89: =IF(N89=B89,1) | P89: {=_xlfn.XLOOKUP(N89,'OA名单'!B:B,'OA名单'!G:G)} | Q89: =IF(P89=E89,1) | R89: {=_xlfn.XLOOKUP(B89,'OA名单'!B:B,'OA名单'!F:F)} | S89: =IF(R89=F89,1) | U89: {=_xlfn.XLOOKUP(N89,'OA名单'!B:B,'OA名单'!E:E)} | V89: =IF(U89=G89,1)
B90: FD-026971 | C90: 26年 | D90: 7月 | E90: 品牌营销部 | F90: 直播中心 | G90: 直播助理 | H90: 曾睿琳 | I90: 0.93373 | J90: 93.83 | K90: 0.9383 | L90: 1433.33 | M90: 1000 | N90: {=_xlfn.XLOOKUP(H90,'OA名单'!C:C,'OA名单'!B:B,1)} | O90: =IF(N90=B90,1) | P90: {=_xlfn.XLOOKUP(N90,'OA名单'!B:B,'OA名单'!G:G)} | Q90: =IF(P90=E90,1) | R90: {=_xlfn.XLOOKUP(B90,'OA名单'!B:B,'OA名单'!F:F)} | S90: =IF(R90=F90,1) | T90: {=_xlfn.XLOOKUP(B90,'系统-原始（副本）'!A:A,'系统-原始（副本）'!B:B)} | U90: {=_xlfn.XLOOKUP(N90,'OA名单'!B:B,'OA名单'!E:E)} | V90: =IF(U90=G90,1)
B91: FD-027796 | C91: 26年 | D91: 7月 | E91: 品牌营销部 | F91: 直播中心 | G91: 直播助理 | H91: 宁燕 | I91: 0.93373 | J91: 93.83 | K91: =K91:J91% | L91: 1533.33 | M91: 1000 | N91: {=_xlfn.XLOOKUP(H91,'OA名单'!C:C,'OA名单'!B:B,1)} | O91: =IF(N91=B91,1) | P91: {=_xlfn.XLOOKUP(N91,'OA名单'!B:B,'OA名单'!G:G)} | Q91: =IF(P91=E91,1) | R91: {=_xlfn.XLOOKUP(B91,'OA名单'!B:B,'OA名单'!F:F)} | S91: =IF(R91=F91,1) | T91: {=_xlfn.XLOOKUP(B91,'系统-原始（副本）'!A:A,'系统-原始（副本）'!B:B)} | U91: {=_xlfn.XLOOKUP(N91,'OA名单'!B:B,'OA名单'!E:E)} | V91: =IF(U91=G91,1)
B92: FD-025314 | C92: 26年 | D92: 7月 | E92: 品牌营销部 | F92: 直播中心 | G92: 直播助理 | H92: 杜润瀚 | I92: 0.9377 | J92: 93.77 | K92: 0.9377 | L92: 600 | M92: 1000 | N92: {=_xlfn.XLOOKUP(H92,'OA名单'!C:C,'OA名单'!B:B,1)} | O92: =IF(N92=B92,1) | P92: {=_xlfn.XLOOKUP(N92,'OA名单'!B:B,'OA名单'!G:G)} | Q92: =IF(P92=E92,1) | R92: {=_xlfn.XLOOKUP(B92,'OA名单'!B:B,'OA名单'!F:F)} | S92: =IF(R92=F92,1) | T92: {=_xlfn.XLOOKUP(B92,'系统-原始（副本）'!A:A,'系统-原始（副本）'!B:B)} | U92: {=_xlfn.XLOOKUP(N92,'OA名单'!B:B,'OA名单'!E:E)} | V92: =IF(U92=G92,1)
B93: FD-027333 | C93: 26年 | D93: 7月 | E93: 品牌营销部 | F93: 直播中心 | G93: 化妆师 | H93: 邓艳佳 | I93: 0.933375 | J93: 93.27 | K93: =K93:J93% | L93: 1032 | M93: 2300 | N93: {=_xlfn.XLOOKUP(H93,'OA名单'!C:C,'OA名单'!B:B,1)} | O93: =IF(N93=B93,1) | P93: {=_xlfn.XLOOKUP(N93,'OA名单'!B:B,'OA名单'!G:G)} | Q93: =IF(P93=E93,1) | R93: {=_xlfn.XLOOKUP(B93,'OA名单'!B:B,'OA名单'!F:F)} | S93: =IF(R93=F93,1) | U93: {=_xlfn.XLOOKUP(N93,'OA名单'!B:B,'OA名单'!E:E)} | V93: =IF(U93=G93,1)
B94: FD-025742 | C94: 26年 | D94: 7月 | E94: 品牌营销部 | F94: 直播中心 | G94: 直播助理 | H94: 吴政锐 | I94: 0.89035 | J94: 93.25 | K94: 0.9325 | L94: 400 | M94: 1000 | N94: {=_xlfn.XLOOKUP(H94,'OA名单'!C:C,'OA名单'!B:B,1)} | O94: =IF(N94=B94,1) | P94: {=_xlfn.XLOOKUP(N94,'OA名单'!B:B,'OA名单'!G:G)} | Q94: =IF(P94=E94,1) | R94: {=_xlfn.XLOOKUP(B94,'OA名单'!B:B,'OA名单'!F:F)} | S94: =IF(R94=F94,1) | T94: {=_xlfn.XLOOKUP(B94,'系统-原始（副本）'!A:A,'系统-原始（副本）'!B:B)} | U94: {=_xlfn.XLOOKUP(N94,'OA名单'!B:B,'OA名单'!E:E)} | V94: =IF(U94=G94,1)
B95: FD-022320 | C95: 26年 | D95: 7月 | E95: 品牌营销部 | F95: 直播中心 | G95: 直播助理 | H95: 李忠翰 | I95: 0.9321 | J95: 93.21 | K95: 0.9321 | L95: 400 | M95: 1000 | N95: {=_xlfn.XLOOKUP(H95,'OA名单'!C:C,'OA名单'!B:B,1)} | O95: =IF(N95=B95,1) | P95: {=_xlfn.XLOOKUP(N95,'OA名单'!B:B,'OA名单'!G:G)} | Q95: =IF(P95=E95,1) | R95: {=_xlfn.XLOOKUP(B95,'OA名单'!B:B,'OA名单'!F:F)} | S95: =IF(R95=F95,1) | T95: {=_xlfn.XLOOKUP(B95,'系统-原始（副本）'!A:A,'系统-原始（副本）'!B:B)} | U95: {=_xlfn.XLOOKUP(N95,'OA名单'!B:B,'OA名单'!E:E)} | V95: =IF(U95=G95,1)
B96: FD-021873 | C96: 26年 | D96: 7月 | E96: 品牌营销部 | F96: 直播中心 | G96: 直播助理 | H96: 张泽诚 | I96: 0.9247 | J96: 92.47 | K96: 0.9247 | L96: 0 | M96: 1000 | N96: {=_xlfn.XLOOKUP(H96,'OA名单'!C:C,'OA名单'!B:B,1)} | O96: =IF(N96=B96,1) | P96: {=_xlfn.XLOOKUP(N96,'OA名单'!B:B,'OA名单'!G:G)} | Q96: =IF(P96=E96,1) | R96: {=_xlfn.XLOOKUP(B96,'OA名单'!B:B,'OA名单'!F:F)} | S96: =IF(R96=F96,1) | T96: {=_xlfn.XLOOKUP(B96,'系统-原始（副本）'!A:A,'系统-原始（副本）'!B:B)} | U96: {=_xlfn.XLOOKUP(N96,'OA名单'!B:B,'OA名单'!E:E)} | V96: =IF(U96=G96,1)
B97: FD-020646 | C97: 26年 | D97: 7月 | E97: 品牌营销部 | F97: 直播中心 | G97: 直播助理 | H97: 林梓烁 | I97: 0.920669 | J97: 92.06 | K97: =K97:J97% | L97: 800 | M97: 1000 | N97: {=_xlfn.XLOOKUP(H97,'OA名单'!C:C,'OA名单'!B:B,1)} | O97: =IF(N97=B97,1) | P97: {=_xlfn.XLOOKUP(N97,'OA名单'!B:B,'OA名单'!G:G)} | Q97: =IF(P97=E97,1) | R97: {=_xlfn.XLOOKUP(B97,'OA名单'!B:B,'OA名单'!F:F)} | S97: =IF(R97=F97,1) | U97: {=_xlfn.XLOOKUP(N97,'OA名单'!B:B,'OA名单'!E:E)} | V97: =IF(U97=G97,1)
B98: FD-026363 | C98: 26年 | D98: 7月 | E98: 品牌营销部 | F98: 直播中心 | G98: 直播助理 | H98: 左世婷 | I98: 0.91973 | J98: 91.83 | K98: 0.9183 | L98: 1433.33 | M98: 1000 | N98: {=_xlfn.XLOOKUP(H98,'OA名单'!C:C,'OA名单'!B:B,1)} | O98: =IF(N98=B98,1) | P98: {=_xlfn.XLOOKUP(N98,'OA名单'!B:B,'OA名单'!G:G)} | Q98: =IF(P98=E98,1) | R98: {=_xlfn.XLOOKUP(B98,'OA名单'!B:B,'OA名单'!F:F)} | S98: =IF(R98=F98,1) | T98: {=_xlfn.XLOOKUP(B98,'系统-原始（副本）'!A:A,'系统-原始（副本）'!B:B)} | U98: {=_xlfn.XLOOKUP(N98,'OA名单'!B:B,'OA名单'!E:E)} | V98: =IF(U98=G98,1)
B99: FD-098633 | C99: 26年 | D99: 7月 | E99: 产品供应部 | F99: 服务中心 | G99: 客服专员 | H99: 莫秋霞 | I99: 0.9135 | J99: 91.4 | K99: =K99:J99% | L99: 2479 | M99: 2500 | N99: {=_xlfn.XLOOKUP(H99,'OA名单'!C:C,'OA名单'!B:B,1)} | O99: =IF(N99=B99,1) | P99: {=_xlfn.XLOOKUP(N99,'OA名单'!B:B,'OA名单'!G:G)} | Q99: =IF(P99=E99,1) | R99: {=_xlfn.XLOOKUP(B99,'OA名单'!B:B,'OA名单'!F:F)} | S99: =IF(R99=F99,1) | T99: {=_xlfn.XLOOKUP(B99,'系统-原始（副本）'!A:A,'系统-原始（副本）'!B:B)} | U99: {=_xlfn.XLOOKUP(N99,'OA名单'!B:B,'OA名单'!E:E)} | V99: =IF(U99=G99,1)
B100: FD-027291 | C100: 26年 | D100: 7月 | E100: 品牌营销部 | F100: 直播中心 | G100: 直播助理 | H100: 韦彩云 | I100: 0.91317 | J100: 91.31 | K100: =K100:J100% | L100: 600 | M100: 1000 | N100: {=_xlfn.XLOOKUP(H100,'OA名单'!C:C,'OA名单'!B:B,1)} | O100: =IF(N100=B100,1) | P100: {=_xlfn.XLOOKUP(N100,'OA名单'!B:B,'OA名单'!G:G)} | Q100: =IF(P100=E100,1) | R100: {=_xlfn.XLOOKUP(B100,'OA名单'!B:B,'OA名单'!F:F)} | S100: =IF(R100=F100,1) | U100: {=_xlfn.XLOOKUP(N100,'OA名单'!B:B,'OA名单'!E:E)} | V100: =IF(U100=G100,1)
B101: FD-020695 | C101: 26年 | D101: 7月 | E101: 品牌营销部 | F101: 直播中心 | G101: 直播助理 | H101: 黄佩娜 | I101: 0.90923 | J101: 90.33 | K101: 0.9033 | L101: 1000 | M101: 1000 | N101: {=_xlfn.XLOOKUP(H101,'OA名单'!C:C,'OA名单'!B:B,1)} | O101: =IF(N101=B101,1) | P101: {=_xlfn.XLOOKUP(N101,'OA名单'!B:B,'OA名单'!G:G)} | Q101: =IF(P101=E101,1) | R101: {=_xlfn.XLOOKUP(B101,'OA名单'!B:B,'OA名单'!F:F)} | S101: =IF(R101=F101,1) | T101: {=_xlfn.XLOOKUP(B101,'系统-原始（副本）'!A:A,'系统-原始（副本）'!B:B)} | U101: {=_xlfn.XLOOKUP(N101,'OA名单'!B:B,'OA名单'!E:E)} | V101: =IF(U101=G101,1)
B102: OD-004665 | C102: 26年 | D102: 7月 | E102: 新品牌事业部 | F102: 品牌创意中心 | G102: 订单交付员 | H102: 张晓琳 | I102: 0.888 | J102: 88.8 | K102: =K102:J102% | L102: 852.5 | M102: 1200 | N102: {=_xlfn.XLOOKUP(H102,'OA名单'!C:C,'OA名单'!B:B,1)} | O102: =IF(N102=B102,1) | P102: {=_xlfn.XLOOKUP(N102,'OA名单'!B:B,'OA名单'!G:G)} | Q102: =IF(P102=E102,1) | R102: {=_xlfn.XLOOKUP(B102,'OA名单'!B:B,'OA名单'!F:F)} | S102: =IF(R102=F102,1) | T102: {=_xlfn.XLOOKUP(B102,'系统-原始（副本）'!A:A,'系统-原始（副本）'!B:B)} | U102: {=_xlfn.XLOOKUP(N102,'OA名单'!B:B,'OA名单'!E:E)} | V102: =IF(U102=G102,1)
B103: FD-028559 | C103: 26年 | D103: 7月 | E103: 品牌营销部 | F103: 直播中心 | G103: 直播助理 | H103: 雷惠朝 | I103: 0.88317 | J103: 88.31 | K103: 0.8831 | L103: 400 | M103: 1000 | N103: {=_xlfn.XLOOKUP(H103,'OA名单'!C:C,'OA名单'!B:B,1)} | O103: =IF(N103=B103,1) | P103: {=_xlfn.XLOOKUP(N103,'OA名单'!B:B,'OA名单'!G:G)} | Q103: =IF(P103=E103,1) | R103: {=_xlfn.XLOOKUP(B103,'OA名单'!B:B,'OA名单'!F:F)} | S103: =IF(R103=F103,1) | T103: {=_xlfn.XLOOKUP(B103,'系统-原始（副本）'!A:A,'系统-原始（副本）'!B:B)} | U103: {=_xlfn.XLOOKUP(N103,'OA名单'!B:B,'OA名单'!E:E)} | V103: =IF(U103=G103,1)
B104: FD-091042 | C104: 26年 | D104: 7月 | E104: 产品供应部 | F104: 服务中心 | G104: 客服专员 | H104: 李秋静 | I104: 0.88 | J104: 88 | K104: =K104:J104% | L104: 0 | M104: 1200 | N104: {=_xlfn.XLOOKUP(H104,'OA名单'!C:C,'OA名单'!B:B,1)} | O104: =IF(N104=B104,1) | P104: {=_xlfn.XLOOKUP(N104,'OA名单'!B:B,'OA名单'!G:G)} | Q104: =IF(P104=E104,1) | R104: {=_xlfn.XLOOKUP(B104,'OA名单'!B:B,'OA名单'!F:F)} | S104: =IF(R104=F104,1) | T104: {=_xlfn.XLOOKUP(B104,'系统-原始（副本）'!A:A,'系统-原始（副本）'!B:B)} | U104: {=_xlfn.XLOOKUP(N104,'OA名单'!B:B,'OA名单'!E:E)} | V104: =IF(U104=G104,1)
B105: FD-022049 | C105: 26年 | D105: 7月 | E105: 品牌营销部 | F105: 直播中心 | G105: 直播助理 | H105: 刘玉婷 | I105: 0.875748 | J105: 87.57 | K105: 0.8757 | L105: 425 | M105: 1000 | N105: {=_xlfn.XLOOKUP(H105,'OA名单'!C:C,'OA名单'!B:B,1)} | O105: =IF(N105=B105,1) | P105: {=_xlfn.XLOOKUP(N105,'OA名单'!B:B,'OA名单'!G:G)} | Q105: =IF(P105=E105,1) | R105: {=_xlfn.XLOOKUP(B105,'OA名单'!B:B,'OA名单'!F:F)} | S105: =IF(R105=F105,1) | T105: {=_xlfn.XLOOKUP(B105,'系统-原始（副本）'!A:A,'系统-原始（副本）'!B:B)} | U105: {=_xlfn.XLOOKUP(N105,'OA名单'!B:B,'OA名单'!E:E)} | V105: =IF(U105=G105,1)
B106: FD-091079 | C106: 26年 | D106: 7月 | E106: 产品供应部 | F106: 服务中心 | G106: 客服专员 | H106: 郭瑶 | I106: 0.865 | J106: 87 | K106: =K106:J106% | L106: 2250 | M106: 1500 | N106: {=_xlfn.XLOOKUP(H106,'OA名单'!C:C,'OA名单'!B:B,1)} | O106: =IF(N106=B106,1) | P106: {=_xlfn.XLOOKUP(N106,'OA名单'!B:B,'OA名单'!G:G)} | Q106: =IF(P106=E106,1) | R106: {=_xlfn.XLOOKUP(B106,'OA名单'!B:B,'OA名单'!F:F)} | S106: =IF(R106=F106,1) | U106: {=_xlfn.XLOOKUP(N106,'OA名单'!B:B,'OA名单'!E:E)} | V106: =IF(U106=G106,1)
B107: FD-094004 | C107: 26年 | D107: 7月 | E107: 产品供应部 | F107: 服务中心 | G107: 客服专员 | H107: 梁丽娟 | I107: 0.851 | J107: 86 | K107: =K107:J107% | L107: 2137 | M107: 2000 | N107: {=_xlfn.XLOOKUP(H107,'OA名单'!C:C,'OA名单'!B:B,1)} | O107: =IF(N107=B107,1) | P107: {=_xlfn.XLOOKUP(N107,'OA名单'!B:B,'OA名单'!G:G)} | Q107: =IF(P107=E107,1) | R107: {=_xlfn.XLOOKUP(B107,'OA名单'!B:B,'OA名单'!F:F)} | S107: =IF(R107=F107,1) | T107: {=_xlfn.XLOOKUP(B107,'系统-原始（副本）'!A:A,'系统-原始（副本）'!B:B)} | U107: {=_xlfn.XLOOKUP(N107,'OA名单'!B:B,'OA名单'!E:E)} | V107: =IF(U107=G107,1)
B108: FD-091806 | C108: 26年 | D108: 7月 | E108: 产品供应部 | F108: 服务中心 | G108: 客服专员 | H108: 谭颖 | I108: 0.86 | J108: 86 | K108: =K108:J108% | L108: 1056 | M108: 1200 | N108: {=_xlfn.XLOOKUP(H108,'OA名单'!C:C,'OA名单'!B:B,1)} | O108: =IF(N108=B108,1) | P108: {=_xlfn.XLOOKUP(N108,'OA名单'!B:B,'OA名单'!G:G)} | Q108: =IF(P108=E108,1) | R108: {=_xlfn.XLOOKUP(B108,'OA名单'!B:B,'OA名单'!F:F)} | S108: =IF(R108=F108,1) | U108: {=_xlfn.XLOOKUP(N108,'OA名单'!B:B,'OA名单'!E:E)} | V108: =IF(U108=G108,1)
B109: FD-092674 | C109: 26年 | D109: 7月 | E109: 产品供应部 | F109: 服务中心 | G109: 客服专员 | H109: 袁颖 | I109: 0.855 | J109: 85.5 | K109: =K109:J109% | L109: 2176 | M109: 2000 | N109: {=_xlfn.XLOOKUP(H109,'OA名单'!C:C,'OA名单'!B:B,1)} | O109: =IF(N109=B109,1) | P109: {=_xlfn.XLOOKUP(N109,'OA名单'!B:B,'OA名单'!G:G)} | Q109: =IF(P109=E109,1) | R109: {=_xlfn.XLOOKUP(B109,'OA名单'!B:B,'OA名单'!F:F)} | S109: =IF(R109=F109,1) | U109: {=_xlfn.XLOOKUP(N109,'OA名单'!B:B,'OA名单'!E:E)} | V109: =IF(U109=G109,1)
B110: FD-025019 | C110: 26年 | D110: 7月 | E110: 品牌营销部 | F110: 直播中心 | G110: 中级直播助理 | H110: 赖燕妮 | I110: 0.85 | J110: 85 | K110: =K110:J110% | L110: 1700 | M110: 2000 | N110: {=_xlfn.XLOOKUP(H110,'OA名单'!C:C,'OA名单'!B:B,1)} | O110: =IF(N110=B110,1) | P110: {=_xlfn.XLOOKUP(N110,'OA名单'!B:B,'OA名单'!G:G)} | Q110: =IF(P110=E110,1) | R110: {=_xlfn.XLOOKUP(B110,'OA名单'!B:B,'OA名单'!F:F)} | S110: =IF(R110=F110,1) | T110: {=_xlfn.XLOOKUP(B110,'系统-原始（副本）'!A:A,'系统-原始（副本）'!B:B)} | U110: {=_xlfn.XLOOKUP(N110,'OA名单'!B:B,'OA名单'!E:E)} | V110: =IF(U110=G110,1)
B111: SX-003214 | C111: 26年 | D111: 7月 | E111: AI效率流程部 | F111: AI研究中心 | G111: 测试实习生 | H111: 陶伟豪 | I111: 0.85 | J111: 85 | K111: =K111:J111% | L111: 0 | M111: 0 | N111: {=_xlfn.XLOOKUP(H111,'OA名单'!C:C,'OA名单'!B:B,1)} | O111: =IF(N111=B111,1) | P111: {=_xlfn.XLOOKUP(N111,'OA名单'!B:B,'OA名单'!G:G)} | Q111: =IF(P111=E111,1) | R111: {=_xlfn.XLOOKUP(B111,'OA名单'!B:B,'OA名单'!F:F)} | S111: =IF(R111=F111,1) | T111: {=_xlfn.XLOOKUP(B111,'系统-原始（副本）'!A:A,'系统-原始（副本）'!B:B)} | U111: {=_xlfn.XLOOKUP(N111,'OA名单'!B:B,'OA名单'!E:E)} | V111: =IF(U111=G111,1)
B112: FD-023810 | C112: 26年 | D112: 7月 | E112: 品牌营销部 | F112: 直播中心 | G112: 直播助理 | H112: 胡雄波 | I112: 0.819475 | J112: 83.12 | K112: 0.8312 | L112: 250 | M112: 1000 | N112: {=_xlfn.XLOOKUP(H112,'OA名单'!C:C,'OA名单'!B:B,1)} | O112: =IF(N112=B112,1) | P112: {=_xlfn.XLOOKUP(N112,'OA名单'!B:B,'OA名单'!G:G)} | Q112: =IF(P112=E112,1) | R112: {=_xlfn.XLOOKUP(B112,'OA名单'!B:B,'OA名单'!F:F)} | S112: =IF(R112=F112,1) | T112: {=_xlfn.XLOOKUP(B112,'系统-原始（副本）'!A:A,'系统-原始（副本）'!B:B)} | U112: {=_xlfn.XLOOKUP(N112,'OA名单'!B:B,'OA名单'!E:E)} | V112: =IF(U112=G112,1)
B113: FD-098102 | C113: 26年 | D113: 7月 | E113: 产品供应部 | F113: 服务中心 | G113: 客服专员 | H113: 夏润利 | I113: 0.832 | J113: 83 | K113: =K113:J113% | L113: 1248 | M113: 1500 | N113: {=_xlfn.XLOOKUP(H113,'OA名单'!C:C,'OA名单'!B:B,1)} | O113: =IF(N113=B113,1) | P113: {=_xlfn.XLOOKUP(N113,'OA名单'!B:B,'OA名单'!G:G)} | Q113: =IF(P113=E113,1) | R113: {=_xlfn.XLOOKUP(B113,'OA名单'!B:B,'OA名单'!F:F)} | S113: =IF(R113=F113,1) | T113: {=_xlfn.XLOOKUP(B113,'系统-原始（副本）'!A:A,'系统-原始（副本）'!B:B)} | U113: {=_xlfn.XLOOKUP(N113,'OA名单'!B:B,'OA名单'!E:E)} | V113: =IF(U113=G113,1)
B114: FD-029809 | C114: 26年 | D114: 7月 | E114: 品牌营销部 | F114: 直播中心 | G114: 直播助理 | H114: 郑海涛 | I114: 0.8519 | J114: 82.14 | K114: 0.8214 | L114: 850 | M114: 1000 | N114: {=_xlfn.XLOOKUP(H114,'OA名单'!C:C,'OA名单'!B:B,1)} | O114: =IF(N114=B114,1) | P114: {=_xlfn.XLOOKUP(N114,'OA名单'!B:B,'OA名单'!G:G)} | Q114: =IF(P114=E114,1) | R114: {=_xlfn.XLOOKUP(B114,'OA名单'!B:B,'OA名单'!F:F)} | S114: =IF(R114=F114,1) | T114: {=_xlfn.XLOOKUP(B114,'系统-原始（副本）'!A:A,'系统-原始（副本）'!B:B)} | U114: {=_xlfn.XLOOKUP(N114,'OA名单'!B:B,'OA名单'!E:E)} | V114: =IF(U114=G114,1)
B115: FD-092125 | C115: 26年 | D115: 7月 | E115: 产品供应部 | F115: 服务中心 | G115: 客服专员 | H115: 梁惠芬 | I115: 0.815 | J115: 82 | K115: =K115:J115% | L115: 1846 | M115: 1500 | N115: {=_xlfn.XLOOKUP(H115,'OA名单'!C:C,'OA名单'!B:B,1)} | O115: =IF(N115=B115,1) | P115: {=_xlfn.XLOOKUP(N115,'OA名单'!B:B,'OA名单'!G:G)} | Q115: =IF(P115=E115,1) | R115: {=_xlfn.XLOOKUP(B115,'OA名单'!B:B,'OA名单'!F:F)} | S115: =IF(R115=F115,1) | U115: {=_xlfn.XLOOKUP(N115,'OA名单'!B:B,'OA名单'!E:E)} | V115: =IF(U115=G115,1)
B116: FD-095372 | C116: 26年 | D116: 7月 | E116: 产品供应部 | F116: 服务中心 | G116: 客服专员 | H116: 欧彩珍 | I116: 0.82 | J116: 82 | K116: =K116:J116% | L116: 1230 | M116: 1500 | N116: {=_xlfn.XLOOKUP(H116,'OA名单'!C:C,'OA名单'!B:B,1)} | O116: =IF(N116=B116,1) | P116: {=_xlfn.XLOOKUP(N116,'OA名单'!B:B,'OA名单'!G:G)} | Q116: =IF(P116=E116,1) | R116: {=_xlfn.XLOOKUP(B116,'OA名单'!B:B,'OA名单'!F:F)} | S116: =IF(R116=F116,1) | T116: {=_xlfn.XLOOKUP(B116,'系统-原始（副本）'!A:A,'系统-原始（副本）'!B:B)} | U116: {=_xlfn.XLOOKUP(N116,'OA名单'!B:B,'OA名单'!E:E)} | V116: =IF(U116=G116,1)
B117: FD-099107 | C117: 26年 | D117: 7月 | E117: 产品供应部 | F117: 服务中心 | G117: 客服专员 | H117: 黄燕玲 | I117: 0.82 | J117: 82 | K117: =K117:J117% | L117: 1361 | M117: 1500 | N117: {=_xlfn.XLOOKUP(H117,'OA名单'!C:C,'OA名单'!B:B,1)} | O117: =IF(N117=B117,1) | P117: {=_xlfn.XLOOKUP(N117,'OA名单'!B:B,'OA名单'!G:G)} | Q117: =IF(P117=E117,1) | R117: {=_xlfn.XLOOKUP(B117,'OA名单'!B:B,'OA名单'!F:F)} | S117: =IF(R117=F117,1) | U117: {=_xlfn.XLOOKUP(N117,'OA名单'!B:B,'OA名单'!E:E)} | V117: =IF(U117=G117,1)
B118: FD-090598 | C118: 26年 | D118: 7月 | E118: 产品供应部 | F118: 服务中心 | G118: 客服专员 | H118: 仇碧颜 | I118: 0.886 | J118: 77 | K118: =K118:J118% | L118: 1350 | M118: 1500 | N118: {=_xlfn.XLOOKUP(H118,'OA名单'!C:C,'OA名单'!B:B,1)} | O118: =IF(N118=B118,1) | P118: {=_xlfn.XLOOKUP(N118,'OA名单'!B:B,'OA名单'!G:G)} | Q118: =IF(P118=E118,1) | R118: {=_xlfn.XLOOKUP(B118,'OA名单'!B:B,'OA名单'!F:F)} | S118: =IF(R118=F118,1) | U118: {=_xlfn.XLOOKUP(N118,'OA名单'!B:B,'OA名单'!E:E)} | V118: =IF(U118=G118,1)
B119: FD-097008 | C119: 26年 | D119: 7月 | E119: 产品供应部 | F119: 服务中心 | G119: 客服专员 | H119: 陈肖颜 | I119: 0.715 | J119: 72 | K119: =K119:J119% | L119: 1125 | M119: 1500 | N119: {=_xlfn.XLOOKUP(H119,'OA名单'!C:C,'OA名单'!B:B,1)} | O119: =IF(N119=B119,1) | P119: {=_xlfn.XLOOKUP(N119,'OA名单'!B:B,'OA名单'!G:G)} | Q119: =IF(P119=E119,1) | R119: {=_xlfn.XLOOKUP(B119,'OA名单'!B:B,'OA名单'!F:F)} | S119: =IF(R119=F119,1) | U119: {=_xlfn.XLOOKUP(N119,'OA名单'!B:B,'OA名单'!E:E)} | V119: =IF(U119=G119,1)
B120: FD-099682 | C120: 26年 | D120: 7月 | E120: 产品供应部 | F120: 服务中心 | G120: 客服专员 | H120: 何卫珊 | I120: 0.7 | J120: 70 | K120: =K120:J120% | L120: 1050 | M120: 1200 | N120: {=_xlfn.XLOOKUP(H120,'OA名单'!C:C,'OA名单'!B:B,1)} | O120: =IF(N120=B120,1) | P120: {=_xlfn.XLOOKUP(N120,'OA名单'!B:B,'OA名单'!G:G)} | Q120: =IF(P120=E120,1) | R120: {=_xlfn.XLOOKUP(B120,'OA名单'!B:B,'OA名单'!F:F)} | S120: =IF(R120=F120,1) | U120: {=_xlfn.XLOOKUP(N120,'OA名单'!B:B,'OA名单'!E:E)} | V120: =IF(U120=G120,1)
B121: FD-095375 | C121: 26年 | D121: 7月 | E121: 产品供应部 | F121: 服务中心 | G121: 客服专员 | H121: 巫超雄 | I121: 0.7 | J121: 70 | K121: =K121:J121% | L121: 1284 | M121: 1500 | N121: {=_xlfn.XLOOKUP(H121,'OA名单'!C:C,'OA名单'!B:B,1)} | O121: =IF(N121=B121,1) | P121: {=_xlfn.XLOOKUP(N121,'OA名单'!B:B,'OA名单'!G:G)} | Q121: =IF(P121=E121,1) | R121: {=_xlfn.XLOOKUP(B121,'OA名单'!B:B,'OA名单'!F:F)} | S121: =IF(R121=F121,1) | U121: {=_xlfn.XLOOKUP(N121,'OA名单'!B:B,'OA名单'!E:E)} | V121: =IF(U121=G121,1)
B122: OD-008682 | C122: 26年 | D122: 7月 | E122: 品牌营销部 | F122: 营销中心J | G122: 营销策划 | H122: 肖绮雯 | I122: 0.7 | J122: 70 | K122: =K122:J122% | L122: 1050 | M122: 1500 | N122: {=_xlfn.XLOOKUP(H122,'OA名单'!C:C,'OA名单'!B:B,1)} | O122: =IF(N122=B122,1) | P122: {=_xlfn.XLOOKUP(N122,'OA名单'!B:B,'OA名单'!G:G)} | Q122: =IF(P122=E122,1) | R122: {=_xlfn.XLOOKUP(B122,'OA名单'!B:B,'OA名单'!F:F)} | S122: =IF(R122=F122,1) | T122: {=_xlfn.XLOOKUP(B122,'系统-原始（副本）'!A:A,'系统-原始（副本）'!B:B)} | U122: {=_xlfn.XLOOKUP(N122,'OA名单'!B:B,'OA名单'!E:E)} | V122: =IF(U122=G122,1)
B123: FD-096836 | C123: 26年 | D123: 7月 | E123: 产品供应部 | F123: 服务中心 | G123: 客服专员 | H123: 邓小兰 | I123: 1 | J123: 67 | K123: =K123:J123% | L123: 900 | M123: 1500 | N123: {=_xlfn.XLOOKUP(H123,'OA名单'!C:C,'OA名单'!B:B,1)} | O123: =IF(N123=B123,1) | P123: {=_xlfn.XLOOKUP(N123,'OA名单'!B:B,'OA名单'!G:G)} | Q123: =IF(P123=E123,1) | R123: {=_xlfn.XLOOKUP(B123,'OA名单'!B:B,'OA名单'!F:F)} | S123: =IF(R123=F123,1) | U123: {=_xlfn.XLOOKUP(N123,'OA名单'!B:B,'OA名单'!E:E)} | V123: =IF(U123=G123,1)
B124: FD-093331 | C124: 26年 | D124: 7月 | E124: 产品供应部 | F124: 服务中心 | G124: 客服专员 | H124: 甘燕平 | I124: 0.58 | J124: 58 | K124: =K124:J124% | L124: 680 | M124: 1200 | N124: {=_xlfn.XLOOKUP(H124,'OA名单'!C:C,'OA名单'!B:B,1)} | O124: =IF(N124=B124,1) | P124: {=_xlfn.XLOOKUP(N124,'OA名单'!B:B,'OA名单'!G:G)} | Q124: =IF(P124=E124,1) | R124: {=_xlfn.XLOOKUP(B124,'OA名单'!B:B,'OA名单'!F:F)} | S124: =IF(R124=F124,1) | T124: {=_xlfn.XLOOKUP(B124,'系统-原始（副本）'!A:A,'系统-原始（副本）'!B:B)} | U124: {=_xlfn.XLOOKUP(N124,'OA名单'!B:B,'OA名单'!E:E)} | V124: =IF(U124=G124,1)
B125: FD-090581 | C125: 26年 | D125: 7月 | E125: 产品供应部 | F125: 服务中心 | G125: 客服专员 | H125: 梁嘉琪 | I125: 0.515 | J125: 52 | K125: =K125:J125% | L125: 714 | M125: 1200 | N125: {=_xlfn.XLOOKUP(H125,'OA名单'!C:C,'OA名单'!B:B,1)} | O125: =IF(N125=B125,1) | P125: {=_xlfn.XLOOKUP(N125,'OA名单'!B:B,'OA名单'!G:G)} | Q125: =IF(P125=E125,1) | R125: {=_xlfn.XLOOKUP(B125,'OA名单'!B:B,'OA名单'!F:F)} | S125: =IF(R125=F125,1) | U125: {=_xlfn.XLOOKUP(N125,'OA名单'!B:B,'OA名单'!E:E)} | V125: =IF(U125=G125,1)
B126: FD-098475 | C126: 26年 | D126: 7月 | E126: 产品供应部 | F126: 服务中心 | G126: 客服专员 | H126: 陆贤慧 | I126: 0.46 | J126: 46 | K126: =K126:J126% | L126: 690 | M126: 1200 | N126: {=_xlfn.XLOOKUP(H126,'OA名单'!C:C,'OA名单'!B:B,1)} | O126: =IF(N126=B126,1) | P126: {=_xlfn.XLOOKUP(N126,'OA名单'!B:B,'OA名单'!G:G)} | Q126: =IF(P126=E126,1) | R126: {=_xlfn.XLOOKUP(B126,'OA名单'!B:B,'OA名单'!F:F)} | S126: =IF(R126=F126,1) | U126: {=_xlfn.XLOOKUP(N126,'OA名单'!B:B,'OA名单'!E:E)} | V126: =IF(U126=G126,1)
B127: FD-093313 | C127: 26年 | D127: 7月 | E127: 产品供应部 | F127: 服务中心 | G127: 客服专员 | H127: 陈玉夏 | I127: 0.425 | J127: 42.5 | K127: =K127:J127% | L127: 630 | M127: 1200 | N127: {=_xlfn.XLOOKUP(H127,'OA名单'!C:C,'OA名单'!B:B,1)} | O127: =IF(N127=B127,1) | P127: {=_xlfn.XLOOKUP(N127,'OA名单'!B:B,'OA名单'!G:G)} | Q127: =IF(P127=E127,1) | R127: {=_xlfn.XLOOKUP(B127,'OA名单'!B:B,'OA名单'!F:F)} | S127: =IF(R127=F127,1) | U127: {=_xlfn.XLOOKUP(N127,'OA名单'!B:B,'OA名单'!E:E)} | V127: =IF(U127=G127,1)
B128: FD-091587 | C128: 26年 | D128: 7月 | E128: 产品供应部 | F128: 服务中心 | G128: 客服专员 | H128: 李美美 | I128: 0.682 | J128: 23.2 | K128: =K128:J128% | L128: 768 | M128: 1200 | N128: {=_xlfn.XLOOKUP(H128,'OA名单'!C:C,'OA名单'!B:B,1)} | O128: =IF(N128=B128,1) | P128: {=_xlfn.XLOOKUP(N128,'OA名单'!B:B,'OA名单'!G:G)} | Q128: =IF(P128=E128,1) | R128: {=_xlfn.XLOOKUP(B128,'OA名单'!B:B,'OA名单'!F:F)} | S128: =IF(R128=F128,1) | U128: {=_xlfn.XLOOKUP(N128,'OA名单'!B:B,'OA名单'!E:E)} | V128: =IF(U128=G128,1)
...

Sheet OA名单
A1: 旧工号 | B1: 新工号 | C1: 姓名 | D1: 岗位类型 | E1: 岗位 | F1: 中心 | G1: 部门 | H1: 绩效基数
A2: FD-11799 | B2: FD-094322 | C2: 卢柳春 | D2: 正式 | E2: 库存文员 | F2: 仓配中心 | G2: 产品供应部 | H2: 800
A3: FD-9138 | B3: FD-099139 | C3: 刘创温 | D3: 正式 | E3: 仓管员 | F3: 仓配中心 | G3: 产品供应部 | H3: 800
A4: FD-31624 | B4: FD-097656 | C4: 卢彩琴 | D4: 正式 | E4: 打包员 | F4: 仓配中心 | G4: 产品供应部 | H4: 计件制
A5: FD-17073 | B5: FD-098416 | C5: 李洁容 | D5: 正式 | E5: 打包员 | F5: 仓配中心 | G5: 产品供应部 | H5: 计件制
A6: FD-17439 | B6: FD-099013 | C6: 谢金连 | D6: 正式 | E6: 打包员 | F6: 仓配中心 | G6: 产品供应部 | H6: 计件制
A7: FD-17850 | B7: FD-095817 | C7: 黎彩霞 | D7: 正式 | E7: 打包员 | F7: 仓配中心 | G7: 产品供应部 | H7: 计件制
A8: FD-0732 | B8: FD-093666 | C8: 张春霞 | D8: 正式 | E8: 打包员 | F8: 仓配中心 | G8: 产品供应部 | H8: 计件制
A9: FD-23798 | B9: FD-092627 | C9: 曾利兰 | D9: 正式 | E9: 打包员 | F9: 仓配中心 | G9: 产品供应部 | H9: 计件制
A10: FD-31041 | B10: FD-098846 | C10: 邹文君 | D10: 正式 | E10: 打包员 | F10: 仓配中心 | G10: 产品供应部 | H10: 计件制
A11: FD-31250 | B11: FD-095261 | C11: 梁静怡 | D11: 正式 | E11: 打包员 | F11: 仓配中心 | G11: 产品供应部 | H11: 计件制
A12: FD-33116 | B12: FD-097635 | C12: 戚少娟 | D12: 正式 | E12: 打单员 | F12: 仓配中心 | G12: 产品供应部 | H12: 800
A13: FD-2114 | B13: FD-097824 | C13: 陈良玉 | D13: 正式 | E13: 打包员 | F13: 仓配中心 | G13: 产品供应部 | H13: 计件制
A14: FD-25822 | B14: FD-074553 | C14: 王娜 | D14: 正式 | E14: 督导 | F14: 渠道运作中心 | G14: 线下渠道部 | H14: 3000
A15: FD-32339 | B15: FD-078246 | C15: 张婷 | D15: 正式 | E15: 督导 | F15: 渠道运作中心 | G15: 线下渠道部 | H15: 3000
A16: FD-10138 | B16: FD-017849 | C16: 倪晓虹 | D16: 正式 | E16: 干部管理高级经理 | F16: 干部管理中心 | G16: 总经办 | H16: 0
A17: FD-11738 | B17: FD-013695 | C17: 钟宝玲 | D17: 正式 | E17: 干部管理经理 | F17: 干部管理中心 | G17: 总经办 | H17: 1500
A18: FD-36925 | B18: FD-155034 | C18: 蒋欣 | D18: 正式 | E18: 培训讲师 | F18: 未分中心 | G18: 凡岛大学 | H18: 2000
A19: FD-8593 | B19: FD-014164 | C19: 黄心河 | D19: 正式 | E19: 投资经理 | F19: 投资模块 | G19: 总经办 | H19: 3000
A20: FD-28166 | B20: FD-018313 | C20: 侯骏雄 | D20: 正式 | E20: PMO | F20: 创业模块 | G20: 总经办 | H20: 0
A21: FD-22075 | B21: FD-017789 | C21: 靳嘉敏 | D21: 正式 | E21: 总助主管 | F21: 总助模块 | G21: 总经办 | H21: 0
A22: FD-44236 | B22: FD-024031 | C22: 练美好 | D22: 正式 | E22: 营销高级经理 | F22: 营销中心D | G22: 品牌营销部 | H22: 5000
A23: FD-49785 | B23: FD-010340 | C23: 王伊瑄 | D23: 正式 | E23: 总经理助理 | F23: 总助模块 | G23: 总经办 | H23: 5000
A24: FD-0002 | B24: FD-174370 | C24: 王带娣 | D24: 正式 | E24: 财务高级经理 | F24: 财资管理中心 | G24: 财务部 | H24: 3000
A25: FD-21584 | B25: FD-172676 | C25: 邓燕霞 | D25: 正式 | E25: 总账会计经理 | F25: 财资管理中心 | G25: 财务部 | H25: 3000
... A155: FD-37265 | B155: FD-098396 | C155: 唐婉泳 | D155: 正式 | E155: 备货文员 | F155: 仓配中心 | G155: 产品供应部 | H155: 800
A156: FD-30891 | B156: FD-095646 | C156: 黄正发 | D156: 正式 | E156: 备货员 | F156: 仓配中心 | G156: 产品供应部 | H156: 计件制
A157: FD-32528 | B157: FD-099558 | C157: 何灿威 | D157: 正式 | E157: 仓管员 | F157: 仓配中心 | G157: 产品供应部 | H157: 800
A158: FD-17074 | B158: FD-098343 | C158: 李国安 | D158: 正式 | E158: 叉车司机 | F158: 仓配中心 | G158: 产品供应部 | H158: 900
A159: FD-27334 | B159: FD-096601 | C159: 黄考联 | D159: 正式 | E159: 叉车司机 | F159: 仓配中心 | G159: 产品供应部 | H159: 900
A160: FD-7115 | B160: FD-091488 | C160: 杨文锦 | D160: 正式 | E160: 装卸工 | F160: 仓配中心 | G160: 产品供应部 | H160: 1000
A161: FD-11554 | B161: FD-097984 | C161: 梁佰新 | D161: 正式 | E161: 装卸工 | F161: 仓配中心 | G161: 产品供应部 | H161: 1000
A162: FD-16238 | B162: FD-097088 | C162: 刘朝家 | D162: 正式 | E162: 装卸工 | F162: 仓配中心 | G162: 产品供应部 | H162: 1000
A163: FD-23735 | B163: FD-096154 | C163: 曾辉旺 | D163: 正式 | E163: 组长 | F163: 仓配中心 | G163: 产品供应部 | H163: 2000
A164: FD-26549 | B164: FD-092060 | C164: 邓进华 | D164: 正式 | E164: 组长 | F164: 仓配中心 | G164: 产品供应部 | H164: 1100
A165: FD-7389 | B165: FD-096932 | C165: 商思莹 | D165: 正式 | E165: 组长 | F165: 仓配中心 | G165: 产品供应部 | H165: 1100
A166: FD-14911 | B166: FD-098074 | C166: 贺强 | D166: 正式 | E166: 组长 | F166: 仓配中心 | G166: 产品供应部 | H166: 1100
A167: FD-25089 | B167: FD-097779 | C167: 曾振华 | D167: 正式 | E167: 组长 | F167: 仓配中心 | G167: 产品供应部 | H167: 1100
A168: FD-29306 | B168: FD-091473 | C168: 郑靖华 | D168: 正式 | E168: 配送经理 | F168: 仓配中心 | G168: 产品供应部 | H168: 2000
... A170: FD-16780 | B170: FD-096977 | C170: 廖树清 | D170: 正式 | E170: 行政专员 | F170: 从化中心 | G170: 人资行政部 | H170: 800
A171: FD-20375 | B171: FD-093777 | C171: 赖翠香 | D171: 正式 | E171: 打包员 | F171: 仓配中心 | G171: 产品供应部 | H171: 计件制
A172: FD-27461 | B172: FD-093761 | C172: 黎敏娟 | D172: 正式 | E172: 打包员 | F172: 仓配中心 | G172: 产品供应部 | H172: 计件制
A173: FD-28089 | B173: FD-099520 | C173: 陆彩群 | D173: 正式 | E173: 售后员 | F173: 仓配中心 | G173: 产品供应部 | H173: 1100
A174: FD-16124 | B174: FD-092954 | C174: 范金凤 | D174: 正式 | E174: 组长 | F174: 仓配中心 | G174: 产品供应部 | H174: 1100
A175: FD-17731 | B175: FD-099237 | C175: 肖青霞 | D175: 正式 | E175: 组长 | F175: 仓配中心 | G175: 产品供应部 | H175: 1100
A176: FD-16123 | B176: FD-099978 | C176: 苏艳寒 | D176: 正式 | E176: 组长 | F176: 仓配中心 | G176: 产品供应部 | H176: 1100
A177: FD-15807 | B177: FD-093712 | C177: 曾美金 | D177: 正式 | E177: 组长 | F177: 仓配中心 | G177: 产品供应部 | H177: 1100
A178: FD-0106 | B178: FD-097394 | C178: 杨雄贤 | D178: 正式 | E178: 质量经理 | F178: 生产中心 | G178: 产品供应部 | H178: 2500
A179: FD-30491 | B179: FD-092271 | C179: 欧阳妙诗 | D179: 正式 | E179: PMC专员 | F179: 生产中心 | G179: 产品供应部 | H179: 1000
A180: FD-16239 | B180: FD-098141 | C180: 陈敏婷 | D180: 正式 | E180: QC组长 | F180: 生产中心 | G180: 产品供应部 | H180: 1000
A181: FD-33734 | B181: FD-090515 | C181: 李德荣 | D181: 正式 | E181: 备料员 | F181: 生产中心 | G181: 产品供应部 | H181: 1000
A182: FD-40249 | B182: FD-099594 | C182: 黄云凤 | D182: 正式 | E182: 备料员 | F182: 生产中心 | G182: 产品供应部 | H182: 1000
A183: FD-48279 | B183: FD-098265 | C183: 李昔培 | D183: 正式 | E183: 备料员 | F183: 生产中心 | G183: 产品供应部 | H183: 1000
A184: FD-29658 | B184: FD-098982 | C184: 龙鉴彬 | D184: 正式 | E184: 组长 | F184: 生产中心 | G184: 产品供应部 | H184: 1000
... A765: FD-58618 | B765: SX-008778 | C765: 肖轶品 | D765: 实习生 | E765: 投资分析实习生 | F765: 投资模块 | G765: 总经办 | H765: 0
A766: FD-58619 | B766: SX-001864 | C766: 廖亦君 | D766: 实习生 | E766: 商务实习生 | F766: 先锋中心 | G766: 市场拓展部 | H766: 上限500
A767: FD-58620 | B767: SX-005365 | C767: 何炜彤 | D767: 实习生 | E767: 财务实习生 | F767: 财资管理中心 | G767: 财务部 | H767: 0
A768: FD-58621 | B768: FD-034976 | C768: 王文欢 | D768: 试用期 | E768: 主播 | F768: 直播A中心 | G768: 广告策划部 | H768: 10000
A769: FD-58622 | B769: FD-048165 | C769: 黎柳琴 | D769: 实习期 | E769: 直播助理 | F769: 直播中心 | G769: 品牌创意部 | H769: 1000
A770: FD-58623 | B770: FD-010463 | C770: 李静晗 | D770: 实习期 | E770: 总监助理 | F770: 未分中心 | G770: AI效率流程部 | H770: 3000
A771: FD-58624 | B771: FD-092488 | C771: 林杜明 | D771: 实习期 | E771: 管培生 | F771: 计划中心 | G771: 产品供应部 | H771: 5000
A772: FD-58625 | B772: FD-050705 | C772: 谷春炎 | D772: 实习期 | E772: 管培生 | F772: 资源开拓中心 | G772: 市场拓展部 | H772: 5000
A773: FD-58626 | B773: FD-158124 | C773: 张韶涵 | D773: 实习期 | E773: 管培生 | F773: 综合招聘中心 | G773: 人资行政部 | H773: 5000
A774: FD-58627 | B774: FD-221053 | C774: 陈洪彪 | D774: 实习期 | E774: AI产品经理 | F774: AI效率流程C中心 | G774: AI效率流程部 | H774: 3400
A775: FD-58628 | B775: SX-004169 | C775: 陈桂炼 | D775: 实习生 | E775: 品控实习生 | F775: 品控中心 | G775: 产品供应部 | H775: 0
A776: FD-58629 | B776: SX-004477 | C776: 林灿涛 | D776: 实习生 | E776: 品控实习生 | F776: 品控中心 | G776: 产品供应部 | H776: 0
A777: FD-58633 | B777: FD-097315 | C777: 刘佳俊 | D777: 实习期 | E777: 品控经理 | F777: 品控中心 | G777: 产品供应部 | H777: 2000
A778: FD-58603 | B778: SX-008692 | C778: 梁芷莹 | D778: 实习生 | E778: 商务实习生 | F778: 先锋中心 | G778: 市场拓展部 | H778: 上限500
A779: FD-58605 | B779: FD-031647 | C779: 刘思 | D779: 试用期 | E779: 视频编辑 | F779: 营销A中心 | G779: 广告策划部 | H779: 2000
A780: FD-58606 | B780: FD-221172 | C780: 刘凯 | D780: 实习期 | E780: AI工程师 | F780: AI效率流程F中心 | G780: AI效率流程部 | H780: 5000
A781: FD-58610 | B781: FD-023018 | C781: 陈广聪 | D781: 实习期 | E781: 视频编辑 | F781: 视频中心 | G781: 品牌营销部 | H781: 2000
A782: FD-58573 | B782: FD-043242 | C782: 刘韵莹 | D782: 试用期 | E782: 直播助理 | F782: 直播中心 | G782: 品牌创意部 | H782: 1000
A783: FD-58575 | B783: FD-025819 | C783: 杨凯琳 | D783: 试用期 | E783: 创意经理 | F783: 品牌创意中心 | G783: 品牌营销部 | H783: 5000
A784: FD-58576 | B784: FD-176987 | C784: 王柄钦 | D784: 试用期 | E784: 管培生 | F784: 财资管理中心 | G784: 财务部 | H784: 5000
A785: FD-58577 | B785: FD-062950 | C785: 张雪瑶 | D785: 试用期 | E785: 管培生 | F785: 赫系渠道B中心 | G785: 电商发展部 | H785: 5000
A786: FD-58578 | B786: FD-062816 | C786: 洪若羽 | D786: 实习期 | E786: 管培生 | F786: WIS渠道B中心 | G786: 电商发展部 | H786: 5000
A787: FD-58579 | B787: FD-046238 | C787: 廖歆玥 | D787: 实习期 | E787: 营销经理 | F787: 赫系营销A中心 | G787: 品牌创意部 | H787: 5000
A788: FD-58580 | B788: FD-026345 | C788: 田智文 | D788: 实习期 | E788: 营销经理 | F788: 营销中心C | G788: 品牌营销部 | H788: 5000
A789: FD-58581 | B789: FD-060430 | C789: 蒋盈颖 | D789: 实习期 | E789: 管培生 | F789: 达播中心 | G789: 电商发展部 | H789: 5000
A790: FD-58582 | B790: FD-061817 | C790: 付文雅 | D790: 实习期 | E790: 管培生 | F790: 达播中心 | G790: 电商发展部 | H790: 5000
... A798: FD-58569 | B798: FD-070208 | C798: 谭小慧 | D798: 试用期 | E798: 大客户商务经理 | F798: KONO-KONO销售B中心 | G798: 线下渠道部（KONO） | H798: 5000
A799: FD-58552 | B799: SX-001600 | C799: 张文珂 | D799: 实习生 | E799: 商务实习生 | F799: 明星中心 | G799: 市场拓展部 | H799: 上限500
A800: FD-58554 | B800: FD-039808 | C800: 黄智扬 | D800: 试用期 | E800: 信息流优化师 | F800: 营销A中心 | G800: 广告策划部 | H800: 3000
A801: FD-58548 | B801: FD-093313 | C801: 陈玉夏 | D801: 试用期 | E801: 客服专员 | F801: 服务中心 | G801: 产品供应部 | H801: 1200
A802: FD-58861 | B802: FD-049772 | C802: 陈月华 | D802: 试用期 | E802: 营销经理 | F802: 赫系营销D中心 | G802: 品牌创意部 | H802: 5000
A803: FD-58843 | B803: FD-057591 | C803: 程宇 | D803: 试用期 | E803: 商务PR | F803: 先锋中心 | G803: 市场拓展部 | H803: 2000
A804: FD-58844 | B804: SX-006993 | C804: 庄茜妍 | D804: 实习生 | E804: 商务实习生 | F804: 先锋中心 | G804: 市场拓展部 | H804: 上限500
A805: FD-58845 | B805: SQ-002976 | C805: 李欣怡 | D805: 实习生 | E805: 电商实习生 | F805: WIS渠道B中心 | G805: 电商发展部 | H805: 0
A806: FD-58846 | B806: FD-077452 | C806: 张渘浚 | D806: 试用期 | E806: 大客户商务经理 | F806: KONO-KONO销售B中心 | G806: 线下渠道部（KONO） | H806: 5000
A807: FD-58847 | B807: FD-067782 | C807: 劳浩桓 | D807: 试用期 | E807: 商务PR | F807: 达播中心 | G807: 电商发展部 | H807: 2000
A808: FD-58848 | B808: FD-070685 | C808: 石家硕 | D808: 实习期 | E808: 商务经理 | F808: 未分中心 | G808: 线下渠道部 | H808: 6000
A809: FD-58849 | B809: SQ-008969 | C809: 姚亿涵 | D809: 实习生 | E809: COE实习生 | F809: 组织发展中心 | G809: 人资行政部 | H809: 0
A810: FD-58850 | B810: SX-009012 | C810: 赵晗 | D810: 实习生 | E810: 市场开拓实习生 | F810: 创业模块 | G810: 总经办 | H810: 0
A811: FD-58852 | B811: SQ-005463 | C811: 曾佳佳 | D811: 实习生 | E811: 研发实习生 | F811: 未分中心 | G811: 凡岛研究院 | H811: 0
A812: FD-58854 | B812: FD-049969 | C812: 李婕 | D812: 实习期 | E812: 直播助理 | F812: 直播中心 | G812: 品牌创意部 | H812: 1000
A813: FD-58857 | B813: FD-028150 | C813: 陈荟聿 | D813: 实习期 | E813: 主播 | F813: 直播中心 | G813: 品牌营销部 | H813: 10000
A814: FD-58859 | B814: FD-038309 | C814: 钟泽纯 | D814: 实习期 | E814: 直播助理 | F814: 直播A中心 | G814: 广告策划部 | H814: 1000
A815: FD-58831 | B815: FD-065580 | C815: 冉光讯 | D815: 试用期 | E815: 电商经理 | F815: WIS渠道B中心 | G815: 电商发展部 | H815: 5000
A816: FD-58832 | B816: SX-000211 | C816: 任泽恩琦 | D816: 实习生 | E816: 商务实习生 | F816: 先锋中心 | G816: 市场拓展部 | H816: 上限500
A817: FD-58833 | B817: FD-030900 | C817: 肖烨涛 | D817: 试用期 | E817: 营销经理 | F817: 创新B中心 | G817: 广告策划部 | H817: 5000
...
